Workbook

Sheet Stock Selection
A1: 1. BRAC Bank
A2: Year | B2: P/E | C2: NAV | D2: ROA | E2: ROE | F2: NPM | G2: EPS
A3: 2021 | B3: 14.09 | C3: 30.24 | D3: 0.0131 | E3: 0.1038 | F3: 0.1901 | G3: 2.39
A4: 2022 | B4: 9.55 | C4: 32.37 | D4: 0.0102 | E4: 0.0777 | F4: 0.168 | G4: 2.63
A5: 2023 | B5: 7.57 | C5: 35.5 | D5: 0.0111 | E5: 0.1192 | F5: 0.1741 | G5: 3.32
A6: 2024 | B6: 7.05 | C6: 42.09 | D6: 0.0146 | E6: 0.1743 | F6: 0.2027 | G6: 5.37
A7: 2025 | B7: 6.92 | C7: 55.4 | D7: 0.0152 | E7: 0.2006 | F7: 0.2311 | G7: 7.93
A9: 2. NCC Bank
A10: Year | B10: P/E | C10: NAV | D10: ROA | E10: ROE | F10: NPM | G10: EPS
A11: 2021 | B11: 5.95 | C11: 21.11 | D11: 0.95% | E11: 11.72% | F11: 22% | G11: 2.37
A12: 2022 | B12: 5.52 | C12: 20.86 | D12: 0.87% | E12: 11.41% | F12: 20.7% | G12: 2.38
A13: 2023 | B13: 6.33 | C13: 21.82 | D13: 0.72% | E13: 9.48% | F13: 16% | G13: 2.07
A14: 2024 | B14: 2.74 | C14: 22.37 | D14: 1.26% | E14: 16.2% | F14: 26.1% | G14: 2.1
A15: 2025 | B15: 2.84 | C15: 27.2 | D15: 1.19% | E15: 15.78% | F15: 25.4% | G15: 4.29
A17: 3. IPDC
A18: Year | B18: P/E | C18: NAV | D18: ROA | E18: ROE | F18: NPM | G18: EPS
A19: 2021 | B19: 16.26 | C19: 14.79 | D19: 0.0104 | E19: 0.1387 | F19: 0.257 | G19: 2.05
A20: 2022 | B20: 23.72 | C20: 15.84 | D20: 0.0104 | E20: 0.1324 | F20: 0.29 | G20: 2.1
A21: 2023 | B21: 62.33 | C21: 15.72 | D21: 0.0037 | E21: 0.0508 | F21: 0.12 | G21: 0.8
A22: 2024 | B22: 19.63 | C22: 16.08 | D22: 0.0041 | E22: 0.0526 | F22: 0.113 | G22: 0.85
A23: 2025 | B23: 16.98 | C23: 17 | D23: 0.0046 | E23: 0.0624 | F23: 0.132 | G23: 1.06
A25: 4. DBH Finance PLC. (DBH)
A26: Year | B26: P/E | C26: NAV | D26: ROA | E26: ROE | F26: NPM | G26: EPS
A27: 2021 | B27: 13.09 | C27: 35.71 | D27: 0.0173 | E27: 0.1441 | F27: 0.421 | G27: 5.15
A28: 2022 | B28: 11.09 | C28: 39.37 | D28: 0.0165 | E28: 0.1274 | F28: 0.477 | G28: 5.01
A29: 2023 | B29: 11.46 | C29: 42.78 | D29: 0.0146 | E29: 0.1134 | F29: 0.454 | G29: 4.85
A30: 2024 | B30: 7.67 | C30: 46.33 | D30: 0.015 | E30: 0.1074 | F30: 0.398 | G30: 4.97
A31: 2025 | B31: 7.38 | C31: 49.55 | D31: 0.0138 | E31: 0.0947 | F31: 0.381 | G31: 4.69
A33: 5. Paramount
A34: Year | B34: P/E | C34: NAV | D34: ROA | E34: ROE | F34: NPM | G34: EPS
A35: 2021 | B35: 24.22 | C35: 25.26 | D35: 0.0783 | E35: 0.1198 | F35: 0.3217 | G35: 3.03
A36: 2022 | B36: 23.8 | C36: 25.82 | D36: 0.0463 | E36: 0.0724 | F36: 0.2228 | G36: 1.87
A37: 2023 | B37: 32.77 | C37: 26.56 | D37: 0.0415 | E37: 0.0653 | F37: 0.2014 | G37: 1.73
A38: 2024 | B38: 18.5 | C38: 27.25 | D38: 0.0498 | E38: 0.0817 | F38: 0.2041 | G38: 2.23
A39: 2025 | B39: 19.65 | C39: 28.16 | D39: 0.0497 | E39: 0.0779 | F39: 0.2029 | G39: 2.19
A41: 6. Asia Pecific General Insurance PLC
A42: Year | B42: P/E | C42: NAV | D42: ROA | E42: ROE | F42: NPM | G42: EPS
A43: 2021 | B43: 29.39 | C43: 21.96 | D43: 0.0694 | E43: 0.1061 | F43: 0.2501 | G43: 2.33
A44: 2022 | B44: 17.59 | C44: 22.53 | D44: 0.068 | E44: 0.105 | F44: 0.2274 | G44: 2.37
A45: 2023 | B45: 24.23 | C45: 23.1 | D45: 0.0564 | E45: 0.0895 | F45: 0.17 | G45: 2.07
A46: 2024 | B46: 16.89 | C46: 23.8 | D46: 0.0498 | E46: 0.0796 | F46: 0.1828 | G46: 1.89
A47: 2025 | B47: 12.17 | C47: 25.29 | D47: 0.0581 | E47: 0.0991 | F47: 0.1568 | G47: 2.51
A49: 7. Lovello
A50: Year | B50: P/E | C50: NAV | D50: ROA | E50: ROE | F50: NPM | G50: EPS
A51: 2021 | B51: 25.05 | C51: 10.88 | D51: 0.0442 | E51: 0.089 | F51: 0.1117 | G51: 1.22
A52: 2022 | B52: 29.29 | C52: 11.16 | D52: 0.0531 | E52: 0.1109 | F52: 0.1266 | G52: 1.24
A53: 2023 | B53: 30.6 | C53: 11.2 | D53: 0.0401 | E53: 0.0957 | F53: 0.1115 | G53: 1.07
A54: 2024 | B54: 60.45 | C54: 10.74 | D54: 0.0357 | E54: 0.1155 | F54: 0.1227 | G54: 1.24
A55: 2025 | B55: 59.87 | C55: 11.44 | D55: 0.0396 | E55: 0.1371 | F55: 0.1338 | G55: 1.57
A57: 8. Finefood
A58: Year | B58: P/E | C58: NAV | D58: ROA | E58: ROE | F58: NPM | G58: EPS
A59: 2021 | B59: — | C59: 10.48 | D59: -0.0067 | E59: -0.0105 | F59: -0.0267 | G59: -0.11
A60: 2022 | B60: 1848.08 | C60: 10.49 | D60: 0.0043 | E60: 0.0023 | F60: 0.0057 | G60: 0.02
A61: 2023 | B61: 1790.91 | C61: 10.45 | D61: 0.0057 | E61: 0.0062 | F61: 0.0149 | G61: 0.07
A62: 2024 | B62: 186.86 | C62: 11.2 | D62: 0.0577 | E62: 0.0808 | F62: 0.1682 | G62: 0.88
A63: 2025 | B63: 56.6 | C63: 14.58 | D63: 0.2184 | E63: 0.3223 | F63: 0.4917 | G63: 4.18
A65: 9. Olympic Industries
A66: Year | B66: P/E | C66: NAV | D66: ROA | E66: ROE | F66: NPM | G66: EPS
A67: 2021 | B67: 15.25 | C67: 47.64 | D67: 0.1152 | E67: 0.2331 | F67: 0.113 | G67: 10.19
A68: 2022 | B68: 17.1 | C68: 43.94 | D68: 0.0638 | E68: 0.1296 | F68: 0.0562 | G68: 6.03
A69: 2023 | B69: 13.82 | C69: 44.1 | D69: 0.0919 | E69: 0.1605 | F69: 0.0603 | G69: 7.78
A70: 2024 | B70: 12.65 | C70: 45.67 | D70: 0.0974 | E70: 0.1774 | F70: 0.0707 | G70: 9.17
A71: 2025 | B71: 14.43 | C71: 52.37 | D71: 0.0901 | E71: 0.1739 | F71: 0.0725 | G71: 10.06
A73: 10. Index Agro
A74: Year | B74: P/E | C74: NAV | D74: ROA | E74: ROE | F74: NPM | G74: EPS
A75: 2021 | B75: 22.07 | C75: 55.48 | D75: 0.0462 | E75: 0.0845 | F75: 0.0633 | G75: 5.37
A76: 2022 | B76: 20.05 | C76: 59.94 | D76: 0.0406 | E76: 0.0809 | F76: 0.0579 | G76: 4.85
A77: 2023 | B77: 19.85 | C77: 73.32 | D77: 0.0342 | E77: 0.0678 | F77: 0.0589 | G77: 4.97
A78: 2024 | B78: 11.72 | C78: 78.21 | D78: 0.0372 | E78: 0.0668 | F78: 0.0605 | G78: 5.22
A79: 2025 | B79: 11.3 | C79: 81.66 | D79: 0.0363 | E79: 0.0644 | F79: 0.0592 | G79: 5.26
A81: 11. Apex footwear Ltd.
A82: Year | B82: P/E | C82: NAV | D82: ROA | E82: ROE | F82: NPM | G82: EPS
A83: 2021 | B83: 25.14 | C83: 147.02 | D83: 0.006 | E83: 0.0365 | F83: 0.009 | G83: 5.36
A84: 2022 | B84: 23.2 | C84: 152.06 | D84: 0.0068 | E84: 0.0463 | F84: 0.0107 | G84: 7.03
A85: 2023 | B85: 24.44 | C85: 158.47 | D85: 0.0068 | E85: 0.0537 | F85: 0.0101 | G85: 8.5
A86: 2024 | B86: 19.35 | C86: 345.04 | D86: 0.0062 | E86: 0.026 | F86: 0.0118 | G86: 8.98
A87: 2025 | B87: 23.59 | C87: 349.41 | D87: 0.0044 | E87: 0.0197 | F87: 0.0076 | G87: 6.9
A89: 12. Confidence Cement
A90: Year | B90: P/E | C90: NAV | D90: ROA | E90: ROE | F90: NPM | G90: EPS
A91: 2021 | B91: 8.51 | C91: 66.3 | D91: 0.108 | E91: 0.2169 | F91: 0.2686 | G91: 14.38
A92: 2022 | B92: 78.67 | C92: 65.09 | D92: 0.0083 | E92: 0.0183 | F92: 0.0253 | G92: 1.19
A93: 2023 | B93: 26.92 | C93: 66.57 | D93: 0.0202 | E93: 0.0473 | F93: 0.0596 | G93: 3.15
A94: 2024 | B94: 7.76 | C94: 74.77 | D94: 0.0527 | E94: 0.1168 | F94: 0.1841 | G94: 8.73
A95: 2025 | B95: 4.43 | C95: 88.7 | D95: 0.0628 | E95: 0.1266 | F95: 0.2367 | G95: 11.23
A97: 13. IBN SINA
A98: Year | B98: P/E | C98: NAV | D98: ROA | E98: ROE | F98: NPM | G98: EPS
A99: 2021 | B99: 15.76 | C99: 68.82 | D99: 0.1272 | E99: 0.2275 | F99: 0.0663 | G99: 15.66
A100: 2022 | B100: 15.3 | C100: 84.03 | D100: 0.1406 | E100: 0.2308 | F100: 0.0714 | G100: 19.39
A101: 2023 | B101: 14.79 | C101: 97.82 | D101: 0.1209 | E101: 0.1981 | F101: 0.0663 | G101: 19.38
A102: 2024 | B102: 11.64 | C102: 113.09 | D102: 0.103 | E102: 0.1898 | F102: 0.059 | G102: 21.46
A103: 2025 | B103: 14.51 | C103: 127.98 | D103: 0.0839 | E103: 0.1584 | F103: 0.0533 | G103: 20.27
A105: 14. Renata Pharmacuticals
A106: Year | B106: P/E | C106: NAV | D106: ROA | E106: ROE | F106: NPM | G106: EPS
A107: 2021 | B107: 25.41 | C107: 153.1 | D107: 0.1456 | E107: 0.1969 | F107: 0.1689 | G107: 44.13
A108: 2022 | B108: 28.22 | C108: 153.52 | D108: 0.1216 | E108: 0.1738 | F108: 0.1645 | G108: 44.56
A109: 2023 | B109: 59.72 | C109: 159.33 | D109: 0.0479 | E109: 0.0764 | F109: 0.0709 | G109: 20.4
A110: 2024 | B110: 24.43 | C110: 173.12 | D110: 0.064 | E110: 0.1067 | F110: 0.0959 | G110: 31.53
A111: 2025 | B111: 25.22 | C111: 185.96 | D111: 0.0376 | E111: 0.0634 | F111: 0.0518 | G111: 19.36
A113: 15. Marico
A114: Year | B114: P/E | C114: NAV | D114: ROA | E114: ROE | F114: NPM | G114: EPS
...

Sheet Price Data
C1: Bank | E1: Financial Institutions | G1: Insurance | I1: Food & Allied | L1: Miscellaneous | M1: Tannery | N1: Cement | O1: Telecommunication | P1: Pharmacuticals & Chemicals | T1: Engineering | U1: IT Sector | V1: Fuel & Power
A2: Years | B2: Months | C2: BRACBANK | D2: NCC | E2: IPDC | F2: DBH | G2: PARAMOUNT | H2: ASIAPACINS | I2: LOVELLO | J2: FINEFOODS | K2: OLYMPIC | L2: INDEXAGRO | M2: APEXFOOT | N2: CONFIDCEM | O2: GP | P2: IBNSINA | Q2: RENATA | R2: MARICO | S2: RECKITTBEN | T2: KDSALTD | U2: ADNTEL | V2: JAMUNAOIL
A3: 2021 | B3: August | C3: 30.79 | D3: 15.6 | E3: 36.86 | F3: 74.73 | G3: 89.2 | H3: 71 | I3: 31.27 | J3: 56.5 | K3: 174.2 | L3: 129.7 | M3: 132.69 | N3: 141.14 | O3: 362.6 | P3: 256.5 | Q3: 1202.46 | R3: 2322.8 | S3: 4475.1 | T3: 58 | U3: 61.3 | V3: 182.9
B4: September | C4: 31.11 | D4: 15.7 | E4: 46.29 | F4: 78.45 | G4: 83.5 | H4: 68.7 | I4: 33.09 | J4: 53.7 | K4: 196.8 | L4: 118.4 | M4: 174.13 | N4: 152.57 | O4: 380.2 | P4: 273.1 | Q4: 1217.08 | R4: 2333.7 | S4: 4837.2 | T4: 76 | U4: 74.1 | V4: 183.9
B5: October | C5: 29.94 | D5: 15.5 | E5: 39.52 | F5: 72.91 | G5: 78.5 | H5: 67.8 | I5: 32.36 | J5: 41.3 | K5: 174.8 | L5: 105.3 | M5: 156.03 | N5: 123.81 | O5: 358.5 | P5: 269.1 | Q5: 1230.76 | R5: 2295.1 | S5: 5038.7 | T5: 73.1 | U5: 58.6 | V5: 173.4
B6: November | C6: 35.43 | D6: 15.4 | E6: 37.24 | F6: 70.18 | G6: 71 | H6: 61.3 | I6: 33.45 | J6: 38 | K6: 159 | L6: 111.1 | M6: 139.92 | N6: 108.29 | O6: 348.3 | P6: 268.5 | Q6: 1206.07 | R6: 2280.5 | S6: 4892.4 | T6: 63.4 | U6: 55.9 | V6: 171
B7: December | C7: 36.15 | D7: 15.3 | E7: 36.76 | F7: 70.09 | G7: 73.3 | H7: 68.5 | I7: 30.55 | J7: 50.4 | K7: 160.6 | L7: 122.2 | M7: 161.14 | N7: 116.1 | O7: 349.5 | P7: 271.3 | Q7: 1226.17 | R7: 2301 | S7: 5729.9 | T7: 70 | U7: 52.4 | V7: 171.1
A8: 2022 | B8: January | C8: 36.08 | D8: 15.2 | E8: 37.33 | F8: 69.82 | G8: 71.2 | H8: 64.8 | I8: 35.18 | J8: 46.8 | K8: 161.7 | L8: 116.7 | M8: 196.42 | N8: 115.33 | O8: 355.9 | P8: 283 | Q8: 1245.14 | R8: 2356.1 | S8: 5840.1 | T8: 56.9 | U8: 51.8 | V8: 167.8
B9: February | C9: 35.3 | D9: 15 | E9: 34.67 | F9: 66.64 | G9: 67 | H9: 56.9 | I9: 33.27 | J9: 47.9 | K9: 147.2 | L9: 106.6 | M9: 185.73 | N9: 111.33 | O9: 340 | P9: 285 | Q9: 1271.4 | R9: 2399.4 | S9: 5853.3 | T9: 55 | U9: 60.8 | V9: 168.2
B10: March | C10: 32.49 | D10: 15.4 | E10: 39.33 | F10: 65.6 | G10: 61.4 | H10: 55.2 | I10: 37.91 | J10: 45.6 | K10: 137.2 | L10: 102.8 | M10: 183.26 | N10: 108.57 | O10: 328.9 | P10: 298.1 | Q10: 1264.77 | R10: 2355.2 | S10: 5388.4 | T10: 56.9 | U10: 65.1 | V10: 163.2
B11: April | C11: 32.32 | D11: 15.6 | E11: 54.19 | F11: 66.4 | G11: 57.1 | H11: 57.5 | I11: 38.36 | J11: 41.8 | K11: 130.7 | L11: 105.1 | M11: 176.83 | N11: 108.29 | O11: 319.9 | P11: 295.7 | Q11: 1272.9 | R11: 2353.1 | S11: 4871.3 | T11: 54.6 | U11: 68.3 | V11: 167.6
B12: May | C12: 28.88 | D12: 15.6 | E12: 50.1 | F12: 62.2 | G12: 48.3 | H12: 51.9 | I12: 38.36 | J12: 42.2 | K12: 124 | L12: 100.1 | M12: 165.23 | N12: 98.76 | O12: 307.1 | P12: 288.3 | Q12: 1247.76 | R12: 2344.8 | S12: 4695.9 | T12: 55.1 | U12: 65.7 | V12: 167.6
B13: June | C13: 29.16 | D13: 14.4 | E13: 50.19 | F13: 62.1 | G13: 51.8 | H13: 51.3 | I13: 38.09 | J13: 45.2 | K13: 124.1 | L13: 102.1 | M13: 163.19 | N13: 98.48 | O13: 294.1 | P13: 296.7 | Q13: 1257.57 | R13: 2421 | S13: 4868.5 | T13: 60 | U13: 65.8 | V13: 177.2
B14: July | C14: 27.12 | D14: 13.8 | E14: 54.95 | F14: 59 | G14: 50.4 | H14: 47.8 | I14: 34.64 | J14: 44.3 | K14: 120.3 | L14: 103.8 | M14: 158.2 | N14: 90.1 | O14: 294.3 | P14: 287.5 | Q14: 1218.41 | R14: 2449.7 | S14: 4796.1 | T14: 80.6 | U14: 60 | V14: 168.9
B15: August | C15: 27.12 | D15: 14.1 | E15: 65.14 | F15: 62.6 | G15: 48.6 | H15: 49.7 | I15: 37.82 | J15: 52.8 | K15: 137 | L15: 108.6 | M15: 174.06 | N15: 102.29 | O15: 287.8 | P15: 301 | Q15: 1224.39 | R15: 2472.6 | S15: 4892.2 | T15: 83 | U15: 63.1 | V15: 170.2
B16: September | C16: 27.05 | D16: 13.8 | E16: 63.33 | F16: 57.8 | G16: 46.5 | H16: 46.1 | I16: 38.55 | J16: 59.6 | K16: 129.6 | L16: 141.5 | M16: 182.78 | N16: 94 | O16: 286.6 | P16: 306.4 | Q16: 1217.94 | R16: 2430.7 | S16: 4830.9 | T16: 77 | U16: 84.8 | V16: 167.4
B17: October | C17: 27.05 | D17: 13.8 | E17: 54.86 | F17: 57.8 | G17: 46.5 | H17: 44.4 | I17: 36.18 | J17: 62.5 | K17: 113.7 | L17: 107.7 | M17: 170.25 | N17: 89.05 | O17: 286.6 | P17: 286.6 | Q17: 1217.94 | R17: 2421.5 | S17: 4760.7 | T17: 93.4 | U17: 131 | V17: 167.5
B18: November | C18: 27.05 | D18: 13.8 | E18: 54.86 | F18: 57.8 | G18: 46.5 | H18: 43.6 | I18: 34.45 | J18: 58.2 | K18: 120.2 | L18: 103.8 | M18: 170.25 | N18: 89.05 | O18: 286.6 | P18: 286.6 | Q18: 1217.9 | R18: 2421.5 | S18: 4760.7 | T18: 77 | U18: 101.4 | V18: 169
B19: December | C19: 27.05 | D19: 13.8 | E19: 54.86 | F19: 57.8 | G19: 44.5 | H19: 41.6 | I19: 34.45 | J19: 59.7 | K19: 124 | L19: 103.6 | M19: 173.29 | N19: 89 | O19: 286.6 | P19: 286.6 | Q19: 1217.9 | R19: 2421.5 | S19: 4760.7 | T19: 77 | U19: 114.1 | V19: 167.3
A20: 2023 | B20: January | C20: 27.05 | D20: 13.8 | E20: 54.86 | F20: 57.8 | G20: 43.5 | H20: 47.9 | I20: 34.45 | J20: 57.7 | K20: 138 | L20: 103.6 | M20: 170.25 | N20: 89 | O20: 286.6 | P20: 286.6 | Q20: 1217.9 | R20: 2421.5 | S20: 4760.7 | T20: 77 | U20: 115 | V20: 170
B21: February | C21: 27.05 | D21: 13.8 | E21: 54.86 | F21: 57.8 | G21: 38.4 | H21: 43.9 | I21: 34.45 | J21: 61.5 | K21: 148.7 | L21: 103.6 | M21: 195.31 | N21: 89 | O21: 286.6 | P21: 286.6 | Q21: 1217.9 | R21: 2421.5 | S21: 4760.7 | T21: 77 | U21: 130.7 | V21: 170
B22: March | C22: 27.05 | D22: 13.8 | E22: 54.86 | F22: 57.8 | G22: 38.4 | H22: 43.6 | I22: 34.45 | J22: 72.2 | K22: 155.4 | L22: 103.6 | M22: 198.21 | N22: 89 | O22: 286.6 | P22: 286.6 | Q22: 1217.9 | R22: 2421.5 | S22: 4760.7 | T22: 77 | U22: 163.6 | V22: 178.5
B23: April | C23: 27.05 | D23: 13.8 | E23: 54.86 | F23: 56.7 | G23: 38.4 | H23: 44.8 | I23: 34.45 | J23: 71.4 | K23: 165.9 | L23: 103.6 | M23: 223.34 | N23: 89 | O23: 286.6 | P23: 286.6 | Q23: 1217.9 | R23: 2421.5 | S23: 4777.9 | T23: 77 | U23: 131.5 | V23: 182.9
B24: May | C24: 25.16 | D24: 13.8 | E24: 54.86 | F24: 56.7 | G24: 57.9 | H24: 54.9 | I24: 34.45 | J24: 92.8 | K24: 155.3 | L24: 103.6 | M24: 209.59 | N24: 89 | O24: 286.6 | P24: 286.6 | Q24: 1217.9 | R24: 2421.5 | S24: 4772.2 | T24: 77 | U24: 133.7 | V24: 180.9
B25: June | C25: 25.16 | D25: 13.1 | E25: 54.86 | F25: 56.7 | G25: 48.3 | H25: 48.8 | I25: 34.45 | J25: 117.7 | K25: 153.6 | L25: 103.6 | M25: 207.87 | N25: 89 | O25: 286.6 | P25: 286.6 | Q25: 1217.9 | R25: 2421.5 | S25: 4873.7 | T25: 77 | U25: 131.7 | V25: 179.9
B26: July | C26: 25.16 | D26: 13.1 | E26: 54.86 | F26: 56.7 | G26: 44.3 | H26: 61.9 | I26: 34.45 | J26: 123.6 | K26: 145.2 | L26: 103.6 | M26: 191.34 | N26: 89 | O26: 286.6 | P26: 286.6 | Q26: 1217.9 | R26: 2421.5 | S26: 4790 | T26: 77 | U26: 134.3 | V26: 177.5
B27: August | C27: 25.16 | D27: 13.1 | E27: 54.86 | F27: 56.7 | G27: 41.6 | H27: 56.8 | I27: 34.45 | J27: 122.9 | K27: 148.2 | L27: 103.6 | M27: 188.1 | N27: 89 | O27: 286.6 | P27: 286.6 | Q27: 1217.9 | R27: 2560.2 | S27: 4824.1 | T27: 77 | U27: 131.2 | V27: 176.5
B28: September | C28: 25.16 | D28: 13.1 | E28: 54.86 | F28: 56.7 | G28: 71.1 | H28: 61.4 | I28: 34.45 | J28: 118 | K28: 153.1 | L28: 103.6 | M28: 203.57 | N28: 89 | O28: 286.6 | P28: 286.6 | Q28: 1217.9 | R28: 2471.9 | S28: 4763.4 | T28: 77 | U28: 123.9 | V28: 177.1
B29: October | C29: 25.16 | D29: 13.1 | E29: 54.86 | F29: 56.7 | G29: 58.6 | H29: 53 | I29: 34.45 | J29: 127.1 | K29: 152.9 | L29: 103.6 | M29: 191.93 | N29: 89 | O29: 286.6 | P29: 286.6 | Q29: 1217.9 | R29: 2469.1 | S29: 4760.7 | T29: 77 | U29: 119.1 | V29: 177.7
B30: November | C30: 25.16 | D30: 13.1 | E30: 54.86 | F30: 56.7 | G30: 53.5 | H30: 50.7 | I30: 34.45 | J30: 122.8 | K30: 143.2 | L30: 103.6 | M30: 187.27 | N30: 89 | O30: 286.6 | P30: 286.6 | Q30: 1217.9 | R30: 2421.5 | S30: 4760.7 | T30: 77 | U30: 109.5 | V30: 177.8
B31: December | C31: 25.16 | D31: 13.1 | E31: 54.86 | F31: 56.7 | G31: 56.8 | H31: 50.1 | I31: 34.45 | J31: 133.9 | K31: 152 | L31: 103.6 | M31: 187.27 | N31: 89 | O31: 286.6 | P31: 286.6 | Q31: 1217.9 | R31: 2460.7 | S31: 4760.7 | T31: 77 | U31: 117.1 | V31: 168.5
A32: 2024 | B32: January | C32: 26.49 | D32: 11.7 | E32: 29.9 | F32: 49.1 | G32: 58.5 | H32: 51.1 | I32: 29.73 | J32: 133.1 | K32: 152.7 | L32: 77.4 | M32: 173.38 | N32: 74.4 | O32: 286.6 | P32: 266.7 | Q32: 1217.9 | R32: 2520.4 | S32: 4988 | T32: 59.3 | U32: 127.9 | V32: 169.9
B33: February | C33: 30 | D33: 11.9 | E33: 30.67 | F33: 47 | G33: 54.6 | H33: 50.1 | I33: 43.64 | J33: 159.1 | K33: 145.2 | L33: 81.1 | M33: 183.49 | N33: 80.4 | O33: 286.6 | P33: 271 | Q33: 943.6 | R33: 2515.9 | S33: 5007.7 | T33: 55.1 | U33: 124.1 | V33: 174.5
B34: March | C34: 28.25 | D34: 11.9 | E34: 26 | F34: 40.8 | G34: 54.6 | H34: 45.1 | I34: 49.64 | J34: 178 | K34: 152.1 | L34: 71.9 | M34: 177.09 | N34: 73.7 | O34: 237.8 | P34: 263.2 | Q34: 776 | R34: 2444.9 | S34: 4687.9 | T34: 45 | U34: 119.3 | V34: 173.3
B35: April | C35: 27.19 | D35: 11.9 | E35: 20.76 | F35: 37.1 | G35: 58.1 | H35: 43.2 | I35: 72.45 | J35: 177.8 | K35: 144.1 | L35: 66.6 | M35: 170.4 | N35: 75 | O35: 235.8 | P35: 256.6 | Q35: 768.7 | R35: 2328.5 | S35: 4474.9 | T35: 45.2 | U35: 110 | V35: 174.5
B36: May | C36: 26.05 | D36: 12.3 | E36: 18.76 | F36: 32.6 | G36: 54.6 | H36: 39.3 | I36: 79 | J36: 165.8 | K36: 131.8 | L36: 62.9 | M36: 155.93 | N36: 65.1 | O36: 223.5 | P36: 243 | Q36: 634.2 | R36: 2007.3 | S36: 4122.9 | T36: 40 | U36: 86.3 | V36: 170.1
B37: June | C37: 26.51 | D37: 9.8 | E37: 17.71 | F37: 31.7 | G37: 53.3 | H37: 39.9 | I37: 78.73 | J37: 165.1 | K37: 132.4 | L37: 64.3 | M37: 173.75 | N37: 67.8 | O37: 247.7 | P37: 249.8 | Q37: 770.1 | R37: 2274.5 | S37: 4600 | T37: 37.9 | U37: 99.1 | V37: 174.6
B38: July | C38: 28.68 | D38: 10.4 | E38: 19.05 | F38: 31.7 | G38: 56.2 | H38: 38.4 | I38: 85.18 | J38: 163 | K38: 119.5 | L38: 62.6 | M38: 165.82 | N38: 62.5 | O38: 252.5 | P38: 242.7 | Q38: 710.1 | R38: 2292 | S38: 4767.7 | T38: 38 | U38: 92.4 | V38: 178.5
B39: August | C39: 41.43 | D39: 12.4 | E39: 23.62 | F39: 43.3 | G39: 48.3 | H39: 39 | I39: 69.73 | J39: 160.5 | K39: 201.1 | L39: 71.1 | M39: 172.58 | N39: 76.3 | O39: 344 | P39: 322.5 | Q39: 761.1 | R39: 2263.7 | S39: 4839.4 | T39: 41.6 | U39: 91.1 | V39: 194.3
B40: September | C40: 41.89 | D40: 10.8 | E40: 20.1 | F40: 38.5 | G40: 38.5 | H40: 36.3 | I40: 78.91 | J40: 164 | K40: 184.5 | L40: 66.1 | M40: 174.47 | N40: 59.1 | O40: 350.2 | P40: 357.9 | Q40: 700.6 | R40: 2311.9 | S40: 4782.5 | T40: 34.9 | U40: 93.9 | V40: 178.9
B41: October | C41: 39.88 | D41: 11.9 | E41: 18.95 | F41: 39.7 | G41: 37.9 | H41: 31.6 | I41: 80.82 | J41: 157.5 | K41: 148 | L41: 63 | M41: 162.48 | N41: 48.9 | O41: 314.2 | P41: 306.1 | Q41: 670 | R41: 2287.8 | S41: 4642.9 | T41: 32.4 | U41: 86.9 | V41: 176.1
B42: November | C42: 37.33 | D42: 11 | E42: 18.86 | F42: 41 | G42: 43 | H42: 34.4 | I42: 89.1 | J42: 214 | K42: 154 | L42: 64.5 | M42: 162.8 | N42: 62.3 | O42: 319.7 | P42: 285 | Q42: 637.7 | R42: 2332.5 | S42: 4344.6 | T42: 36.9 | U42: 85.1 | V42: 191.1
B43: December | C43: 37.87 | D43: 10.8 | E43: 17.43 | F43: 38.9 | G43: 41.2 | H43: 32 | I43: 86.6 | J43: 225.3 | K43: 158 | L43: 66.4 | M43: 159.92 | N43: 56.7 | O43: 323.1 | P43: 286.8 | Q43: 635.1 | R43: 2282.8 | S43: 4350 | T43: 34.4 | U43: 85.2 | V43: 171.4
A44: 2025 | B44: January | C44: 40.04 | D44: 10.3 | E44: 16.29 | F44: 35.3 | G44: 39 | H44: 32 | I44: 84.5 | J44: 191.9 | K44: 153.7 | L44: 67.1 | M44: 161.12 | N44: 55.6 | O44: 335.4 | P44: 287.9 | Q44: 499.3 | R44: 2321.1 | S44: 4074.7 | T44: 32.1 | U44: 90.3 | V44: 174.6
B45: February | C45: 40.43 | D45: 10.3 | E45: 17.24 | F45: 37.1 | G45: 37.6 | H45: 30.7 | I45: 84.4 | J45: 192.8 | K45: 146 | L45: 66.9 | M45: 162.56 | N45: 53.3 | O45: 328.2 | P45: 293.3 | Q45: 508.3 | R45: 2371.5 | S45: 3999.9 | T45: 40.8 | U45: 93.7 | V45: 175.3
B46: March | C46: 39.34 | D46: 10.9 | E46: 16.19 | F46: 36.1 | G46: 38.5 | H46: 30 | I46: 83.8 | J46: 194.8 | K46: 147.2 | L46: 66.5 | M46: 165.52 | N46: 51.6 | O46: 321.9 | P46: 287.7 | Q46: 500.5 | R46: 2435.8 | S46: 3861.8 | T46: 44.8 | U46: 84 | V46: 175.5
B47: April | C47: 38.34 | D47: 10.7 | E47: 15.43 | F47: 33.9 | G47: 34.8 | H47: 31.2 | I47: 83.4 | J47: 201.9 | K47: 152.1 | L47: 64.7 | M47: 166.56 | N47: 49.4 | O47: 299.6 | P47: 293 | Q47: 490.9 | R47: 2541.2 | S47: 3678.7 | T47: 40.7 | U47: 71.1 | V47: 172.2
B48: May | C48: 40 | D48: 9.8 | E48: 13.8 | F48: 32 | G48: 34.1 | H48: 27.8 | I48: 80.3 | J48: 217.1 | K48: 144.5 | L48: 59.4 | M48: 156.64 | N48: 48.1 | O48: 283.4 | P48: 283.9 | Q48: 477.5 | R48: 2299.7 | S48: 3280.8 | T48: 39.6 | U48: 62.8 | V48: 171.8
B49: June | C49: 44.09 | D49: 9.9 | E49: 14.2 | F49: 33.6 | G49: 39.3 | H49: 28.9 | I49: 98.6 | J49: 236.8 | K49: 153.5 | L49: 62.4 | M49: 162.72 | N49: 49.7 | O49: 303.1 | P49: 294.1 | Q49: 488.4 | R49: 2423.1 | S49: 3341 | T49: 39.5 | U49: 69.8 | V49: 182.4
B50: July | C50: 61.48 | D50: 13 | E50: 18.9 | F50: 40.8 | G50: 41 | H50: 34.5 | I50: 92.4 | J50: 259.3 | K50: 166.9 | L50: 67.7 | M50: 175.68 | N50: 55.9 | O50: 313 | P50: 313.4 | Q50: 510.9 | R50: 2880.2 | S50: 3389 | T50: 40.2 | U50: 76.5 | V50: 190.4
B51: August | C51: 66.52 | D51: 12.1 | E51: 19.1 | F51: 38.6 | G51: 46.8 | H51: 35.6 | I51: 103.3 | J51: 287.7 | K51: 169.9 | L51: 77.7 | M51: 186.72 | N51: 62.4 | O51: 310.4 | P51: 321.3 | Q51: 528.5 | R51: 2918.8 | S51: 3439.4 | T51: 45.8 | U51: 82.6 | V51: 191.1
B52: September | C52: 60.43 | D52: 12.2 | E52: 22.1 | F52: 38.1 | G52: 44.4 | H52: 34.4 | I52: 96.7 | J52: 316.7 | K52: 154.7 | L52: 76.3 | M52: 189.12 | N52: 59.1 | O52: 299 | P52: 307.3 | Q52: 480.4 | R52: 2842.1 | S52: 3415.9 | T52: 47.7 | U52: 74.7 | V52: 187.3
B53: October | C53: 59.22 | D53: 11.1 | E53: 21.5 | F53: 36.6 | G53: 43.3 | H53: 31.8 | I53: 95.4 | J53: 308.3 | K53: 148.6 | L53: 75.7 | M53: 193.1 | N53: 55.1 | O53: 283.4 | P53: 291.7 | Q53: 437.2 | R53: 2780.2 | S53: 3523.1 | T53: 42.2 | U53: 65.6 | V53: 187.8
B54: November | C54: 57.22 | D54: 11.6 | E54: 19.7 | F54: 35.7 | G54: 40.5 | H54: 30.4 | I54: 71.1 | J54: 315.4 | K54: 140.9 | L54: 66.4 | M54: 190.5 | N54: 51.9 | O54: 279.5 | P54: 312.6 | Q54: 406.2 | R54: 2735.2 | S54: 3388.1 | T54: 41.5 | U54: 60.7 | V54: 191.5
B55: December | C55: 54.87 | D55: 12.2 | E55: 18.9 | F55: 34.6 | G55: 43.1 | H55: 30.5 | I55: 67.6 | J55: 380.3 | K55: 137.4 | L55: 65.3 | M55: 177.5 | N55: 49.2 | O55: 257.9 | P55: 314 | Q55: 391.8 | R55: 2673.5 | S55: 3424.4 | T55: 41 | U55: 57.8 | V55: 167.9
A56: 2026 | B56: January | C56: 64.35 | D56: 12.8 | E56: 19.7 | F56: 37.5 | G56: 55 | H56: 40.8 | I56: 69.3 | J56: 439 | K56: 144.2 | L56: 65.4 | M56: 182.5 | N56: 51 | O56: 267.8 | P56: 344.6 | Q56: 421.3 | R56: 2780.6 | S56: 3470.2 | T56: 40.5 | U56: 62.1 | V56: 169.5
B57: February | C57: 76.09 | D57: 13.3 | E57: 20.5 | F57: 38.9 | G57: 53.3 | H57: 38.5 | I57: 70 | J57: 470.9 | K57: 157.8 | L57: 69.1 | M57: 191.7 | N57: 69.8 | O57: 262.1 | P57: 329.9 | Q57: 454 | R57: 2877.1 | S57: 3561.6 | T57: 42.4 | U57: 64.8 | V57: 177
B58: March | C58: 58.26 | D58: 12.8 | E58: 18.7 | F58: 36.4 | G58: 52.3 | H58: 37.1 | I58: 68.7 | J58: 484.6 | K58: 147.1 | L58: 64.3 | M58: 184 | N58: 60.3 | O58: 244 | P58: 315.8 | Q58: 423.2 | R58: 2731.8 | S58: 3474.2 | T58: 39.5 | U58: 57.8 | V58: 171.1
B59: April | C59: 63.65 | D59: 16.9 | E59: 18.8 | F59: 38.1 | G59: 53.1 | H59: 37.8 | I59: 84.7 | J59: 530.9 | K59: 142.1 | L59: 70.4 | M59: 194 | N59: 64.1 | O59: 243 | P59: 310 | Q59: 416.3 | R59: 2768.7 | S59: 3470.4 | T59: 45.9 | U59: 60.2 | V59: 169.5
B60: May | C60: 67.3 | D60: 14.6 | E60: 18.9 | F60: 37.3 | G60: 50.9 | H60: 42 | I60: 75.6 | J60: 577 | K60: 143 | L60: 72.2 | M60: 201.1 | N60: 62.1 | O60: 241 | P60: 315.5 | Q60: 414 | R60: 2759.9 | S60: 3282 | T60: 49.6 | U60: 61.8 | V60: 168.5
B61: June | C61: 65.5 | D61: 16 | E61: 32.9 | F61: 41 | G61: 64.3 | H61: 45.4 | I61: 70.9 | J61: 513.9 | K61: 155 | L61: 73.1 | M61: 205.6 | N61: 67.8 | O61: 259.6 | P61: 319.6 | Q61: 456 | R61: 2771.2 | S61: 3369.2 | T61: 53.2 | U61: 68.5 | V61: 186.5
B62: July | C62: 63.3 | D62: 15.4 | E62: 32.2 | F62: 44 | G62: 63 | H62: 48.2 | I62: 69.5 | J62: 482.2 | K62: 154.2 | L62: 74.1 | M62: 217.7 | N62: 68.5 | O62: 259.8 | P62: 319.9 | Q62: 470.2 | R62: 2721.5 | S62: 3315.5 | T62: 50.5 | U62: 67.2 | V62: 182.4
B63: August | C63: 62.2 | D63: 15 | E63: 31 | F63: 40.8 | G63: 58.6 | H63: 47.2 | I63: 52.5 | J63: 472.2 | K63: 145.3 | L63: 68.8 | M63: 204.7 | N63: 63.4 | O63: 242.5 | P63: 313.1 | Q63: 460 | R63: 2699.2 | S63: 3285.3 | T63: 45.8 | U63: 60.5 | V63: 176

Sheet Cash Dividend
C1: Bank | E1: Financial Institutions | G1: Insurance | I1: Food & Allied | L1: Miscellaneous | M1: Tannery | N1: Cement | O1: Telecommunication | P1: Pharmacuticals & Chemicals | T1: Engineering | U1: IT Sector | V1: Fuel & Power
A2: Years | B2: Months | C2: BRACBANK | D2: NCC | E2: IPDC | F2: DBH | G2: PARAMOUNT | H2: ASIAPACINS | I2: LOVELLO | J2: FINEFOODS | K2: OLYMPIC | L2: INDEXAGRO | M2: APEXFOOT | N2: CONFIDCEM | O2: GP | P2: IBNSINA | Q2: RENATA | R2: MARICO | S2: RECKITTBEN | T2: KDSALTD | U2: ADNTEL | V2: JAMUNAOIL
A3: 2021 | B3: August
B4: September
B5: October | L5: =10*25% -> 2.5 | M5: 3.5 | P5: 4.7
B6: November | I6: =10*11% -> 1.1 | K6: 5.4 | N6: 2.5 | Q6: 14.5 | T6: 1.5 | U6: 1
B7: December
A8: 2022 | B8: January | V8: 12
B9: February | O9: 25
B10: March | E10: =10*12% -> 1.2 | F10: =10*15% -> 1.5
B11: April | C11: 0.75 | G11: =10*10% -> 1 | S11: =10*1650% -> 165
B12: May | H12: =10*18% -> 1.8 | R12: =10*800% -> 80
B13: June | D13: =10*12% -> 1.2
B14: July
B15: August
B16: September | P16: 6
B17: October | M17: 3.5 | U17: 1
B18: November | I18: =10*12% -> 1.2 | J18: 0.15 | K18: 4.5 | L18: 1 | Q18: 14 | T18: 1.6
B19: December | N19: 0.5 | V19: 12
A20: 2023 | B20: January
B21: February | O21: 22
B22: March | E22: =10*10% -> 1 | S22: 98
B23: April | F23: =10*15% -> 1.5
B24: May | C24: 0.75 | G24: =10*10% -> 1 | H24: =10*15% -> 1.5 | R24: 75
B25: June | D25: =10*5% -> 0.5
B26: July
B27: August
B28: September | P28: 6
B29: October | M29: 3.5 | U29: 1.5
B30: November | I30: =10*10% -> 1 | J30: 0.125 | K30: 6 | L30: 2 | Q30: 6.25 | T30: 1
B31: December | N31: 0.5 | V31: 13
A32: 2024 | B32: January
B33: February | O33: 12.5
B34: March
B35: April | E35: =10*5% -> 0.5 | F35: =10*15% -> 1.5 | S35: 55
B36: May | C36: 1 | G36: =10*10% -> 1 | H36: =10*12% -> 1.2 | R36: 20
B37: June | D37: =10*12% -> 1.2
B38: July
B39: August
B40: September | N40: 1
B41: October | M41: 3.5 | P41: 6.3 | Q41: 9.2
B42: November | I42: =10*10% -> 1 | K42: 1 | L42: 2.5 | T42: 0.5 | U42: 1
B43: December | J43: 1 | V43: 15
A44: 2025 | B44: January
B45: February | O45: 33
B46: March
B47: April | G47: =10*10% -> 1 | S47: 333
B48: May | C48: 1.25 | D48: =10*13% -> 1.3 | E48: =10*5% -> 0.5 | F48: =10*15% -> 1.5 | R48: =10*3840% -> 384
B49: June | H49: =10*10% -> 1
B50: July
B51: August
B52: September
B53: October | M53: 2.5 | P53: 6.4
B54: November | I54: =10*11% -> 1.1 | J54: 1.4 | K54: 3 | L54: 1.2 | N54: 1 | Q54: 5.5 | T54: 1 | U54: 1
B55: December | V55: 18
A56: 2026 | B56: January
B57: February
B58: March | O58: 21.5
B59: April | G59: =10*10% -> 1
B60: May | C60: 1.5 | D60: =10*17% -> 1.7 | H60: =10*14% -> 1.4
B61: June | E61: =10*5% -> 0.5 | F61: =10*15% -> 1.5 | R61: =10*2075% -> 207.5 | S61: 173
B62: July
B63: August

Sheet Stock Dividend
C1: Bank | E1: Financial Institutions | G1: Insurance | I1: Food & Allied | L1: Miscellaneous | M1: Tannery | N1: Cement | O1: Telecommunication | P1: Pharmacuticals & Chemicals | T1: Engineering | U1: IT Sector | V1: Fuel & Power
A2: Years | B2: Months | C2: BRACBANK | D2: NCC | E2: IPDC | F2: DBH | G2: PARAMOUNT | H2: ASIAPACINS | I2: LOVELLO | J2: FINEFOODS | K2: OLYMPIC | L2: INDEXAGRO | M2: APEXFOOT | N2: CONFIDCEM | O2: GP | P2: IBNSINA | Q2: RENATA | R2: MARICO | S2: RECKITTBEN | T2: KDSALTD | U2: ADNTEL | V2: JAMUNAOIL
A3: 2021 | B3: August
B4: September
B5: October | M5: 0.05
B6: November | Q6: 0.1
B7: December
A8: 2022 | B8: January
B9: February
B10: March | F10: 0.1
B11: April | C11: 0.075
B12: May
B13: June | D13: 0.04
B14: July
B15: August
B16: September
B17: October | M17: 0.1
B18: November | Q18: 0.07
B19: December | N19: 0.05
A20: 2023 | B20: January
B21: February
B22: March
B23: April | F23: 0.02
B24: May | C24: 0.075
B25: June | D25: 0.05
B26: July
B27: August
B28: September
B29: October | M29: 0.1
B30: November
B31: December | N31: 0.05
A32: 2024 | B32: January
B33: February
B34: March
B35: April | E35: 0.05
B36: May | C36: 0.1
B37: June
B38: July
B39: August
B40: September
B41: October | M41: 0.1
B42: November | I42: 0.1 | T42: 0.05
B43: December
A44: 2025 | B44: January
B45: February
B46: March
B47: April
B48: May | C48: 0.125 | E48: 0.05
B49: June | F49: 0.02
B50: July
B51: August
B52: September
B53: October | M53: 0.25
B54: November | I54: 0.05 | L54: 0.05
B55: December
A56: 2026 | B56: January
B57: February
B58: March
B59: April
B60: May | C60: 0.15 | D60: 0.04
B61: June | E61: 0.05
B62: July
B63: August

Sheet Right Share Ratio
C1: Bank | E1: Financial Institutions | G1: Insurance | I1: Food & Allied | L1: Miscellaneous | M1: Tannery | N1: Cement | O1: Telecommunication | P1: Pharmacuticals & Chemicals | T1: Engineering | U1: IT Sector | V1: Fuel & Power
A2: Years | B2: Months | C2: BRACBANK | D2: NCC | E2: IPDC | F2: DBH | G2: PARAMOUNT | H2: ASIAPACINS | I2: LOVELLO | J2: FINEFOODS | K2: OLYMPIC | L2: INDEXAGRO | M2: APEXFOOT | N2: CONFIDCEM | O2: GP | P2: IBNSINA | Q2: RENATA | R2: MARICO | S2: RECKITTBEN | T2: KDSALTD | U2: ADNTEL | V2: JAMUNAOIL
A3: 2021 | B3: August
B4: September
B5: October
B6: November
B7: December
A8: 2022 | B8: January
B9: February
B10: March
B11: April
B12: May
B13: June
B14: July
B15: August
B16: September
B17: October
B18: November
B19: December
A20: 2023 | B20: January
B21: February
B22: March
B23: April
B24: May
B25: June
B26: July
B27: August
B28: September
B29: October
B30: November
B31: December
A32: 2024 | B32: January
B33: February
B34: March
B35: April
B36: May
B37: June
B38: July
B39: August
B40: September
B41: October
B42: November
B43: December
A44: 2025 | B44: January
B45: February
B46: March
B47: April
B48: May
B49: June
B50: July
B51: August
B52: September
B53: October
B54: November
B55: December
A56: 2026 | B56: January
B57: February
B58: March
B59: April
B60: May
B61: June
B62: July
B63: August

Sheet Right Share Offer Price
C1: Bank | E1: Financial Institutions | G1: Insurance | I1: Food & Allied | L1: Miscellaneous | M1: Tannery | N1: Cement | O1: Telecommunication | P1: Pharmacuticals & Chemicals | T1: Engineering | U1: IT Sector | V1: Fuel & Power
A2: Years | B2: Months | C2: BRACBANK | D2: NCC | E2: IPDC | F2: DBH | G2: PARAMOUNT | H2: ASIAPACINS | I2: LOVELLO | J2: FINEFOODS | K2: OLYMPIC | L2: INDEXAGRO | M2: APEXFOOT | N2: CONFIDCEM | O2: GP | P2: IBNSINA | Q2: RENATA | R2: MARICO | S2: RECKITTBEN | T2: KDSALTD | U2: ADNTEL | V2: JAMUNAOIL
A3: 2021 | B3: August
B4: September
B5: October
B6: November
B7: December
A8: 2022 | B8: January
B9: February
B10: March
B11: April
B12: May
B13: June
B14: July
B15: August
B16: September
B17: October
B18: November
B19: December
A20: 2023 | B20: January
B21: February
B22: March
B23: April
B24: May
B25: June
B26: July
B27: August
B28: September
B29: October
B30: November
B31: December
A32: 2024 | B32: January
B33: February
B34: March
B35: April
B36: May
B37: June
B38: July
B39: August
B40: September
B41: October
B42: November
B43: December
A44: 2025 | B44: January
B45: February
B46: March
B47: April
B48: May
B49: June
B50: July
B51: August
B52: September
B53: October
B54: November
B55: December
A56: 2026 | B56: January
B57: February
B58: March
B59: April
B60: May
B61: June
B62: July
B63: August

Sheet Split
C1: Bank | E1: Financial Institutions | G1: Insurance | I1: Food & Allied | L1: Miscellaneous | M1: Tannery | N1: Cement | O1: Telecommunication | P1: Pharmacuticals & Chemicals | T1: Engineering | U1: IT Sector | V1: Fuel & Power
A2: Years | B2: Months | C2: BRACBANK | D2: NCC | E2: IPDC | F2: DBH | G2: PARAMOUNT | H2: ASIAPACINS | I2: LOVELLO | J2: FINEFOODS | K2: OLYMPIC | L2: INDEXAGRO | M2: APEXFOOT | N2: CONFIDCEM | O2: GP | P2: IBNSINA | Q2: RENATA | R2: MARICO | S2: RECKITTBEN | T2: KDSALTD | U2: ADNTEL | V2: JAMUNAOIL
A3: 2021 | B3: August | C3: 1 | D3: 1 | E3: 1 | F3: 1 | G3: 1 | H3: 1 | I3: 1 | J3: 1 | K3: 1 | L3: 1 | M3: 1 | N3: 1 | O3: 1 | P3: 1 | Q3: 1 | R3: 1 | S3: 1 | T3: 1 | U3: 1 | V3: 1
B4: September | C4: 1 | D4: 1 | E4: 1 | F4: 1 | G4: 1 | H4: 1 | I4: 1 | J4: 1 | K4: 1 | L4: 1 | M4: 1 | N4: 1 | O4: 1 | P4: 1 | Q4: 1 | R4: 1 | S4: 1 | T4: 1 | U4: 1 | V4: 1
B5: October | C5: 1 | D5: 1 | E5: 1 | F5: 1 | G5: 1 | H5: 1 | I5: 1 | J5: 1 | K5: 1 | L5: 1 | M5: 1 | N5: 1 | O5: 1 | P5: 1 | Q5: 1 | R5: 1 | S5: 1 | T5: 1 | U5: 1 | V5: 1
B6: November | C6: 1 | D6: 1 | E6: 1 | F6: 1 | G6: 1 | H6: 1 | I6: 1 | J6: 1 | K6: 1 | L6: 1 | M6: 1 | N6: 1 | O6: 1 | P6: 1 | Q6: 1 | R6: 1 | S6: 1 | T6: 1 | U6: 1 | V6: 1
B7: December | C7: 1 | D7: 1 | E7: 1 | F7: 1 | G7: 1 | H7: 1 | I7: 1 | J7: 1 | K7: 1 | L7: 1 | M7: 1 | N7: 1 | O7: 1 | P7: 1 | Q7: 1 | R7: 1 | S7: 1 | T7: 1 | U7: 1 | V7: 1
A8: 2022 | B8: January | C8: 1 | D8: 1 | E8: 1 | F8: 1 | G8: 1 | H8: 1 | I8: 1 | J8: 1 | K8: 1 | L8: 1 | M8: 1 | N8: 1 | O8: 1 | P8: 1 | Q8: 1 | R8: 1 | S8: 1 | T8: 1 | U8: 1 | V8: 1
B9: February | C9: 1 | D9: 1 | E9: 1 | F9: 1 | G9: 1 | H9: 1 | I9: 1 | J9: 1 | K9: 1 | L9: 1 | M9: 1 | N9: 1 | O9: 1 | P9: 1 | Q9: 1 | R9: 1 | S9: 1 | T9: 1 | U9: 1 | V9: 1
B10: March | C10: 1 | D10: 1 | E10: 1 | F10: 1 | G10: 1 | H10: 1 | I10: 1 | J10: 1 | K10: 1 | L10: 1 | M10: 1 | N10: 1 | O10: 1 | P10: 1 | Q10: 1 | R10: 1 | S10: 1 | T10: 1 | U10: 1 | V10: 1
B11: April | C11: 1 | D11: 1 | E11: 1 | F11: 1 | G11: 1 | H11: 1 | I11: 1 | J11: 1 | K11: 1 | L11: 1 | M11: 1 | N11: 1 | O11: 1 | P11: 1 | Q11: 1 | R11: 1 | S11: 1 | T11: 1 | U11: 1 | V11: 1
B12: May | C12: 1 | D12: 1 | E12: 1 | F12: 1 | G12: 1 | H12: 1 | I12: 1 | J12: 1 | K12: 1 | L12: 1 | M12: 1 | N12: 1 | O12: 1 | P12: 1 | Q12: 1 | R12: 1 | S12: 1 | T12: 1 | U12: 1 | V12: 1
B13: June | C13: 1 | D13: 1 | E13: 1 | F13: 1 | G13: 1 | H13: 1 | I13: 1 | J13: 1 | K13: 1 | L13: 1 | M13: 1 | N13: 1 | O13: 1 | P13: 1 | Q13: 1 | R13: 1 | S13: 1 | T13: 1 | U13: 1 | V13: 1
B14: July | C14: 1 | D14: 1 | E14: 1 | F14: 1 | G14: 1 | H14: 1 | I14: 1 | J14: 1 | K14: 1 | L14: 1 | M14: 1 | N14: 1 | O14: 1 | P14: 1 | Q14: 1 | R14: 1 | S14: 1 | T14: 1 | U14: 1 | V14: 1
B15: August | C15: 1 | D15: 1 | E15: 1 | F15: 1 | G15: 1 | H15: 1 | I15: 1 | J15: 1 | K15: 1 | L15: 1 | M15: 1 | N15: 1 | O15: 1 | P15: 1 | Q15: 1 | R15: 1 | S15: 1 | T15: 1 | U15: 1 | V15: 1
B16: September | C16: 1 | D16: 1 | E16: 1 | F16: 1 | G16: 1 | H16: 1 | I16: 1 | J16: 1 | K16: 1 | L16: 1 | M16: 1 | N16: 1 | O16: 1 | P16: 1 | Q16: 1 | R16: 1 | S16: 1 | T16: 1 | U16: 1 | V16: 1
B17: October | C17: 1 | D17: 1 | E17: 1 | F17: 1 | G17: 1 | H17: 1 | I17: 1 | J17: 1 | K17: 1 | L17: 1 | M17: 1 | N17: 1 | O17: 1 | P17: 1 | Q17: 1 | R17: 1 | S17: 1 | T17: 1 | U17: 1 | V17: 1
B18: November | C18: 1 | D18: 1 | E18: 1 | F18: 1 | G18: 1 | H18: 1 | I18: 1 | J18: 1 | K18: 1 | L18: 1 | M18: 1 | N18: 1 | O18: 1 | P18: 1 | Q18: 1 | R18: 1 | S18: 1 | T18: 1 | U18: 1 | V18: 1
B19: December | C19: 1 | D19: 1 | E19: 1 | F19: 1 | G19: 1 | H19: 1 | I19: 1 | J19: 1 | K19: 1 | L19: 1 | M19: 1 | N19: 1 | O19: 1 | P19: 1 | Q19: 1 | R19: 1 | S19: 1 | T19: 1 | U19: 1 | V19: 1
A20: 2023 | B20: January | C20: 1 | D20: 1 | E20: 1 | F20: 1 | G20: 1 | H20: 1 | I20: 1 | J20: 1 | K20: 1 | L20: 1 | M20: 1 | N20: 1 | O20: 1 | P20: 1 | Q20: 1 | R20: 1 | S20: 1 | T20: 1 | U20: 1 | V20: 1
B21: February | C21: 1 | D21: 1 | E21: 1 | F21: 1 | G21: 1 | H21: 1 | I21: 1 | J21: 1 | K21: 1 | L21: 1 | M21: 1 | N21: 1 | O21: 1 | P21: 1 | Q21: 1 | R21: 1 | S21: 1 | T21: 1 | U21: 1 | V21: 1
B22: March | C22: 1 | D22: 1 | E22: 1 | F22: 1 | G22: 1 | H22: 1 | I22: 1 | J22: 1 | K22: 1 | L22: 1 | M22: 1 | N22: 1 | O22: 1 | P22: 1 | Q22: 1 | R22: 1 | S22: 1 | T22: 1 | U22: 1 | V22: 1
B23: April | C23: 1 | D23: 1 | E23: 1 | F23: 1 | G23: 1 | H23: 1 | I23: 1 | J23: 1 | K23: 1 | L23: 1 | M23: 1 | N23: 1 | O23: 1 | P23: 1 | Q23: 1 | R23: 1 | S23: 1 | T23: 1 | U23: 1 | V23: 1
B24: May | C24: 1 | D24: 1 | E24: 1 | F24: 1 | G24: 1 | H24: 1 | I24: 1 | J24: 1 | K24: 1 | L24: 1 | M24: 1 | N24: 1 | O24: 1 | P24: 1 | Q24: 1 | R24: 1 | S24: 1 | T24: 1 | U24: 1 | V24: 1
B25: June | C25: 1 | D25: 1 | E25: 1 | F25: 1 | G25: 1 | H25: 1 | I25: 1 | J25: 1 | K25: 1 | L25: 1 | M25: 1 | N25: 1 | O25: 1 | P25: 1 | Q25: 1 | R25: 1 | S25: 1 | T25: 1 | U25: 1 | V25: 1
B26: July | C26: 1 | D26: 1 | E26: 1 | F26: 1 | G26: 1 | H26: 1 | I26: 1 | J26: 1 | K26: 1 | L26: 1 | M26: 1 | N26: 1 | O26: 1 | P26: 1 | Q26: 1 | R26: 1 | S26: 1 | T26: 1 | U26: 1 | V26: 1
B27: August | C27: 1 | D27: 1 | E27: 1 | F27: 1 | G27: 1 | H27: 1 | I27: 1 | J27: 1 | K27: 1 | L27: 1 | M27: 1 | N27: 1 | O27: 1 | P27: 1 | Q27: 1 | R27: 1 | S27: 1 | T27: 1 | U27: 1 | V27: 1
B28: September | C28: 1 | D28: 1 | E28: 1 | F28: 1 | G28: 1 | H28: 1 | I28: 1 | J28: 1 | K28: 1 | L28: 1 | M28: 1 | N28: 1 | O28: 1 | P28: 1 | Q28: 1 | R28: 1 | S28: 1 | T28: 1 | U28: 1 | V28: 1
B29: October | C29: 1 | D29: 1 | E29: 1 | F29: 1 | G29: 1 | H29: 1 | I29: 1 | J29: 1 | K29: 1 | L29: 1 | M29: 1 | N29: 1 | O29: 1 | P29: 1 | Q29: 1 | R29: 1 | S29: 1 | T29: 1 | U29: 1 | V29: 1
B30: November | C30: 1 | D30: 1 | E30: 1 | F30: 1 | G30: 1 | H30: 1 | I30: 1 | J30: 1 | K30: 1 | L30: 1 | M30: 1 | N30: 1 | O30: 1 | P30: 1 | Q30: 1 | R30: 1 | S30: 1 | T30: 1 | U30: 1 | V30: 1
B31: December | C31: 1 | D31: 1 | E31: 1 | F31: 1 | G31: 1 | H31: 1 | I31: 1 | J31: 1 | K31: 1 | L31: 1 | M31: 1 | N31: 1 | O31: 1 | P31: 1 | Q31: 1 | R31: 1 | S31: 1 | T31: 1 | U31: 1 | V31: 1
A32: 2024 | B32: January | C32: 1 | D32: 1 | E32: 1 | F32: 1 | G32: 1 | H32: 1 | I32: 1 | J32: 1 | K32: 1 | L32: 1 | M32: 1 | N32: 1 | O32: 1 | P32: 1 | Q32: 1 | R32: 1 | S32: 1 | T32: 1 | U32: 1 | V32: 1
B33: February | C33: 1 | D33: 1 | E33: 1 | F33: 1 | G33: 1 | H33: 1 | I33: 1 | J33: 1 | K33: 1 | L33: 1 | M33: 1 | N33: 1 | O33: 1 | P33: 1 | Q33: 1 | R33: 1 | S33: 1 | T33: 1 | U33: 1 | V33: 1
B34: March | C34: 1 | D34: 1 | E34: 1 | F34: 1 | G34: 1 | H34: 1 | I34: 1 | J34: 1 | K34: 1 | L34: 1 | M34: 1 | N34: 1 | O34: 1 | P34: 1 | Q34: 1 | R34: 1 | S34: 1 | T34: 1 | U34: 1 | V34: 1
B35: April | C35: 1 | D35: 1 | E35: 1 | F35: 1 | G35: 1 | H35: 1 | I35: 1 | J35: 1 | K35: 1 | L35: 1 | M35: 1 | N35: 1 | O35: 1 | P35: 1 | Q35: 1 | R35: 1 | S35: 1 | T35: 1 | U35: 1 | V35: 1
B36: May | C36: 1 | D36: 1 | E36: 1 | F36: 1 | G36: 1 | H36: 1 | I36: 1 | J36: 1 | K36: 1 | L36: 1 | M36: 1 | N36: 1 | O36: 1 | P36: 1 | Q36: 1 | R36: 1 | S36: 1 | T36: 1 | U36: 1 | V36: 1
B37: June | C37: 1 | D37: 1 | E37: 1 | F37: 1 | G37: 1 | H37: 1 | I37: 1 | J37: 1 | K37: 1 | L37: 1 | M37: 1 | N37: 1 | O37: 1 | P37: 1 | Q37: 1 | R37: 1 | S37: 1 | T37: 1 | U37: 1 | V37: 1
B38: July | C38: 1 | D38: 1 | E38: 1 | F38: 1 | G38: 1 | H38: 1 | I38: 1 | J38: 1 | K38: 1 | L38: 1 | M38: 1 | N38: 1 | O38: 1 | P38: 1 | Q38: 1 | R38: 1 | S38: 1 | T38: 1 | U38: 1 | V38: 1
B39: August | C39: 1 | D39: 1 | E39: 1 | F39: 1 | G39: 1 | H39: 1 | I39: 1 | J39: 1 | K39: 1 | L39: 1 | M39: 1 | N39: 1 | O39: 1 | P39: 1 | Q39: 1 | R39: 1 | S39: 1 | T39: 1 | U39: 1 | V39: 1
B40: September | C40: 1 | D40: 1 | E40: 1 | F40: 1 | G40: 1 | H40: 1 | I40: 1 | J40: 1 | K40: 1 | L40: 1 | M40: 1 | N40: 1 | O40: 1 | P40: 1 | Q40: 1 | R40: 1 | S40: 1 | T40: 1 | U40: 1 | V40: 1
B41: October | C41: 1 | D41: 1 | E41: 1 | F41: 1 | G41: 1 | H41: 1 | I41: 1 | J41: 1 | K41: 1 | L41: 1 | M41: 1 | N41: 1 | O41: 1 | P41: 1 | Q41: 1 | R41: 1 | S41: 1 | T41: 1 | U41: 1 | V41: 1
B42: November | C42: 1 | D42: 1 | E42: 1 | F42: 1 | G42: 1 | H42: 1 | I42: 1 | J42: 1 | K42: 1 | L42: 1 | M42: 1 | N42: 1 | O42: 1 | P42: 1 | Q42: 1 | R42: 1 | S42: 1 | T42: 1 | U42: 1 | V42: 1
B43: December | C43: 1 | D43: 1 | E43: 1 | F43: 1 | G43: 1 | H43: 1 | I43: 1 | J43: 1 | K43: 1 | L43: 1 | M43: 1 | N43: 1 | O43: 1 | P43: 1 | Q43: 1 | R43: 1 | S43: 1 | T43: 1 | U43: 1 | V43: 1
A44: 2025 | B44: January | C44: 1 | D44: 1 | E44: 1 | F44: 1 | G44: 1 | H44: 1 | I44: 1 | J44: 1 | K44: 1 | L44: 1 | M44: 1 | N44: 1 | O44: 1 | P44: 1 | Q44: 1 | R44: 1 | S44: 1 | T44: 1 | U44: 1 | V44: 1
B45: February | C45: 1 | D45: 1 | E45: 1 | F45: 1 | G45: 1 | H45: 1 | I45: 1 | J45: 1 | K45: 1 | L45: 1 | M45: 1 | N45: 1 | O45: 1 | P45: 1 | Q45: 1 | R45: 1 | S45: 1 | T45: 1 | U45: 1 | V45: 1
B46: March | C46: 1 | D46: 1 | E46: 1 | F46: 1 | G46: 1 | H46: 1 | I46: 1 | J46: 1 | K46: 1 | L46: 1 | M46: 1 | N46: 1 | O46: 1 | P46: 1 | Q46: 1 | R46: 1 | S46: 1 | T46: 1 | U46: 1 | V46: 1
B47: April | C47: 1 | D47: 1 | E47: 1 | F47: 1 | G47: 1 | H47: 1 | I47: 1 | J47: 1 | K47: 1 | L47: 1 | M47: 1 | N47: 1 | O47: 1 | P47: 1 | Q47: 1 | R47: 1 | S47: 1 | T47: 1 | U47: 1 | V47: 1
B48: May | C48: 1 | D48: 1 | E48: 1 | F48: 1 | G48: 1 | H48: 1 | I48: 1 | J48: 1 | K48: 1 | L48: 1 | M48: 1 | N48: 1 | O48: 1 | P48: 1 | Q48: 1 | R48: 1 | S48: 1 | T48: 1 | U48: 1 | V48: 1
B49: June | C49: 1 | D49: 1 | E49: 1 | F49: 1 | G49: 1 | H49: 1 | I49: 1 | J49: 1 | K49: 1 | L49: 1 | M49: 1 | N49: 1 | O49: 1 | P49: 1 | Q49: 1 | R49: 1 | S49: 1 | T49: 1 | U49: 1 | V49: 1
B50: July | C50: 1 | D50: 1 | E50: 1 | F50: 1 | G50: 1 | H50: 1 | I50: 1 | J50: 1 | K50: 1 | L50: 1 | M50: 1 | N50: 1 | O50: 1 | P50: 1 | Q50: 1 | R50: 1 | S50: 1 | T50: 1 | U50: 1 | V50: 1
B51: August | C51: 1 | D51: 1 | E51: 1 | F51: 1 | G51: 1 | H51: 1 | I51: 1 | J51: 1 | K51: 1 | L51: 1 | M51: 1 | N51: 1 | O51: 1 | P51: 1 | Q51: 1 | R51: 1 | S51: 1 | T51: 1 | U51: 1 | V51: 1
B52: September | C52: 1 | D52: 1 | E52: 1 | F52: 1 | G52: 1 | H52: 1 | I52: 1 | J52: 1 | K52: 1 | L52: 1 | M52: 1 | N52: 1 | O52: 1 | P52: 1 | Q52: 1 | R52: 1 | S52: 1 | T52: 1 | U52: 1 | V52: 1
B53: October | C53: 1 | D53: 1 | E53: 1 | F53: 1 | G53: 1 | H53: 1 | I53: 1 | J53: 1 | K53: 1 | L53: 1 | M53: 1 | N53: 1 | O53: 1 | P53: 1 | Q53: 1 | R53: 1 | S53: 1 | T53: 1 | U53: 1 | V53: 1
B54: November | C54: 1 | D54: 1 | E54: 1 | F54: 1 | G54: 1 | H54: 1 | I54: 1 | J54: 1 | K54: 1 | L54: 1 | M54: 1 | N54: 1 | O54: 1 | P54: 1 | Q54: 1 | R54: 1 | S54: 1 | T54: 1 | U54: 1 | V54: 1
B55: December | C55: 1 | D55: 1 | E55: 1 | F55: 1 | G55: 1 | H55: 1 | I55: 1 | J55: 1 | K55: 1 | L55: 1 | M55: 1 | N55: 1 | O55: 1 | P55: 1 | Q55: 1 | R55: 1 | S55: 1 | T55: 1 | U55: 1 | V55: 1
A56: 2026 | B56: January | C56: 1 | D56: 1 | E56: 1 | F56: 1 | G56: 1 | H56: 1 | I56: 1 | J56: 1 | K56: 1 | L56: 1 | M56: 1 | N56: 1 | O56: 1 | P56: 1 | Q56: 1 | R56: 1 | S56: 1 | T56: 1 | U56: 1 | V56: 1
B57: February | C57: 1 | D57: 1 | E57: 1 | F57: 1 | G57: 1 | H57: 1 | I57: 1 | J57: 1 | K57: 1 | L57: 1 | M57: 1 | N57: 1 | O57: 1 | P57: 1 | Q57: 1 | R57: 1 | S57: 1 | T57: 1 | U57: 1 | V57: 1
B58: March | C58: 1 | D58: 1 | E58: 1 | F58: 1 | G58: 1 | H58: 1 | I58: 1 | J58: 1 | K58: 1 | L58: 1 | M58: 1 | N58: 1 | O58: 1 | P58: 1 | Q58: 1 | R58: 1 | S58: 1 | T58: 1 | U58: 1 | V58: 1
B59: April | C59: 1 | D59: 1 | E59: 1 | F59: 1 | G59: 1 | H59: 1 | I59: 1 | J59: 1 | K59: 1 | L59: 1 | M59: 1 | N59: 1 | O59: 1 | P59: 1 | Q59: 1 | R59: 1 | S59: 1 | T59: 1 | U59: 1 | V59: 1
B60: May | C60: 1 | D60: 1 | E60: 1 | F60: 1 | G60: 1 | H60: 1 | I60: 1 | J60: 1 | K60: 1 | L60: 1 | M60: 1 | N60: 1 | O60: 1 | P60: 1 | Q60: 1 | R60: 1 | S60: 1 | T60: 1 | U60: 1 | V60: 1
B61: June | C61: 1 | D61: 1 | E61: 1 | F61: 1 | G61: 1 | H61: 1 | I61: 1 | J61: 1 | K61: 1 | L61: 1 | M61: 1 | N61: 1 | O61: 1 | P61: 1 | Q61: 1 | R61: 1 | S61: 1 | T61: 1 | U61: 1 | V61: 1
B62: July | C62: 1 | D62: 1 | E62: 1 | F62: 1 | G62: 1 | H62: 1 | I62: 1 | J62: 1 | K62: 1 | L62: 1 | M62: 1 | N62: 1 | O62: 1 | P62: 1 | Q62: 1 | R62: 1 | S62: 1 | T62: 1 | U62: 1 | V62: 1
B63: August | C63: 1 | D63: 1 | E63: 1 | F63: 1 | G63: 1 | H63: 1 | I63: 1 | J63: 1 | K63: 1 | L63: 1 | M63: 1 | N63: 1 | O63: 1 | P63: 1 | Q63: 1 | R63: 1 | S63: 1 | T63: 1 | U63: 1 | V63: 1

Sheet Dividend Yield
C1: Bank | E1: Financial Institutions | G1: Insurance | I1: Food & Allied | L1: Miscellaneous | M1: Tannery | N1: Cement | O1: Telecommunication | P1: Pharmacuticals & Chemicals | T1: Engineering | U1: IT Sector | V1: Fuel & Power
A2: Years | B2: Months | C2: BRACBANK | D2: NCC | E2: IPDC | F2: DBH | G2: PARAMOUNT | H2: ASIAPACINS | I2: LOVELLO | J2: FINEFOODS | K2: OLYMPIC | L2: INDEXAGRO | M2: APEXFOOT | N2: CONFIDCEM | O2: GP | P2: IBNSINA | Q2: RENATA | R2: MARICO | S2: RECKITTBEN | T2: KDSALTD | U2: ADNTEL | V2: JAMUNAOIL
A3: 2021 | B3: August
B4: September | C4: ='Cash Dividend'!C4/'Price Data'!C4 -> 0 | D4: ='Cash Dividend'!D4/'Price Data'!D4 -> 0 | E4: ='Cash Dividend'!E4/'Price Data'!E4 -> 0 | F4: ='Cash Dividend'!F4/'Price Data'!F4 -> 0 | G4: ='Cash Dividend'!G4/'Price Data'!G4 -> 0 | H4: ='Cash Dividend'!H4/'Price Data'!H4 -> 0 | I4: ='Cash Dividend'!I4/'Price Data'!I4 -> 0 | J4: ='Cash Dividend'!J4/'Price Data'!J4 -> 0 | ... V4: ='Cash Dividend'!V4/'Price Data'!V4 -> 0
B5: October | C5: ='Cash Dividend'!C5/'Price Data'!C5 -> 0 | D5: ='Cash Dividend'!D5/'Price Data'!D5 -> 0 | E5: ='Cash Dividend'!E5/'Price Data'!E5 -> 0 | F5: ='Cash Dividend'!F5/'Price Data'!F5 -> 0 | G5: ='Cash Dividend'!G5/'Price Data'!G5 -> 0 | H5: ='Cash Dividend'!H5/'Price Data'!H5 -> 0 | I5: ='Cash Dividend'!I5/'Price Data'!I5 -> 0 | J5: ='Cash Dividend'!J5/'Price Data'!J5 -> 0 | ... V5: ='Cash Dividend'!V5/'Price Data'!V5 -> 0
B6: November | C6: ='Cash Dividend'!C6/'Price Data'!C6 -> 0 | D6: ='Cash Dividend'!D6/'Price Data'!D6 -> 0 | E6: ='Cash Dividend'!E6/'Price Data'!E6 -> 0 | F6: ='Cash Dividend'!F6/'Price Data'!F6 -> 0 | G6: ='Cash Dividend'!G6/'Price Data'!G6 -> 0 | H6: ='Cash Dividend'!H6/'Price Data'!H6 -> 0 | I6: ='Cash Dividend'!I6/'Price Data'!I6 -> 0.032884903 | J6: ='Cash Dividend'!J6/'Price Data'!J6 -> 0 | ... V6: ='Cash Dividend'!V6/'Price Data'!V6 -> 0
B7: December | C7: ='Cash Dividend'!C7/'Price Data'!C7 -> 0 | D7: ='Cash Dividend'!D7/'Price Data'!D7 -> 0 | E7: ='Cash Dividend'!E7/'Price Data'!E7 -> 0 | F7: ='Cash Dividend'!F7/'Price Data'!F7 -> 0 | G7: ='Cash Dividend'!G7/'Price Data'!G7 -> 0 | H7: ='Cash Dividend'!H7/'Price Data'!H7 -> 0 | I7: ='Cash Dividend'!I7/'Price Data'!I7 -> 0 | J7: ='Cash Dividend'!J7/'Price Data'!J7 -> 0 | ... V7: ='Cash Dividend'!V7/'Price Data'!V7 -> 0
A8: 2022 | B8: January | C8: ='Cash Dividend'!C8/'Price Data'!C8 -> 0 | D8: ='Cash Dividend'!D8/'Price Data'!D8 -> 0 | E8: ='Cash Dividend'!E8/'Price Data'!E8 -> 0 | F8: ='Cash Dividend'!F8/'Price Data'!F8 -> 0 | G8: ='Cash Dividend'!G8/'Price Data'!G8 -> 0 | H8: ='Cash Dividend'!H8/'Price Data'!H8 -> 0 | I8: ='Cash Dividend'!I8/'Price Data'!I8 -> 0 | J8: ='Cash Dividend'!J8/'Price Data'!J8 -> 0 | ... V8: ='Cash Dividend'!V8/'Price Data'!V8 -> 0.071513707
B9: February | C9: ='Cash Dividend'!C9/'Price Data'!C9 -> 0 | D9: ='Cash Dividend'!D9/'Price Data'!D9 -> 0 | E9: ='Cash Dividend'!E9/'Price Data'!E9 -> 0 | F9: ='Cash Dividend'!F9/'Price Data'!F9 -> 0 | G9: ='Cash Dividend'!G9/'Price Data'!G9 -> 0 | H9: ='Cash Dividend'!H9/'Price Data'!H9 -> 0 | I9: ='Cash Dividend'!I9/'Price Data'!I9 -> 0 | J9: ='Cash Dividend'!J9/'Price Data'!J9 -> 0 | ... V9: ='Cash Dividend'!V9/'Price Data'!V9 -> 0
B10: March | C10: ='Cash Dividend'!C10/'Price Data'!C10 -> 0 | D10: ='Cash Dividend'!D10/'Price Data'!D10 -> 0 | E10: ='Cash Dividend'!E10/'Price Data'!E10 -> 0.03051106 | F10: ='Cash Dividend'!F10/'Price Data'!F10 -> 0.022865854 | G10: ='Cash Dividend'!G10/'Price Data'!G10 -> 0 | H10: ='Cash Dividend'!H10/'Price Data'!H10 -> 0 | I10: ='Cash Dividend'!I10/'Price Data'!I10 -> 0 | J10: ='Cash Dividend'!J10/'Price Data'!J10 -> 0 | ... V10: ='Cash Dividend'!V10/'Price Data'!V10 -> 0
B11: April | C11: ='Cash Dividend'!C11/'Price Data'!C11 -> 0.023205446 | D11: ='Cash Dividend'!D11/'Price Data'!D11 -> 0 | E11: ='Cash Dividend'!E11/'Price Data'!E11 -> 0 | F11: ='Cash Dividend'!F11/'Price Data'!F11 -> 0 | G11: ='Cash Dividend'!G11/'Price Data'!G11 -> 0.017513135 | H11: ='Cash Dividend'!H11/'Price Data'!H11 -> 0 | I11: ='Cash Dividend'!I11/'Price Data'!I11 -> 0 | J11: ='Cash Dividend'!J11/'Price Data'!J11 -> 0 | ... V11: ='Cash Dividend'!V11/'Price Data'!V11 -> 0
B12: May | C12: ='Cash Dividend'!C12/'Price Data'!C12 -> 0 | D12: ='Cash Dividend'!D12/'Price Data'!D12 -> 0 | E12: ='Cash Dividend'!E12/'Price Data'!E12 -> 0 | F12: ='Cash Dividend'!F12/'Price Data'!F12 -> 0 | G12: ='Cash Dividend'!G12/'Price Data'!G12 -> 0 | H12: ='Cash Dividend'!H12/'Price Data'!H12 -> 0.034682081 | I12: ='Cash Dividend'!I12/'Price Data'!I12 -> 0 | J12: ='Cash Dividend'!J12/'Price Data'!J12 -> 0 | ... V12: ='Cash Dividend'!V12/'Price Data'!V12 -> 0
B13: June | C13: ='Cash Dividend'!C13/'Price Data'!C13 -> 0 | D13: ='Cash Dividend'!D13/'Price Data'!D13 -> 0.083333333 | E13: ='Cash Dividend'!E13/'Price Data'!E13 -> 0 | F13: ='Cash Dividend'!F13/'Price Data'!F13 -> 0 | G13: ='Cash Dividend'!G13/'Price Data'!G13 -> 0 | H13: ='Cash Dividend'!H13/'Price Data'!H13 -> 0 | I13: ='Cash Dividend'!I13/'Price Data'!I13 -> 0 | J13: ='Cash Dividend'!J13/'Price Data'!J13 -> 0 | ... V13: ='Cash Dividend'!V13/'Price Data'!V13 -> 0
B14: July | C14: ='Cash Dividend'!C14/'Price Data'!C14 -> 0 | D14: ='Cash Dividend'!D14/'Price Data'!D14 -> 0 | E14: ='Cash Dividend'!E14/'Price Data'!E14 -> 0 | F14: ='Cash Dividend'!F14/'Price Data'!F14 -> 0 | G14: ='Cash Dividend'!G14/'Price Data'!G14 -> 0 | H14: ='Cash Dividend'!H14/'Price Data'!H14 -> 0 | I14: ='Cash Dividend'!I14/'Price Data'!I14 -> 0 | J14: ='Cash Dividend'!J14/'Price Data'!J14 -> 0 | ... V14: ='Cash Dividend'!V14/'Price Data'!V14 -> 0
B15: August | C15: ='Cash Dividend'!C15/'Price Data'!C15 -> 0 | D15: ='Cash Dividend'!D15/'Price Data'!D15 -> 0 | E15: ='Cash Dividend'!E15/'Price Data'!E15 -> 0 | F15: ='Cash Dividend'!F15/'Price Data'!F15 -> 0 | G15: ='Cash Dividend'!G15/'Price Data'!G15 -> 0 | H15: ='Cash Dividend'!H15/'Price Data'!H15 -> 0 | I15: ='Cash Dividend'!I15/'Price Data'!I15 -> 0 | J15: ='Cash Dividend'!J15/'Price Data'!J15 -> 0 | ... V15: ='Cash Dividend'!V15/'Price Data'!V15 -> 0
B16: September | C16: ='Cash Dividend'!C16/'Price Data'!C16 -> 0 | D16: ='Cash Dividend'!D16/'Price Data'!D16 -> 0 | E16: ='Cash Dividend'!E16/'Price Data'!E16 -> 0 | F16: ='Cash Dividend'!F16/'Price Data'!F16 -> 0 | G16: ='Cash Dividend'!G16/'Price Data'!G16 -> 0 | H16: ='Cash Dividend'!H16/'Price Data'!H16 -> 0 | I16: ='Cash Dividend'!I16/'Price Data'!I16 -> 0 | J16: ='Cash Dividend'!J16/'Price Data'!J16 -> 0 | ... V16: ='Cash Dividend'!V16/'Price Data'!V16 -> 0
B17: October | C17: ='Cash Dividend'!C17/'Price Data'!C17 -> 0 | D17: ='Cash Dividend'!D17/'Price Data'!D17 -> 0 | E17: ='Cash Dividend'!E17/'Price Data'!E17 -> 0 | F17: ='Cash Dividend'!F17/'Price Data'!F17 -> 0 | G17: ='Cash Dividend'!G17/'Price Data'!G17 -> 0 | H17: ='Cash Dividend'!H17/'Price Data'!H17 -> 0 | I17: ='Cash Dividend'!I17/'Price Data'!I17 -> 0 | J17: ='Cash Dividend'!J17/'Price Data'!J17 -> 0 | ... V17: ='Cash Dividend'!V17/'Price Data'!V17 -> 0
B18: November | C18: ='Cash Dividend'!C18/'Price Data'!C18 -> 0 | D18: ='Cash Dividend'!D18/'Price Data'!D18 -> 0 | E18: ='Cash Dividend'!E18/'Price Data'!E18 -> 0 | F18: ='Cash Dividend'!F18/'Price Data'!F18 -> 0 | G18: ='Cash Dividend'!G18/'Price Data'!G18 -> 0 | H18: ='Cash Dividend'!H18/'Price Data'!H18 -> 0 | I18: ='Cash Dividend'!I18/'Price Data'!I18 -> 0.034833091 | J18: ='Cash Dividend'!J18/'Price Data'!J18 -> 0.0025773196 | ... V18: ='Cash Dividend'!V18/'Price Data'!V18 -> 0
B19: December | C19: ='Cash Dividend'!C19/'Price Data'!C19 -> 0 | D19: ='Cash Dividend'!D19/'Price Data'!D19 -> 0 | E19: ='Cash Dividend'!E19/'Price Data'!E19 -> 0 | F19: ='Cash Dividend'!F19/'Price Data'!F19 -> 0 | G19: ='Cash Dividend'!G19/'Price Data'!G19 -> 0 | H19: ='Cash Dividend'!H19/'Price Data'!H19 -> 0 | I19: ='Cash Dividend'!I19/'Price Data'!I19 -> 0 | J19: ='Cash Dividend'!J19/'Price Data'!J19 -> 0 | ... V19: ='Cash Dividend'!V19/'Price Data'!V19 -> 0.071727436
A20: 2023 | B20: January | C20: ='Cash Dividend'!C20/'Price Data'!C20 -> 0 | D20: ='Cash Dividend'!D20/'Price Data'!D20 -> 0 | E20: ='Cash Dividend'!E20/'Price Data'!E20 -> 0 | F20: ='Cash Dividend'!F20/'Price Data'!F20 -> 0 | G20: ='Cash Dividend'!G20/'Price Data'!G20 -> 0 | H20: ='Cash Dividend'!H20/'Price Data'!H20 -> 0 | I20: ='Cash Dividend'!I20/'Price Data'!I20 -> 0 | J20: ='Cash Dividend'!J20/'Price Data'!J20 -> 0 | ... V20: ='Cash Dividend'!V20/'Price Data'!V20 -> 0
B21: February | C21: ='Cash Dividend'!C21/'Price Data'!C21 -> 0 | D21: ='Cash Dividend'!D21/'Price Data'!D21 -> 0 | E21: ='Cash Dividend'!E21/'Price Data'!E21 -> 0 | F21: ='Cash Dividend'!F21/'Price Data'!F21 -> 0 | G21: ='Cash Dividend'!G21/'Price Data'!G21 -> 0 | H21: ='Cash Dividend'!H21/'Price Data'!H21 -> 0 | I21: ='Cash Dividend'!I21/'Price Data'!I21 -> 0 | J21: ='Cash Dividend'!J21/'Price Data'!J21 -> 0 | ... V21: ='Cash Dividend'!V21/'Price Data'!V21 -> 0
B22: March | C22: ='Cash Dividend'!C22/'Price Data'!C22 -> 0 | D22: ='Cash Dividend'!D22/'Price Data'!D22 -> 0 | E22: ='Cash Dividend'!E22/'Price Data'!E22 -> 0.018228217 | F22: ='Cash Dividend'!F22/'Price Data'!F22 -> 0 | G22: ='Cash Dividend'!G22/'Price Data'!G22 -> 0 | H22: ='Cash Dividend'!H22/'Price Data'!H22 -> 0 | I22: ='Cash Dividend'!I22/'Price Data'!I22 -> 0 | J22: ='Cash Dividend'!J22/'Price Data'!J22 -> 0 | ... V22: ='Cash Dividend'!V22/'Price Data'!V22 -> 0
B23: April | C23: ='Cash Dividend'!C23/'Price Data'!C23 -> 0 | D23: ='Cash Dividend'!D23/'Price Data'!D23 -> 0 | E23: ='Cash Dividend'!E23/'Price Data'!E23 -> 0 | F23: ='Cash Dividend'!F23/'Price Data'!F23 -> 0.026455026 | G23: ='Cash Dividend'!G23/'Price Data'!G23 -> 0 | H23: ='Cash Dividend'!H23/'Price Data'!H23 -> 0 | I23: ='Cash Dividend'!I23/'Price Data'!I23 -> 0 | J23: ='Cash Dividend'!J23/'Price Data'!J23 -> 0 | ... V23: ='Cash Dividend'!V23/'Price Data'!V23 -> 0
B24: May | C24: ='Cash Dividend'!C24/'Price Data'!C24 -> 0.029809221 | D24: ='Cash Dividend'!D24/'Price Data'!D24 -> 0 | E24: ='Cash Dividend'!E24/'Price Data'!E24 -> 0 | F24: ='Cash Dividend'!F24/'Price Data'!F24 -> 0 | G24: ='Cash Dividend'!G24/'Price Data'!G24 -> 0.017271157 | H24: ='Cash Dividend'!H24/'Price Data'!H24 -> 0.027322404 | I24: ='Cash Dividend'!I24/'Price Data'!I24 -> 0 | J24: ='Cash Dividend'!J24/'Price Data'!J24 -> 0 | ... V24: ='Cash Dividend'!V24/'Price Data'!V24 -> 0
B25: June | C25: ='Cash Dividend'!C25/'Price Data'!C25 -> 0 | D25: ='Cash Dividend'!D25/'Price Data'!D25 -> 0.038167939 | E25: ='Cash Dividend'!E25/'Price Data'!E25 -> 0 | F25: ='Cash Dividend'!F25/'Price Data'!F25 -> 0 | G25: ='Cash Dividend'!G25/'Price Data'!G25 -> 0 | H25: ='Cash Dividend'!H25/'Price Data'!H25 -> 0 | I25: ='Cash Dividend'!I25/'Price Data'!I25 -> 0 | J25: ='Cash Dividend'!J25/'Price Data'!J25 -> 0 | ... V25: ='Cash Dividend'!V25/'Price Data'!V25 -> 0
B26: July | C26: ='Cash Dividend'!C26/'Price Data'!C26 -> 0 | D26: ='Cash Dividend'!D26/'Price Data'!D26 -> 0 | E26: ='Cash Dividend'!E26/'Price Data'!E26 -> 0 | F26: ='Cash Dividend'!F26/'Price Data'!F26 -> 0 | G26: ='Cash Dividend'!G26/'Price Data'!G26 -> 0 | H26: ='Cash Dividend'!H26/'Price Data'!H26 -> 0 | I26: ='Cash Dividend'!I26/'Price Data'!I26 -> 0 | J26: ='Cash Dividend'!J26/'Price Data'!J26 -> 0 | ... V26: ='Cash Dividend'!V26/'Price Data'!V26 -> 0
B27: August | C27: ='Cash Dividend'!C27/'Price Data'!C27 -> 0 | D27: ='Cash Dividend'!D27/'Price Data'!D27 -> 0 | E27: ='Cash Dividend'!E27/'Price Data'!E27 -> 0 | F27: ='Cash Dividend'!F27/'Price Data'!F27 -> 0 | G27: ='Cash Dividend'!G27/'Price Data'!G27 -> 0 | H27: ='Cash Dividend'!H27/'Price Data'!H27 -> 0 | I27: ='Cash Dividend'!I27/'Price Data'!I27 -> 0 | J27: ='Cash Dividend'!J27/'Price Data'!J27 -> 0 | ... V27: ='Cash Dividend'!V27/'Price Data'!V27 -> 0
B28: September | C28: ='Cash Dividend'!C28/'Price Data'!C28 -> 0 | D28: ='Cash Dividend'!D28/'Price Data'!D28 -> 0 | E28: ='Cash Dividend'!E28/'Price Data'!E28 -> 0 | F28: ='Cash Dividend'!F28/'Price Data'!F28 -> 0 | G28: ='Cash Dividend'!G28/'Price Data'!G28 -> 0 | H28: ='Cash Dividend'!H28/'Price Data'!H28 -> 0 | I28: ='Cash Dividend'!I28/'Price Data'!I28 -> 0 | J28: ='Cash Dividend'!J28/'Price Data'!J28 -> 0 | ... V28: ='Cash Dividend'!V28/'Price Data'!V28 -> 0
B29: October | C29: ='Cash Dividend'!C29/'Price Data'!C29 -> 0 | D29: ='Cash Dividend'!D29/'Price Data'!D29 -> 0 | E29: ='Cash Dividend'!E29/'Price Data'!E29 -> 0 | F29: ='Cash Dividend'!F29/'Price Data'!F29 -> 0 | G29: ='Cash Dividend'!G29/'Price Data'!G29 -> 0 | H29: ='Cash Dividend'!H29/'Price Data'!H29 -> 0 | I29: ='Cash Dividend'!I29/'Price Data'!I29 -> 0 | J29: ='Cash Dividend'!J29/'Price Data'!J29 -> 0 | ... V29: ='Cash Dividend'!V29/'Price Data'!V29 -> 0
B30: November | C30: ='Cash Dividend'!C30/'Price Data'!C30 -> 0 | D30: ='Cash Dividend'!D30/'Price Data'!D30 -> 0 | E30: ='Cash Dividend'!E30/'Price Data'!E30 -> 0 | F30: ='Cash Dividend'!F30/'Price Data'!F30 -> 0 | G30: ='Cash Dividend'!G30/'Price Data'!G30 -> 0 | H30: ='Cash Dividend'!H30/'Price Data'!H30 -> 0 | I30: ='Cash Dividend'!I30/'Price Data'!I30 -> 0.029027576 | J30: ='Cash Dividend'!J30/'Price Data'!J30 -> 0.0010179153 | ... V30: ='Cash Dividend'!V30/'Price Data'!V30 -> 0
B31: December | C31: ='Cash Dividend'!C31/'Price Data'!C31 -> 0 | D31: ='Cash Dividend'!D31/'Price Data'!D31 -> 0 | E31: ='Cash Dividend'!E31/'Price Data'!E31 -> 0 | F31: ='Cash Dividend'!F31/'Price Data'!F31 -> 0 | G31: ='Cash Dividend'!G31/'Price Data'!G31 -> 0 | H31: ='Cash Dividend'!H31/'Price Data'!H31 -> 0 | I31: ='Cash Dividend'!I31/'Price Data'!I31 -> 0 | J31: ='Cash Dividend'!J31/'Price Data'!J31 -> 0 | ... V31: ='Cash Dividend'!V31/'Price Data'!V31 -> 0.077151335
A32: 2024 | B32: January | C32: ='Cash Dividend'!C32/'Price Data'!C32 -> 0 | D32: ='Cash Dividend'!D32/'Price Data'!D32 -> 0 | E32: ='Cash Dividend'!E32/'Price Data'!E32 -> 0 | F32: ='Cash Dividend'!F32/'Price Data'!F32 -> 0 | G32: ='Cash Dividend'!G32/'Price Data'!G32 -> 0 | H32: ='Cash Dividend'!H32/'Price Data'!H32 -> 0 | I32: ='Cash Dividend'!I32/'Price Data'!I32 -> 0 | J32: ='Cash Dividend'!J32/'Price Data'!J32 -> 0 | ... V32: ='Cash Dividend'!V32/'Price Data'!V32 -> 0
B33: February | C33: ='Cash Dividend'!C33/'Price Data'!C33 -> 0 | D33: ='Cash Dividend'!D33/'Price Data'!D33 -> 0 | E33: ='Cash Dividend'!E33/'Price Data'!E33 -> 0 | F33: ='Cash Dividend'!F33/'Price Data'!F33 -> 0 | G33: ='Cash Dividend'!G33/'Price Data'!G33 -> 0 | H33: ='Cash Dividend'!H33/'Price Data'!H33 -> 0 | I33: ='Cash Dividend'!I33/'Price Data'!I33 -> 0 | J33: ='Cash Dividend'!J33/'Price Data'!J33 -> 0 | ... V33: ='Cash Dividend'!V33/'Price Data'!V33 -> 0
B34: March | C34: ='Cash Dividend'!C34/'Price Data'!C34 -> 0 | D34: ='Cash Dividend'!D34/'Price Data'!D34 -> 0 | E34: ='Cash Dividend'!E34/'Price Data'!E34 -> 0 | F34: ='Cash Dividend'!F34/'Price Data'!F34 -> 0 | G34: ='Cash Dividend'!G34/'Price Data'!G34 -> 0 | H34: ='Cash Dividend'!H34/'Price Data'!H34 -> 0 | I34: ='Cash Dividend'!I34/'Price Data'!I34 -> 0 | J34: ='Cash Dividend'!J34/'Price Data'!J34 -> 0 | ... V34: ='Cash Dividend'!V34/'Price Data'!V34 -> 0
B35: April | C35: ='Cash Dividend'!C35/'Price Data'!C35 -> 0 | D35: ='Cash Dividend'!D35/'Price Data'!D35 -> 0 | E35: ='Cash Dividend'!E35/'Price Data'!E35 -> 0.024084778 | F35: ='Cash Dividend'!F35/'Price Data'!F35 -> 0.040431267 | G35: ='Cash Dividend'!G35/'Price Data'!G35 -> 0 | H35: ='Cash Dividend'!H35/'Price Data'!H35 -> 0 | I35: ='Cash Dividend'!I35/'Price Data'!I35 -> 0 | J35: ='Cash Dividend'!J35/'Price Data'!J35 -> 0 | ... V35: ='Cash Dividend'!V35/'Price Data'!V35 -> 0
B36: May | C36: ='Cash Dividend'!C36/'Price Data'!C36 -> 0.038387716 | D36: ='Cash Dividend'!D36/'Price Data'!D36 -> 0 | E36: ='Cash Dividend'!E36/'Price Data'!E36 -> 0 | F36: ='Cash Dividend'!F36/'Price Data'!F36 -> 0 | G36: ='Cash Dividend'!G36/'Price Data'!G36 -> 0.018315018 | H36: ='Cash Dividend'!H36/'Price Data'!H36 -> 0.030534351 | I36: ='Cash Dividend'!I36/'Price Data'!I36 -> 0 | J36: ='Cash Dividend'!J36/'Price Data'!J36 -> 0 | ... V36: ='Cash Dividend'!V36/'Price Data'!V36 -> 0
B37: June | C37: ='Cash Dividend'!C37/'Price Data'!C37 -> 0 | D37: ='Cash Dividend'!D37/'Price Data'!D37 -> 0.12244898 | E37: ='Cash Dividend'!E37/'Price Data'!E37 -> 0 | F37: ='Cash Dividend'!F37/'Price Data'!F37 -> 0 | G37: ='Cash Dividend'!G37/'Price Data'!G37 -> 0 | H37: ='Cash Dividend'!H37/'Price Data'!H37 -> 0 | I37: ='Cash Dividend'!I37/'Price Data'!I37 -> 0 | J37: ='Cash Dividend'!J37/'Price Data'!J37 -> 0 | ... V37: ='Cash Dividend'!V37/'Price Data'!V37 -> 0
B38: July | C38: ='Cash Dividend'!C38/'Price Data'!C38 -> 0 | D38: ='Cash Dividend'!D38/'Price Data'!D38 -> 0 | E38: ='Cash Dividend'!E38/'Price Data'!E38 -> 0 | F38: ='Cash Dividend'!F38/'Price Data'!F38 -> 0 | G38: ='Cash Dividend'!G38/'Price Data'!G38 -> 0 | H38: ='Cash Dividend'!H38/'Price Data'!H38 -> 0 | I38: ='Cash Dividend'!I38/'Price Data'!I38 -> 0 | J38: ='Cash Dividend'!J38/'Price Data'!J38 -> 0 | ... V38: ='Cash Dividend'!V38/'Price Data'!V38 -> 0
B39: August | C39: ='Cash Dividend'!C39/'Price Data'!C39 -> 0 | D39: ='Cash Dividend'!D39/'Price Data'!D39 -> 0 | E39: ='Cash Dividend'!E39/'Price Data'!E39 -> 0 | F39: ='Cash Dividend'!F39/'Price Data'!F39 -> 0 | G39: ='Cash Dividend'!G39/'Price Data'!G39 -> 0 | H39: ='Cash Dividend'!H39/'Price Data'!H39 -> 0 | I39: ='Cash Dividend'!I39/'Price Data'!I39 -> 0 | J39: ='Cash Dividend'!J39/'Price Data'!J39 -> 0 | ... V39: ='Cash Dividend'!V39/'Price Data'!V39 -> 0
B40: September | C40: ='Cash Dividend'!C40/'Price Data'!C40 -> 0 | D40: ='Cash Dividend'!D40/'Price Data'!D40 -> 0 | E40: ='Cash Dividend'!E40/'Price Data'!E40 -> 0 | F40: ='Cash Dividend'!F40/'Price Data'!F40 -> 0 | G40: ='Cash Dividend'!G40/'Price Data'!G40 -> 0 | H40: ='Cash Dividend'!H40/'Price Data'!H40 -> 0 | I40: ='Cash Dividend'!I40/'Price Data'!I40 -> 0 | J40: ='Cash Dividend'!J40/'Price Data'!J40 -> 0 | ... V40: ='Cash Dividend'!V40/'Price Data'!V40 -> 0
B41: October | C41: ='Cash Dividend'!C41/'Price Data'!C41 -> 0 | D41: ='Cash Dividend'!D41/'Price Data'!D41 -> 0 | E41: ='Cash Dividend'!E41/'Price Data'!E41 -> 0 | F41: ='Cash Dividend'!F41/'Price Data'!F41 -> 0 | G41: ='Cash Dividend'!G41/'Price Data'!G41 -> 0 | H41: ='Cash Dividend'!H41/'Price Data'!H41 -> 0 | I41: ='Cash Dividend'!I41/'Price Data'!I41 -> 0 | J41: ='Cash Dividend'!J41/'Price Data'!J41 -> 0 | ... V41: ='Cash Dividend'!V41/'Price Data'!V41 -> 0
B42: November | C42: ='Cash Dividend'!C42/'Price Data'!C42 -> 0 | D42: ='Cash Dividend'!D42/'Price Data'!D42 -> 0 | E42: ='Cash Dividend'!E42/'Price Data'!E42 -> 0 | F42: ='Cash Dividend'!F42/'Price Data'!F42 -> 0 | G42: ='Cash Dividend'!G42/'Price Data'!G42 -> 0 | H42: ='Cash Dividend'!H42/'Price Data'!H42 -> 0 | I42: ='Cash Dividend'!I42/'Price Data'!I42 -> 0.011223345 | J42: ='Cash Dividend'!J42/'Price Data'!J42 -> 0 | ... V42: ='Cash Dividend'!V42/'Price Data'!V42 -> 0
B43: December | C43: ='Cash Dividend'!C43/'Price Data'!C43 -> 0 | D43: ='Cash Dividend'!D43/'Price Data'!D43 -> 0 | E43: ='Cash Dividend'!E43/'Price Data'!E43 -> 0 | F43: ='Cash Dividend'!F43/'Price Data'!F43 -> 0 | G43: ='Cash Dividend'!G43/'Price Data'!G43 -> 0 | H43: ='Cash Dividend'!H43/'Price Data'!H43 -> 0 | I43: ='Cash Dividend'!I43/'Price Data'!I43 -> 0 | J43: ='Cash Dividend'!J43/'Price Data'!J43 -> 0.0044385264 | ... V43: ='Cash Dividend'!V43/'Price Data'!V43 -> 0.087514586
A44: 2025 | B44: January | C44: ='Cash Dividend'!C44/'Price Data'!C44 -> 0 | D44: ='Cash Dividend'!D44/'Price Data'!D44 -> 0 | E44: ='Cash Dividend'!E44/'Price Data'!E44 -> 0 | F44: ='Cash Dividend'!F44/'Price Data'!F44 -> 0 | G44: ='Cash Dividend'!G44/'Price Data'!G44 -> 0 | H44: ='Cash Dividend'!H44/'Price Data'!H44 -> 0 | I44: ='Cash Dividend'!I44/'Price Data'!I44 -> 0 | J44: ='Cash Dividend'!J44/'Price Data'!J44 -> 0 | ... V44: ='Cash Dividend'!V44/'Price Data'!V44 -> 0
B45: February | C45: ='Cash Dividend'!C45/'Price Data'!C45 -> 0 | D45: ='Cash Dividend'!D45/'Price Data'!D45 -> 0 | E45: ='Cash Dividend'!E45/'Price Data'!E45 -> 0 | F45: ='Cash Dividend'!F45/'Price Data'!F45 -> 0 | G45: ='Cash Dividend'!G45/'Price Data'!G45 -> 0 | H45: ='Cash Dividend'!H45/'Price Data'!H45 -> 0 | I45: ='Cash Dividend'!I45/'Price Data'!I45 -> 0 | J45: ='Cash Dividend'!J45/'Price Data'!J45 -> 0 | ... V45: ='Cash Dividend'!V45/'Price Data'!V45 -> 0
B46: March | C46: ='Cash Dividend'!C46/'Price Data'!C46 -> 0 | D46: ='Cash Dividend'!D46/'Price Data'!D46 -> 0 | E46: ='Cash Dividend'!E46/'Price Data'!E46 -> 0 | F46: ='Cash Dividend'!F46/'Price Data'!F46 -> 0 | G46: ='Cash Dividend'!G46/'Price Data'!G46 -> 0 | H46: ='Cash Dividend'!H46/'Price Data'!H46 -> 0 | I46: ='Cash Dividend'!I46/'Price Data'!I46 -> 0 | J46: ='Cash Dividend'!J46/'Price Data'!J46 -> 0 | ... V46: ='Cash Dividend'!V46/'Price Data'!V46 -> 0
B47: April | C47: ='Cash Dividend'!C47/'Price Data'!C47 -> 0 | D47: ='Cash Dividend'!D47/'Price Data'!D47 -> 0 | E47: ='Cash Dividend'!E47/'Price Data'!E47 -> 0 | F47: ='Cash Dividend'!F47/'Price Data'!F47 -> 0 | G47: ='Cash Dividend'!G47/'Price Data'!G47 -> 0.028735632 | H47: ='Cash Dividend'!H47/'Price Data'!H47 -> 0 | I47: ='Cash Dividend'!I47/'Price Data'!I47 -> 0 | J47: ='Cash Dividend'!J47/'Price Data'!J47 -> 0 | ... V47: ='Cash Dividend'!V47/'Price Data'!V47 -> 0
B48: May | C48: ='Cash Dividend'!C48/'Price Data'!C48 -> 0.03125 | D48: ='Cash Dividend'!D48/'Price Data'!D48 -> 0.13265306 | E48: ='Cash Dividend'!E48/'Price Data'!E48 -> 0.036231884 | F48: ='Cash Dividend'!F48/'Price Data'!F48 -> 0.046875 | G48: ='Cash Dividend'!G48/'Price Data'!G48 -> 0 | H48: ='Cash Dividend'!H48/'Price Data'!H48 -> 0 | I48: ='Cash Dividend'!I48/'Price Data'!I48 -> 0 | J48: ='Cash Dividend'!J48/'Price Data'!J48 -> 0 | ... V48: ='Cash Dividend'!V48/'Price Data'!V48 -> 0
B49: June | C49: ='Cash Dividend'!C49/'Price Data'!C49 -> 0 | D49: ='Cash Dividend'!D49/'Price Data'!D49 -> 0 | E49: ='Cash Dividend'!E49/'Price Data'!E49 -> 0 | F49: ='Cash Dividend'!F49/'Price Data'!F49 -> 0 | G49: ='Cash Dividend'!G49/'Price Data'!G49 -> 0 | H49: ='Cash Dividend'!H49/'Price Data'!H49 -> 0.034602076 | I49: ='Cash Dividend'!I49/'Price Data'!I49 -> 0 | J49: ='Cash Dividend'!J49/'Price Data'!J49 -> 0 | ... V49: ='Cash Dividend'!V49/'Price Data'!V49 -> 0
B50: July | C50: ='Cash Dividend'!C50/'Price Data'!C50 -> 0 | D50: ='Cash Dividend'!D50/'Price Data'!D50 -> 0 | E50: ='Cash Dividend'!E50/'Price Data'!E50 -> 0 | F50: ='Cash Dividend'!F50/'Price Data'!F50 -> 0 | G50: ='Cash Dividend'!G50/'Price Data'!G50 -> 0 | H50: ='Cash Dividend'!H50/'Price Data'!H50 -> 0 | I50: ='Cash Dividend'!I50/'Price Data'!I50 -> 0 | J50: ='Cash Dividend'!J50/'Price Data'!J50 -> 0 | ... V50: ='Cash Dividend'!V50/'Price Data'!V50 -> 0
B51: August | C51: ='Cash Dividend'!C51/'Price Data'!C51 -> 0 | D51: ='Cash Dividend'!D51/'Price Data'!D51 -> 0 | E51: ='Cash Dividend'!E51/'Price Data'!E51 -> 0 | F51: ='Cash Dividend'!F51/'Price Data'!F51 -> 0 | G51: ='Cash Dividend'!G51/'Price Data'!G51 -> 0 | H51: ='Cash Dividend'!H51/'Price Data'!H51 -> 0 | I51: ='Cash Dividend'!I51/'Price Data'!I51 -> 0 | J51: ='Cash Dividend'!J51/'Price Data'!J51 -> 0 | ... V51: ='Cash Dividend'!V51/'Price Data'!V51 -> 0
B52: September | C52: ='Cash Dividend'!C52/'Price Data'!C52 -> 0 | D52: ='Cash Dividend'!D52/'Price Data'!D52 -> 0 | E52: ='Cash Dividend'!E52/'Price Data'!E52 -> 0 | F52: ='Cash Dividend'!F52/'Price Data'!F52 -> 0 | G52: ='Cash Dividend'!G52/'Price Data'!G52 -> 0 | H52: ='Cash Dividend'!H52/'Price Data'!H52 -> 0 | I52: ='Cash Dividend'!I52/'Price Data'!I52 -> 0 | J52: ='Cash Dividend'!J52/'Price Data'!J52 -> 0 | ... V52: ='Cash Dividend'!V52/'Price Data'!V52 -> 0
B53: October | C53: ='Cash Dividend'!C53/'Price Data'!C53 -> 0 | D53: ='Cash Dividend'!D53/'Price Data'!D53 -> 0 | E53: ='Cash Dividend'!E53/'Price Data'!E53 -> 0 | F53: ='Cash Dividend'!F53/'Price Data'!F53 -> 0 | G53: ='Cash Dividend'!G53/'Price Data'!G53 -> 0 | H53: ='Cash Dividend'!H53/'Price Data'!H53 -> 0 | I53: ='Cash Dividend'!I53/'Price Data'!I53 -> 0 | J53: ='Cash Dividend'!J53/'Price Data'!J53 -> 0 | ... V53: ='Cash Dividend'!V53/'Price Data'!V53 -> 0
B54: November | C54: ='Cash Dividend'!C54/'Price Data'!C54 -> 0 | D54: ='Cash Dividend'!D54/'Price Data'!D54 -> 0 | E54: ='Cash Dividend'!E54/'Price Data'!E54 -> 0 | F54: ='Cash Dividend'!F54/'Price Data'!F54 -> 0 | G54: ='Cash Dividend'!G54/'Price Data'!G54 -> 0 | H54: ='Cash Dividend'!H54/'Price Data'!H54 -> 0 | I54: ='Cash Dividend'!I54/'Price Data'!I54 -> 0.015471167 | J54: ='Cash Dividend'!J54/'Price Data'!J54 -> 0.0044388079 | ... V54: ='Cash Dividend'!V54/'Price Data'!V54 -> 0
B55: December | C55: ='Cash Dividend'!C55/'Price Data'!C55 -> 0 | D55: ='Cash Dividend'!D55/'Price Data'!D55 -> 0 | E55: ='Cash Dividend'!E55/'Price Data'!E55 -> 0 | F55: ='Cash Dividend'!F55/'Price Data'!F55 -> 0 | G55: ='Cash Dividend'!G55/'Price Data'!G55 -> 0 | H55: ='Cash Dividend'!H55/'Price Data'!H55 -> 0 | I55: ='Cash Dividend'!I55/'Price Data'!I55 -> 0 | J55: ='Cash Dividend'!J55/'Price Data'!J55 -> 0 | ... V55: ='Cash Dividend'!V55/'Price Data'!V55 -> 0.10720667
A56: 2026 | B56: January | C56: ='Cash Dividend'!C56/'Price Data'!C56 -> 0 | D56: ='Cash Dividend'!D56/'Price Data'!D56 -> 0 | E56: ='Cash Dividend'!E56/'Price Data'!E56 -> 0 | F56: ='Cash Dividend'!F56/'Price Data'!F56 -> 0 | G56: ='Cash Dividend'!G56/'Price Data'!G56 -> 0 | H56: ='Cash Dividend'!H56/'Price Data'!H56 -> 0 | I56: ='Cash Dividend'!I56/'Price Data'!I56 -> 0 | J56: ='Cash Dividend'!J56/'Price Data'!J56 -> 0 | ... V56: ='Cash Dividend'!V56/'Price Data'!V56 -> 0
B57: February | C57: ='Cash Dividend'!C57/'Price Data'!C57 -> 0 | D57: ='Cash Dividend'!D57/'Price Data'!D57 -> 0 | E57: ='Cash Dividend'!E57/'Price Data'!E57 -> 0 | F57: ='Cash Dividend'!F57/'Price Data'!F57 -> 0 | G57: ='Cash Dividend'!G57/'Price Data'!G57 -> 0 | H57: ='Cash Dividend'!H57/'Price Data'!H57 -> 0 | I57: ='Cash Dividend'!I57/'Price Data'!I57 -> 0 | J57: ='Cash Dividend'!J57/'Price Data'!J57 -> 0 | ... V57: ='Cash Dividend'!V57/'Price Data'!V57 -> 0
B58: March | C58: ='Cash Dividend'!C58/'Price Data'!C58 -> 0 | D58: ='Cash Dividend'!D58/'Price Data'!D58 -> 0 | E58: ='Cash Dividend'!E58/'Price Data'!E58 -> 0 | F58: ='Cash Dividend'!F58/'Price Data'!F58 -> 0 | G58: ='Cash Dividend'!G58/'Price Data'!G58 -> 0 | H58: ='Cash Dividend'!H58/'Price Data'!H58 -> 0 | I58: ='Cash Dividend'!I58/'Price Data'!I58 -> 0 | J58: ='Cash Dividend'!J58/'Price Data'!J58 -> 0 | ... V58: ='Cash Dividend'!V58/'Price Data'!V58 -> 0
B59: April | C59: ='Cash Dividend'!C59/'Price Data'!C59 -> 0 | D59: ='Cash Dividend'!D59/'Price Data'!D59 -> 0 | E59: ='Cash Dividend'!E59/'Price Data'!E59 -> 0 | F59: ='Cash Dividend'!F59/'Price Data'!F59 -> 0 | G59: ='Cash Dividend'!G59/'Price Data'!G59 -> 0.018832392 | H59: ='Cash Dividend'!H59/'Price Data'!H59 -> 0 | I59: ='Cash Dividend'!I59/'Price Data'!I59 -> 0 | J59: ='Cash Dividend'!J59/'Price Data'!J59 -> 0 | ... V59: ='Cash Dividend'!V59/'Price Data'!V59 -> 0
B60: May | C60: ='Cash Dividend'!C60/'Price Data'!C60 -> 0.022288262 | D60: ='Cash Dividend'!D60/'Price Data'!D60 -> 0.11643836 | E60: ='Cash Dividend'!E60/'Price Data'!E60 -> 0 | F60: ='Cash Dividend'!F60/'Price Data'!F60 -> 0 | G60: ='Cash Dividend'!G60/'Price Data'!G60 -> 0 | H60: ='Cash Dividend'!H60/'Price Data'!H60 -> 0.033333333 | I60: ='Cash Dividend'!I60/'Price Data'!I60 -> 0 | J60: ='Cash Dividend'!J60/'Price Data'!J60 -> 0 | ... V60: ='Cash Dividend'!V60/'Price Data'!V60 -> 0
B61: June | C61: ='Cash Dividend'!C61/'Price Data'!C61 -> 0 | D61: ='Cash Dividend'!D61/'Price Data'!D61 -> 0 | E61: ='Cash Dividend'!E61/'Price Data'!E61 -> 0.015197568 | F61: ='Cash Dividend'!F61/'Price Data'!F61 -> 0.036585366 | G61: ='Cash Dividend'!G61/'Price Data'!G61 -> 0 | H61: ='Cash Dividend'!H61/'Price Data'!H61 -> 0 | I61: ='Cash Dividend'!I61/'Price Data'!I61 -> 0 | J61: ='Cash Dividend'!J61/'Price Data'!J61 -> 0 | ... V61: ='Cash Dividend'!V61/'Price Data'!V61 -> 0
B62: July | C62: ='Cash Dividend'!C62/'Price Data'!C62 -> 0 | D62: ='Cash Dividend'!D62/'Price Data'!D62 -> 0 | E62: ='Cash Dividend'!E62/'Price Data'!E62 -> 0 | F62: ='Cash Dividend'!F62/'Price Data'!F62 -> 0 | G62: ='Cash Dividend'!G62/'Price Data'!G62 -> 0 | H62: ='Cash Dividend'!H62/'Price Data'!H62 -> 0 | I62: ='Cash Dividend'!I62/'Price Data'!I62 -> 0 | J62: ='Cash Dividend'!J62/'Price Data'!J62 -> 0 | ... V62: ='Cash Dividend'!V62/'Price Data'!V62 -> 0
B63: August | C63: ='Cash Dividend'!C63/'Price Data'!C63 -> 0 | D63: ='Cash Dividend'!D63/'Price Data'!D63 -> 0 | E63: ='Cash Dividend'!E63/'Price Data'!E63 -> 0 | F63: ='Cash Dividend'!F63/'Price Data'!F63 -> 0 | G63: ='Cash Dividend'!G63/'Price Data'!G63 -> 0 | H63: ='Cash Dividend'!H63/'Price Data'!H63 -> 0 | I63: ='Cash Dividend'!I63/'Price Data'!I63 -> 0 | J63: ='Cash Dividend'!J63/'Price Data'!J63 -> 0 | ... V63: ='Cash Dividend'!V63/'Price Data'!V63 -> 0

Sheet Capital Gain
C1: Bank | E1: Financial Institutions | G1: Insurance | I1: Food & Allied | L1: Miscellaneous | M1: Tannery | N1: Cement | O1: Telecommunication | P1: Pharmacuticals & Chemicals | T1: Engineering | U1: IT Sector | V1: Fuel & Power
A2: Years | B2: Months | C2: BRACBANK | D2: NCC | E2: IPDC | F2: DBH | G2: PARAMOUNT | H2: ASIAPACINS | I2: LOVELLO | J2: FINEFOODS | K2: OLYMPIC | L2: INDEXAGRO | M2: APEXFOOT | N2: CONFIDCEM | O2: GP | P2: IBNSINA | Q2: RENATA | R2: MARICO | S2: RECKITTBEN | T2: KDSALTD | U2: ADNTEL | V2: JAMUNAOIL
A3: 2021 | B3: August
B4: September | C4: =('Price Data'!C4*(1+'Stock Dividend'!C4+'Right Share Ratio'!C4)*Split!C4-'Price Data'!C3-'Right Share Ratio'!C4*'Right Share Offer Price'!C4*Split!C4)/'Price Data'!C3 -> 0.010392985 | D4: =('Price Data'!D4*(1+'Stock Dividend'!D4+'Right Share Ratio'!D4)*Split!D4-'Price Data'!D3-'Right Share Ratio'!D4*'Right Share Offer Price'!D4*Split!D4)/'Price Data'!D3 -> 0.0064102564 | E4: =('Price Data'!E4*(1+'Stock Dividend'!E4+'Right Share Ratio'!E4)*Split!E4-'Price Data'!E3-'Right Share Ratio'!E4*'Right Share Offer Price'!E4*Split!E4)/'Price Data'!E3 -> 0.25583288 | F4: =('Price Data'!F4*(1+'Stock Dividend'!F4+'Right Share Ratio'!F4)*Split!F4-'Price Data'!F3-'Right Share Ratio'!F4*'Right Share Offer Price'!F4*Split!F4)/'Price Data'!F3 -> 0.049779205 | G4: =('Price Data'!G4*(1+'Stock Dividend'!G4+'Right Share Ratio'!G4)*Split!G4-'Price Data'!G3-'Right Share Ratio'!G4*'Right Share Offer Price'!G4*Split!G4)/'Price Data'!G3 -> -0.063901345 | H4: =('Price Data'!H4*(1+'Stock Dividend'!H4+'Right Share Ratio'!H4)*Split!H4-'Price Data'!H3-'Right Share Ratio'!H4*'Right Share Offer Price'!H4*Split!H4)/'Price Data'!H3 -> -0.032394366 | I4: =('Price Data'!I4*(1+'Stock Dividend'!I4+'Right Share Ratio'!I4)*Split!I4-'Price Data'!I3-'Right Share Ratio'!I4*'Right Share Offer Price'!I4*Split!I4)/'Price Data'!I3 -> 0.05820275 | J4: =('Price Data'!J4*(1+'Stock Dividend'!J4+'Right Share Ratio'!J4)*Split!J4-'Price Data'!J3-'Right Share Ratio'!J4*'Right Share Offer Price'!J4*Split!J4)/'Price Data'!J3 -> -0.049557522 | ... V4: =('Price Data'!V4*(1+'Stock Dividend'!V4+'Right Share Ratio'!V4)*Split!V4-'Price Data'!V3-'Right Share Ratio'!V4*'Right Share Offer Price'!V4*Split!V4)/'Price Data'!V3 -> 0.0054674686
B5: October | C5: =('Price Data'!C5*(1+'Stock Dividend'!C5+'Right Share Ratio'!C5)*Split!C5-'Price Data'!C4-'Right Share Ratio'!C5*'Right Share Offer Price'!C5*Split!C5)/'Price Data'!C4 -> -0.037608486 | D5: =('Price Data'!D5*(1+'Stock Dividend'!D5+'Right Share Ratio'!D5)*Split!D5-'Price Data'!D4-'Right Share Ratio'!D5*'Right Share Offer Price'!D5*Split!D5)/'Price Data'!D4 -> -0.012738854 | E5: =('Price Data'!E5*(1+'Stock Dividend'!E5+'Right Share Ratio'!E5)*Split!E5-'Price Data'!E4-'Right Share Ratio'!E5*'Right Share Offer Price'!E5*Split!E5)/'Price Data'!E4 -> -0.14625189 | F5: =('Price Data'!F5*(1+'Stock Dividend'!F5+'Right Share Ratio'!F5)*Split!F5-'Price Data'!F4-'Right Share Ratio'!F5*'Right Share Offer Price'!F5*Split!F5)/'Price Data'!F4 -> -0.070618228 | G5: =('Price Data'!G5*(1+'Stock Dividend'!G5+'Right Share Ratio'!G5)*Split!G5-'Price Data'!G4-'Right Share Ratio'!G5*'Right Share Offer Price'!G5*Split!G5)/'Price Data'!G4 -> -0.05988024 | H5: =('Price Data'!H5*(1+'Stock Dividend'!H5+'Right Share Ratio'!H5)*Split!H5-'Price Data'!H4-'Right Share Ratio'!H5*'Right Share Offer Price'!H5*Split!H5)/'Price Data'!H4 -> -0.013100437 | I5: =('Price Data'!I5*(1+'Stock Dividend'!I5+'Right Share Ratio'!I5)*Split!I5-'Price Data'!I4-'Right Share Ratio'!I5*'Right Share Offer Price'!I5*Split!I5)/'Price Data'!I4 -> -0.022061046 | J5: =('Price Data'!J5*(1+'Stock Dividend'!J5+'Right Share Ratio'!J5)*Split!J5-'Price Data'!J4-'Right Share Ratio'!J5*'Right Share Offer Price'!J5*Split!J5)/'Price Data'!J4 -> -0.23091248 | ... V5: =('Price Data'!V5*(1+'Stock Dividend'!V5+'Right Share Ratio'!V5)*Split!V5-'Price Data'!V4-'Right Share Ratio'!V5*'Right Share Offer Price'!V5*Split!V5)/'Price Data'!V4 -> -0.057096248
B6: November | C6: =('Price Data'!C6*(1+'Stock Dividend'!C6+'Right Share Ratio'!C6)*Split!C6-'Price Data'!C5-'Right Share Ratio'!C6*'Right Share Offer Price'!C6*Split!C6)/'Price Data'!C5 -> 0.18336673 | D6: =('Price Data'!D6*(1+'Stock Dividend'!D6+'Right Share Ratio'!D6)*Split!D6-'Price Data'!D5-'Right Share Ratio'!D6*'Right Share Offer Price'!D6*Split!D6)/'Price Data'!D5 -> -0.0064516129 | E6: =('Price Data'!E6*(1+'Stock Dividend'!E6+'Right Share Ratio'!E6)*Split!E6-'Price Data'!E5-'Right Share Ratio'!E6*'Right Share Offer Price'!E6*Split!E6)/'Price Data'!E5 -> -0.057692308 | F6: =('Price Data'!F6*(1+'Stock Dividend'!F6+'Right Share Ratio'!F6)*Split!F6-'Price Data'!F5-'Right Share Ratio'!F6*'Right Share Offer Price'!F6*Split!F6)/'Price Data'!F5 -> -0.037443423 | G6: =('Price Data'!G6*(1+'Stock Dividend'!G6+'Right Share Ratio'!G6)*Split!G6-'Price Data'!G5-'Right Share Ratio'!G6*'Right Share Offer Price'!G6*Split!G6)/'Price Data'!G5 -> -0.095541401 | H6: =('Price Data'!H6*(1+'Stock Dividend'!H6+'Right Share Ratio'!H6)*Split!H6-'Price Data'!H5-'Right Share Ratio'!H6*'Right Share Offer Price'!H6*Split!H6)/'Price Data'!H5 -> -0.095870206 | I6: =('Price Data'!I6*(1+'Stock Dividend'!I6+'Right Share Ratio'!I6)*Split!I6-'Price Data'!I5-'Right Share Ratio'!I6*'Right Share Offer Price'!I6*Split!I6)/'Price Data'!I5 -> 0.03368356 | J6: =('Price Data'!J6*(1+'Stock Dividend'!J6+'Right Share Ratio'!J6)*Split!J6-'Price Data'!J5-'Right Share Ratio'!J6*'Right Share Offer Price'!J6*Split!J6)/'Price Data'!J5 -> -0.079903148 | ... V6: =('Price Data'!V6*(1+'Stock Dividend'!V6+'Right Share Ratio'!V6)*Split!V6-'Price Data'!V5-'Right Share Ratio'!V6*'Right Share Offer Price'!V6*Split!V6)/'Price Data'!V5 -> -0.01384083
B7: December | C7: =('Price Data'!C7*(1+'Stock Dividend'!C7+'Right Share Ratio'!C7)*Split!C7-'Price Data'!C6-'Right Share Ratio'!C7*'Right Share Offer Price'!C7*Split!C7)/'Price Data'!C6 -> 0.020321761 | D7: =('Price Data'!D7*(1+'Stock Dividend'!D7+'Right Share Ratio'!D7)*Split!D7-'Price Data'!D6-'Right Share Ratio'!D7*'Right Share Offer Price'!D7*Split!D7)/'Price Data'!D6 -> -0.0064935065 | E7: =('Price Data'!E7*(1+'Stock Dividend'!E7+'Right Share Ratio'!E7)*Split!E7-'Price Data'!E6-'Right Share Ratio'!E7*'Right Share Offer Price'!E7*Split!E7)/'Price Data'!E6 -> -0.012889366 | F7: =('Price Data'!F7*(1+'Stock Dividend'!F7+'Right Share Ratio'!F7)*Split!F7-'Price Data'!F6-'Right Share Ratio'!F7*'Right Share Offer Price'!F7*Split!F7)/'Price Data'!F6 -> -0.0012824166 | G7: =('Price Data'!G7*(1+'Stock Dividend'!G7+'Right Share Ratio'!G7)*Split!G7-'Price Data'!G6-'Right Share Ratio'!G7*'Right Share Offer Price'!G7*Split!G7)/'Price Data'!G6 -> 0.032394366 | H7: =('Price Data'!H7*(1+'Stock Dividend'!H7+'Right Share Ratio'!H7)*Split!H7-'Price Data'!H6-'Right Share Ratio'!H7*'Right Share Offer Price'!H7*Split!H7)/'Price Data'!H6 -> 0.11745514 | I7: =('Price Data'!I7*(1+'Stock Dividend'!I7+'Right Share Ratio'!I7)*Split!I7-'Price Data'!I6-'Right Share Ratio'!I7*'Right Share Offer Price'!I7*Split!I7)/'Price Data'!I6 -> -0.086696562 | J7: =('Price Data'!J7*(1+'Stock Dividend'!J7+'Right Share Ratio'!J7)*Split!J7-'Price Data'!J6-'Right Share Ratio'!J7*'Right Share Offer Price'!J7*Split!J7)/'Price Data'!J6 -> 0.32631579 | ... V7: =('Price Data'!V7*(1+'Stock Dividend'!V7+'Right Share Ratio'!V7)*Split!V7-'Price Data'!V6-'Right Share Ratio'!V7*'Right Share Offer Price'!V7*Split!V7)/'Price Data'!V6 -> 0.00058479532
A8: 2022 | B8: January | C8: =('Price Data'!C8*(1+'Stock Dividend'!C8+'Right Share Ratio'!C8)*Split!C8-'Price Data'!C7-'Right Share Ratio'!C8*'Right Share Offer Price'!C8*Split!C8)/'Price Data'!C7 -> -0.0019363762 | D8: =('Price Data'!D8*(1+'Stock Dividend'!D8+'Right Share Ratio'!D8)*Split!D8-'Price Data'!D7-'Right Share Ratio'!D8*'Right Share Offer Price'!D8*Split!D8)/'Price Data'!D7 -> -0.0065359477 | E8: =('Price Data'!E8*(1+'Stock Dividend'!E8+'Right Share Ratio'!E8)*Split!E8-'Price Data'!E7-'Right Share Ratio'!E8*'Right Share Offer Price'!E8*Split!E8)/'Price Data'!E7 -> 0.015505985 | F8: =('Price Data'!F8*(1+'Stock Dividend'!F8+'Right Share Ratio'!F8)*Split!F8-'Price Data'!F7-'Right Share Ratio'!F8*'Right Share Offer Price'!F8*Split!F8)/'Price Data'!F7 -> -0.00385219 | G8: =('Price Data'!G8*(1+'Stock Dividend'!G8+'Right Share Ratio'!G8)*Split!G8-'Price Data'!G7-'Right Share Ratio'!G8*'Right Share Offer Price'!G8*Split!G8)/'Price Data'!G7 -> -0.028649386 | H8: =('Price Data'!H8*(1+'Stock Dividend'!H8+'Right Share Ratio'!H8)*Split!H8-'Price Data'!H7-'Right Share Ratio'!H8*'Right Share Offer Price'!H8*Split!H8)/'Price Data'!H7 -> -0.054014599 | I8: =('Price Data'!I8*(1+'Stock Dividend'!I8+'Right Share Ratio'!I8)*Split!I8-'Price Data'!I7-'Right Share Ratio'!I8*'Right Share Offer Price'!I8*Split!I8)/'Price Data'!I7 -> 0.15155483 | J8: =('Price Data'!J8*(1+'Stock Dividend'!J8+'Right Share Ratio'!J8)*Split!J8-'Price Data'!J7-'Right Share Ratio'!J8*'Right Share Offer Price'!J8*Split!J8)/'Price Data'!J7 -> -0.071428571 | ... V8: =('Price Data'!V8*(1+'Stock Dividend'!V8+'Right Share Ratio'!V8)*Split!V8-'Price Data'!V7-'Right Share Ratio'!V8*'Right Share Offer Price'!V8*Split!V8)/'Price Data'!V7 -> -0.019286967
B9: February | C9: =('Price Data'!C9*(1+'Stock Dividend'!C9+'Right Share Ratio'!C9)*Split!C9-'Price Data'!C8-'Right Share Ratio'!C9*'Right Share Offer Price'!C9*Split!C9)/'Price Data'!C8 -> -0.021618625 | D9: =('Price Data'!D9*(1+'Stock Dividend'!D9+'Right Share Ratio'!D9)*Split!D9-'Price Data'!D8-'Right Share Ratio'!D9*'Right Share Offer Price'!D9*Split!D9)/'Price Data'!D8 -> -0.013157895 | E9: =('Price Data'!E9*(1+'Stock Dividend'!E9+'Right Share Ratio'!E9)*Split!E9-'Price Data'!E8-'Right Share Ratio'!E9*'Right Share Offer Price'!E9*Split!E9)/'Price Data'!E8 -> -0.071256362 | F9: =('Price Data'!F9*(1+'Stock Dividend'!F9+'Right Share Ratio'!F9)*Split!F9-'Price Data'!F8-'Right Share Ratio'!F9*'Right Share Offer Price'!F9*Split!F9)/'Price Data'!F8 -> -0.045545689 | G9: =('Price Data'!G9*(1+'Stock Dividend'!G9+'Right Share Ratio'!G9)*Split!G9-'Price Data'!G8-'Right Share Ratio'!G9*'Right Share Offer Price'!G9*Split!G9)/'Price Data'!G8 -> -0.058988764 | H9: =('Price Data'!H9*(1+'Stock Dividend'!H9+'Right Share Ratio'!H9)*Split!H9-'Price Data'!H8-'Right Share Ratio'!H9*'Right Share Offer Price'!H9*Split!H9)/'Price Data'!H8 -> -0.12191358 | I9: =('Price Data'!I9*(1+'Stock Dividend'!I9+'Right Share Ratio'!I9)*Split!I9-'Price Data'!I8-'Right Share Ratio'!I9*'Right Share Offer Price'!I9*Split!I9)/'Price Data'!I8 -> -0.054292211 | J9: =('Price Data'!J9*(1+'Stock Dividend'!J9+'Right Share Ratio'!J9)*Split!J9-'Price Data'!J8-'Right Share Ratio'!J9*'Right Share Offer Price'!J9*Split!J9)/'Price Data'!J8 -> 0.023504274 | ... V9: =('Price Data'!V9*(1+'Stock Dividend'!V9+'Right Share Ratio'!V9)*Split!V9-'Price Data'!V8-'Right Share Ratio'!V9*'Right Share Offer Price'!V9*Split!V9)/'Price Data'!V8 -> 0.0023837902
B10: March | C10: =('Price Data'!C10*(1+'Stock Dividend'!C10+'Right Share Ratio'!C10)*Split!C10-'Price Data'!C9-'Right Share Ratio'!C10*'Right Share Offer Price'!C10*Split!C10)/'Price Data'!C9 -> -0.079603399 | D10: =('Price Data'!D10*(1+'Stock Dividend'!D10+'Right Share Ratio'!D10)*Split!D10-'Price Data'!D9-'Right Share Ratio'!D10*'Right Share Offer Price'!D10*Split!D10)/'Price Data'!D9 -> 0.026666667 | E10: =('Price Data'!E10*(1+'Stock Dividend'!E10+'Right Share Ratio'!E10)*Split!E10-'Price Data'!E9-'Right Share Ratio'!E10*'Right Share Offer Price'!E10*Split!E10)/'Price Data'!E9 -> 0.13441015 | F10: =('Price Data'!F10*(1+'Stock Dividend'!F10+'Right Share Ratio'!F10)*Split!F10-'Price Data'!F9-'Right Share Ratio'!F10*'Right Share Offer Price'!F10*Split!F10)/'Price Data'!F9 -> 0.082833133 | G10: =('Price Data'!G10*(1+'Stock Dividend'!G10+'Right Share Ratio'!G10)*Split!G10-'Price Data'!G9-'Right Share Ratio'!G10*'Right Share Offer Price'!G10*Split!G10)/'Price Data'!G9 -> -0.08358209 | H10: =('Price Data'!H10*(1+'Stock Dividend'!H10+'Right Share Ratio'!H10)*Split!H10-'Price Data'!H9-'Right Share Ratio'!H10*'Right Share Offer Price'!H10*Split!H10)/'Price Data'!H9 -> -0.029876977 | I10: =('Price Data'!I10*(1+'Stock Dividend'!I10+'Right Share Ratio'!I10)*Split!I10-'Price Data'!I9-'Right Share Ratio'!I10*'Right Share Offer Price'!I10*Split!I10)/'Price Data'!I9 -> 0.13946498 | J10: =('Price Data'!J10*(1+'Stock Dividend'!J10+'Right Share Ratio'!J10)*Split!J10-'Price Data'!J9-'Right Share Ratio'!J10*'Right Share Offer Price'!J10*Split!J10)/'Price Data'!J9 -> -0.048016701 | ... V10: =('Price Data'!V10*(1+'Stock Dividend'!V10+'Right Share Ratio'!V10)*Split!V10-'Price Data'!V9-'Right Share Ratio'!V10*'Right Share Offer Price'!V10*Split!V10)/'Price Data'!V9 -> -0.029726516
B11: April | C11: =('Price Data'!C11*(1+'Stock Dividend'!C11+'Right Share Ratio'!C11)*Split!C11-'Price Data'!C10-'Right Share Ratio'!C11*'Right Share Offer Price'!C11*Split!C11)/'Price Data'!C10 -> 0.069375192 | D11: =('Price Data'!D11*(1+'Stock Dividend'!D11+'Right Share Ratio'!D11)*Split!D11-'Price Data'!D10-'Right Share Ratio'!D11*'Right Share Offer Price'!D11*Split!D11)/'Price Data'!D10 -> 0.012987013 | E11: =('Price Data'!E11*(1+'Stock Dividend'!E11+'Right Share Ratio'!E11)*Split!E11-'Price Data'!E10-'Right Share Ratio'!E11*'Right Share Offer Price'!E11*Split!E11)/'Price Data'!E10 -> 0.37782863 | F11: =('Price Data'!F11*(1+'Stock Dividend'!F11+'Right Share Ratio'!F11)*Split!F11-'Price Data'!F10-'Right Share Ratio'!F11*'Right Share Offer Price'!F11*Split!F11)/'Price Data'!F10 -> 0.012195122 | G11: =('Price Data'!G11*(1+'Stock Dividend'!G11+'Right Share Ratio'!G11)*Split!G11-'Price Data'!G10-'Right Share Ratio'!G11*'Right Share Offer Price'!G11*Split!G11)/'Price Data'!G10 -> -0.070032573 | H11: =('Price Data'!H11*(1+'Stock Dividend'!H11+'Right Share Ratio'!H11)*Split!H11-'Price Data'!H10-'Right Share Ratio'!H11*'Right Share Offer Price'!H11*Split!H11)/'Price Data'!H10 -> 0.041666667 | I11: =('Price Data'!I11*(1+'Stock Dividend'!I11+'Right Share Ratio'!I11)*Split!I11-'Price Data'!I10-'Right Share Ratio'!I11*'Right Share Offer Price'!I11*Split!I11)/'Price Data'!I10 -> 0.011870219 | J11: =('Price Data'!J11*(1+'Stock Dividend'!J11+'Right Share Ratio'!J11)*Split!J11-'Price Data'!J10-'Right Share Ratio'!J11*'Right Share Offer Price'!J11*Split!J11)/'Price Data'!J10 -> -0.083333333 | ... V11: =('Price Data'!V11*(1+'Stock Dividend'!V11+'Right Share Ratio'!V11)*Split!V11-'Price Data'!V10-'Right Share Ratio'!V11*'Right Share Offer Price'!V11*Split!V11)/'Price Data'!V10 -> 0.026960784
B12: May | C12: =('Price Data'!C12*(1+'Stock Dividend'!C12+'Right Share Ratio'!C12)*Split!C12-'Price Data'!C11-'Right Share Ratio'!C12*'Right Share Offer Price'!C12*Split!C12)/'Price Data'!C11 -> -0.10643564 | D12: =('Price Data'!D12*(1+'Stock Dividend'!D12+'Right Share Ratio'!D12)*Split!D12-'Price Data'!D11-'Right Share Ratio'!D12*'Right Share Offer Price'!D12*Split!D12)/'Price Data'!D11 -> 0 | E12: =('Price Data'!E12*(1+'Stock Dividend'!E12+'Right Share Ratio'!E12)*Split!E12-'Price Data'!E11-'Right Share Ratio'!E12*'Right Share Offer Price'!E12*Split!E12)/'Price Data'!E11 -> -0.07547518 | F12: =('Price Data'!F12*(1+'Stock Dividend'!F12+'Right Share Ratio'!F12)*Split!F12-'Price Data'!F11-'Right Share Ratio'!F12*'Right Share Offer Price'!F12*Split!F12)/'Price Data'!F11 -> -0.063253012 | G12: =('Price Data'!G12*(1+'Stock Dividend'!G12+'Right Share Ratio'!G12)*Split!G12-'Price Data'!G11-'Right Share Ratio'!G12*'Right Share Offer Price'!G12*Split!G12)/'Price Data'!G11 -> -0.15411559 | H12: =('Price Data'!H12*(1+'Stock Dividend'!H12+'Right Share Ratio'!H12)*Split!H12-'Price Data'!H11-'Right Share Ratio'!H12*'Right Share Offer Price'!H12*Split!H12)/'Price Data'!H11 -> -0.097391304 | I12: =('Price Data'!I12*(1+'Stock Dividend'!I12+'Right Share Ratio'!I12)*Split!I12-'Price Data'!I11-'Right Share Ratio'!I12*'Right Share Offer Price'!I12*Split!I12)/'Price Data'!I11 -> 0 | J12: =('Price Data'!J12*(1+'Stock Dividend'!J12+'Right Share Ratio'!J12)*Split!J12-'Price Data'!J11-'Right Share Ratio'!J12*'Right Share Offer Price'!J12*Split!J12)/'Price Data'!J11 -> 0.009569378 | ... V12: =('Price Data'!V12*(1+'Stock Dividend'!V12+'Right Share Ratio'!V12)*Split!V12-'Price Data'!V11-'Right Share Ratio'!V12*'Right Share Offer Price'!V12*Split!V12)/'Price Data'!V11 -> 0
B13: June | C13: =('Price Data'!C13*(1+'Stock Dividend'!C13+'Right Share Ratio'!C13)*Split!C13-'Price Data'!C12-'Right Share Ratio'!C13*'Right Share Offer Price'!C13*Split!C13)/'Price Data'!C12 -> 0.0096952909 | D13: =('Price Data'!D13*(1+'Stock Dividend'!D13+'Right Share Ratio'!D13)*Split!D13-'Price Data'!D12-'Right Share Ratio'!D13*'Right Share Offer Price'!D13*Split!D13)/'Price Data'!D12 -> -0.04 | E13: =('Price Data'!E13*(1+'Stock Dividend'!E13+'Right Share Ratio'!E13)*Split!E13-'Price Data'!E12-'Right Share Ratio'!E13*'Right Share Offer Price'!E13*Split!E13)/'Price Data'!E12 -> 0.0017964072 | F13: =('Price Data'!F13*(1+'Stock Dividend'!F13+'Right Share Ratio'!F13)*Split!F13-'Price Data'!F12-'Right Share Ratio'!F13*'Right Share Offer Price'!F13*Split!F13)/'Price Data'!F12 -> -0.001607717 | G13: =('Price Data'!G13*(1+'Stock Dividend'!G13+'Right Share Ratio'!G13)*Split!G13-'Price Data'!G12-'Right Share Ratio'!G13*'Right Share Offer Price'!G13*Split!G13)/'Price Data'!G12 -> 0.072463768 | H13: =('Price Data'!H13*(1+'Stock Dividend'!H13+'Right Share Ratio'!H13)*Split!H13-'Price Data'!H12-'Right Share Ratio'!H13*'Right Share Offer Price'!H13*Split!H13)/'Price Data'!H12 -> -0.011560694 | I13: =('Price Data'!I13*(1+'Stock Dividend'!I13+'Right Share Ratio'!I13)*Split!I13-'Price Data'!I12-'Right Share Ratio'!I13*'Right Share Offer Price'!I13*Split!I13)/'Price Data'!I12 -> -0.0070385819 | J13: =('Price Data'!J13*(1+'Stock Dividend'!J13+'Right Share Ratio'!J13)*Split!J13-'Price Data'!J12-'Right Share Ratio'!J13*'Right Share Offer Price'!J13*Split!J13)/'Price Data'!J12 -> 0.071090047 | ... V13: =('Price Data'!V13*(1+'Stock Dividend'!V13+'Right Share Ratio'!V13)*Split!V13-'Price Data'!V12-'Right Share Ratio'!V13*'Right Share Offer Price'!V13*Split!V13)/'Price Data'!V12 -> 0.057279236
B14: July | C14: =('Price Data'!C14*(1+'Stock Dividend'!C14+'Right Share Ratio'!C14)*Split!C14-'Price Data'!C13-'Right Share Ratio'!C14*'Right Share Offer Price'!C14*Split!C14)/'Price Data'!C13 -> -0.069958848 | D14: =('Price Data'!D14*(1+'Stock Dividend'!D14+'Right Share Ratio'!D14)*Split!D14-'Price Data'!D13-'Right Share Ratio'!D14*'Right Share Offer Price'!D14*Split!D14)/'Price Data'!D13 -> -0.041666667 | E14: =('Price Data'!E14*(1+'Stock Dividend'!E14+'Right Share Ratio'!E14)*Split!E14-'Price Data'!E13-'Right Share Ratio'!E14*'Right Share Offer Price'!E14*Split!E14)/'Price Data'!E13 -> 0.094839609 | F14: =('Price Data'!F14*(1+'Stock Dividend'!F14+'Right Share Ratio'!F14)*Split!F14-'Price Data'!F13-'Right Share Ratio'!F14*'Right Share Offer Price'!F14*Split!F14)/'Price Data'!F13 -> -0.049919485 | G14: =('Price Data'!G14*(1+'Stock Dividend'!G14+'Right Share Ratio'!G14)*Split!G14-'Price Data'!G13-'Right Share Ratio'!G14*'Right Share Offer Price'!G14*Split!G14)/'Price Data'!G13 -> -0.027027027 | H14: =('Price Data'!H14*(1+'Stock Dividend'!H14+'Right Share Ratio'!H14)*Split!H14-'Price Data'!H13-'Right Share Ratio'!H14*'Right Share Offer Price'!H14*Split!H14)/'Price Data'!H13 -> -0.068226121 | I14: =('Price Data'!I14*(1+'Stock Dividend'!I14+'Right Share Ratio'!I14)*Split!I14-'Price Data'!I13-'Right Share Ratio'!I14*'Right Share Offer Price'!I14*Split!I14)/'Price Data'!I13 -> -0.090574954 | J14: =('Price Data'!J14*(1+'Stock Dividend'!J14+'Right Share Ratio'!J14)*Split!J14-'Price Data'!J13-'Right Share Ratio'!J14*'Right Share Offer Price'!J14*Split!J14)/'Price Data'!J13 -> -0.019911504 | ... V14: =('Price Data'!V14*(1+'Stock Dividend'!V14+'Right Share Ratio'!V14)*Split!V14-'Price Data'!V13-'Right Share Ratio'!V14*'Right Share Offer Price'!V14*Split!V14)/'Price Data'!V13 -> -0.046839729
B15: August | C15: =('Price Data'!C15*(1+'Stock Dividend'!C15+'Right Share Ratio'!C15)*Split!C15-'Price Data'!C14-'Right Share Ratio'!C15*'Right Share Offer Price'!C15*Split!C15)/'Price Data'!C14 -> 0 | D15: =('Price Data'!D15*(1+'Stock Dividend'!D15+'Right Share Ratio'!D15)*Split!D15-'Price Data'!D14-'Right Share Ratio'!D15*'Right Share Offer Price'!D15*Split!D15)/'Price Data'!D14 -> 0.02173913 | E15: =('Price Data'!E15*(1+'Stock Dividend'!E15+'Right Share Ratio'!E15)*Split!E15-'Price Data'!E14-'Right Share Ratio'!E15*'Right Share Offer Price'!E15*Split!E15)/'Price Data'!E14 -> 0.18544131 | F15: =('Price Data'!F15*(1+'Stock Dividend'!F15+'Right Share Ratio'!F15)*Split!F15-'Price Data'!F14-'Right Share Ratio'!F15*'Right Share Offer Price'!F15*Split!F15)/'Price Data'!F14 -> 0.061016949 | G15: =('Price Data'!G15*(1+'Stock Dividend'!G15+'Right Share Ratio'!G15)*Split!G15-'Price Data'!G14-'Right Share Ratio'!G15*'Right Share Offer Price'!G15*Split!G15)/'Price Data'!G14 -> -0.035714286 | H15: =('Price Data'!H15*(1+'Stock Dividend'!H15+'Right Share Ratio'!H15)*Split!H15-'Price Data'!H14-'Right Share Ratio'!H15*'Right Share Offer Price'!H15*Split!H15)/'Price Data'!H14 -> 0.039748954 | I15: =('Price Data'!I15*(1+'Stock Dividend'!I15+'Right Share Ratio'!I15)*Split!I15-'Price Data'!I14-'Right Share Ratio'!I15*'Right Share Offer Price'!I15*Split!I15)/'Price Data'!I14 -> 0.091801386 | J15: =('Price Data'!J15*(1+'Stock Dividend'!J15+'Right Share Ratio'!J15)*Split!J15-'Price Data'!J14-'Right Share Ratio'!J15*'Right Share Offer Price'!J15*Split!J15)/'Price Data'!J14 -> 0.19187359 | ... V15: =('Price Data'!V15*(1+'Stock Dividend'!V15+'Right Share Ratio'!V15)*Split!V15-'Price Data'!V14-'Right Share Ratio'!V15*'Right Share Offer Price'!V15*Split!V15)/'Price Data'!V14 -> 0.007696862
B16: September | C16: =('Price Data'!C16*(1+'Stock Dividend'!C16+'Right Share Ratio'!C16)*Split!C16-'Price Data'!C15-'Right Share Ratio'!C16*'Right Share Offer Price'!C16*Split!C16)/'Price Data'!C15 -> -0.0025811209 | D16: =('Price Data'!D16*(1+'Stock Dividend'!D16+'Right Share Ratio'!D16)*Split!D16-'Price Data'!D15-'Right Share Ratio'!D16*'Right Share Offer Price'!D16*Split!D16)/'Price Data'!D15 -> -0.021276596 | E16: =('Price Data'!E16*(1+'Stock Dividend'!E16+'Right Share Ratio'!E16)*Split!E16-'Price Data'!E15-'Right Share Ratio'!E16*'Right Share Offer Price'!E16*Split!E16)/'Price Data'!E15 -> -0.027786306 | F16: =('Price Data'!F16*(1+'Stock Dividend'!F16+'Right Share Ratio'!F16)*Split!F16-'Price Data'!F15-'Right Share Ratio'!F16*'Right Share Offer Price'!F16*Split!F16)/'Price Data'!F15 -> -0.076677316 | G16: =('Price Data'!G16*(1+'Stock Dividend'!G16+'Right Share Ratio'!G16)*Split!G16-'Price Data'!G15-'Right Share Ratio'!G16*'Right Share Offer Price'!G16*Split!G16)/'Price Data'!G15 -> -0.043209877 | H16: =('Price Data'!H16*(1+'Stock Dividend'!H16+'Right Share Ratio'!H16)*Split!H16-'Price Data'!H15-'Right Share Ratio'!H16*'Right Share Offer Price'!H16*Split!H16)/'Price Data'!H15 -> -0.072434608 | I16: =('Price Data'!I16*(1+'Stock Dividend'!I16+'Right Share Ratio'!I16)*Split!I16-'Price Data'!I15-'Right Share Ratio'!I16*'Right Share Offer Price'!I16*Split!I16)/'Price Data'!I15 -> 0.019301957 | J16: =('Price Data'!J16*(1+'Stock Dividend'!J16+'Right Share Ratio'!J16)*Split!J16-'Price Data'!J15-'Right Share Ratio'!J16*'Right Share Offer Price'!J16*Split!J16)/'Price Data'!J15 -> 0.12878788 | ... V16: =('Price Data'!V16*(1+'Stock Dividend'!V16+'Right Share Ratio'!V16)*Split!V16-'Price Data'!V15-'Right Share Ratio'!V16*'Right Share Offer Price'!V16*Split!V16)/'Price Data'!V15 -> -0.016451234
B17: October | C17: =('Price Data'!C17*(1+'Stock Dividend'!C17+'Right Share Ratio'!C17)*Split!C17-'Price Data'!C16-'Right Share Ratio'!C17*'Right Share Offer Price'!C17*Split!C17)/'Price Data'!C16 -> 0 | D17: =('Price Data'!D17*(1+'Stock Dividend'!D17+'Right Share Ratio'!D17)*Split!D17-'Price Data'!D16-'Right Share Ratio'!D17*'Right Share Offer Price'!D17*Split!D17)/'Price Data'!D16 -> 0 | E17: =('Price Data'!E17*(1+'Stock Dividend'!E17+'Right Share Ratio'!E17)*Split!E17-'Price Data'!E16-'Right Share Ratio'!E17*'Right Share Offer Price'!E17*Split!E17)/'Price Data'!E16 -> -0.13374388 | F17: =('Price Data'!F17*(1+'Stock Dividend'!F17+'Right Share Ratio'!F17)*Split!F17-'Price Data'!F16-'Right Share Ratio'!F17*'Right Share Offer Price'!F17*Split!F17)/'Price Data'!F16 -> 0 | G17: =('Price Data'!G17*(1+'Stock Dividend'!G17+'Right Share Ratio'!G17)*Split!G17-'Price Data'!G16-'Right Share Ratio'!G17*'Right Share Offer Price'!G17*Split!G17)/'Price Data'!G16 -> 0 | H17: =('Price Data'!H17*(1+'Stock Dividend'!H17+'Right Share Ratio'!H17)*Split!H17-'Price Data'!H16-'Right Share Ratio'!H17*'Right Share Offer Price'!H17*Split!H17)/'Price Data'!H16 -> -0.036876356 | I17: =('Price Data'!I17*(1+'Stock Dividend'!I17+'Right Share Ratio'!I17)*Split!I17-'Price Data'!I16-'Right Share Ratio'!I17*'Right Share Offer Price'!I17*Split!I17)/'Price Data'!I16 -> -0.061478599 | J17: =('Price Data'!J17*(1+'Stock Dividend'!J17+'Right Share Ratio'!J17)*Split!J17-'Price Data'!J16-'Right Share Ratio'!J17*'Right Share Offer Price'!J17*Split!J17)/'Price Data'!J16 -> 0.048657718 | ... V17: =('Price Data'!V17*(1+'Stock Dividend'!V17+'Right Share Ratio'!V17)*Split!V17-'Price Data'!V16-'Right Share Ratio'!V17*'Right Share Offer Price'!V17*Split!V17)/'Price Data'!V16 -> 0.00059737157
B18: November | C18: =('Price Data'!C18*(1+'Stock Dividend'!C18+'Right Share Ratio'!C18)*Split!C18-'Price Data'!C17-'Right Share Ratio'!C18*'Right Share Offer Price'!C18*Split!C18)/'Price Data'!C17 -> 0 | D18: =('Price Data'!D18*(1+'Stock Dividend'!D18+'Right Share Ratio'!D18)*Split!D18-'Price Data'!D17-'Right Share Ratio'!D18*'Right Share Offer Price'!D18*Split!D18)/'Price Data'!D17 -> 0 | E18: =('Price Data'!E18*(1+'Stock Dividend'!E18+'Right Share Ratio'!E18)*Split!E18-'Price Data'!E17-'Right Share Ratio'!E18*'Right Share Offer Price'!E18*Split!E18)/'Price Data'!E17 -> 0 | F18: =('Price Data'!F18*(1+'Stock Dividend'!F18+'Right Share Ratio'!F18)*Split!F18-'Price Data'!F17-'Right Share Ratio'!F18*'Right Share Offer Price'!F18*Split!F18)/'Price Data'!F17 -> 0 | G18: =('Price Data'!G18*(1+'Stock Dividend'!G18+'Right Share Ratio'!G18)*Split!G18-'Price Data'!G17-'Right Share Ratio'!G18*'Right Share Offer Price'!G18*Split!G18)/'Price Data'!G17 -> 0 | H18: =('Price Data'!H18*(1+'Stock Dividend'!H18+'Right Share Ratio'!H18)*Split!H18-'Price Data'!H17-'Right Share Ratio'!H18*'Right Share Offer Price'!H18*Split!H18)/'Price Data'!H17 -> -0.018018018 | I18: =('Price Data'!I18*(1+'Stock Dividend'!I18+'Right Share Ratio'!I18)*Split!I18-'Price Data'!I17-'Right Share Ratio'!I18*'Right Share Offer Price'!I18*Split!I18)/'Price Data'!I17 -> -0.047816473 | J18: =('Price Data'!J18*(1+'Stock Dividend'!J18+'Right Share Ratio'!J18)*Split!J18-'Price Data'!J17-'Right Share Ratio'!J18*'Right Share Offer Price'!J18*Split!J18)/'Price Data'!J17 -> -0.0688 | ... V18: =('Price Data'!V18*(1+'Stock Dividend'!V18+'Right Share Ratio'!V18)*Split!V18-'Price Data'!V17-'Right Share Ratio'!V18*'Right Share Offer Price'!V18*Split!V18)/'Price Data'!V17 -> 0.0089552239
B19: December | C19: =('Price Data'!C19*(1+'Stock Dividend'!C19+'Right Share Ratio'!C19)*Split!C19-'Price Data'!C18-'Right Share Ratio'!C19*'Right Share Offer Price'!C19*Split!C19)/'Price Data'!C18 -> 0 | D19: =('Price Data'!D19*(1+'Stock Dividend'!D19+'Right Share Ratio'!D19)*Split!D19-'Price Data'!D18-'Right Share Ratio'!D19*'Right Share Offer Price'!D19*Split!D19)/'Price Data'!D18 -> 0 | E19: =('Price Data'!E19*(1+'Stock Dividend'!E19+'Right Share Ratio'!E19)*Split!E19-'Price Data'!E18-'Right Share Ratio'!E19*'Right Share Offer Price'!E19*Split!E19)/'Price Data'!E18 -> 0 | F19: =('Price Data'!F19*(1+'Stock Dividend'!F19+'Right Share Ratio'!F19)*Split!F19-'Price Data'!F18-'Right Share Ratio'!F19*'Right Share Offer Price'!F19*Split!F19)/'Price Data'!F18 -> 0 | G19: =('Price Data'!G19*(1+'Stock Dividend'!G19+'Right Share Ratio'!G19)*Split!G19-'Price Data'!G18-'Right Share Ratio'!G19*'Right Share Offer Price'!G19*Split!G19)/'Price Data'!G18 -> -0.043010753 | H19: =('Price Data'!H19*(1+'Stock Dividend'!H19+'Right Share Ratio'!H19)*Split!H19-'Price Data'!H18-'Right Share Ratio'!H19*'Right Share Offer Price'!H19*Split!H19)/'Price Data'!H18 -> -0.04587156 | I19: =('Price Data'!I19*(1+'Stock Dividend'!I19+'Right Share Ratio'!I19)*Split!I19-'Price Data'!I18-'Right Share Ratio'!I19*'Right Share Offer Price'!I19*Split!I19)/'Price Data'!I18 -> 0 | J19: =('Price Data'!J19*(1+'Stock Dividend'!J19+'Right Share Ratio'!J19)*Split!J19-'Price Data'!J18-'Right Share Ratio'!J19*'Right Share Offer Price'!J19*Split!J19)/'Price Data'!J18 -> 0.025773196 | ... V19: =('Price Data'!V19*(1+'Stock Dividend'!V19+'Right Share Ratio'!V19)*Split!V19-'Price Data'!V18-'Right Share Ratio'!V19*'Right Share Offer Price'!V19*Split!V19)/'Price Data'!V18 -> -0.010059172
A20: 2023 | B20: January | C20: =('Price Data'!C20*(1+'Stock Dividend'!C20+'Right Share Ratio'!C20)*Split!C20-'Price Data'!C19-'Right Share Ratio'!C20*'Right Share Offer Price'!C20*Split!C20)/'Price Data'!C19 -> 0 | D20: =('Price Data'!D20*(1+'Stock Dividend'!D20+'Right Share Ratio'!D20)*Split!D20-'Price Data'!D19-'Right Share Ratio'!D20*'Right Share Offer Price'!D20*Split!D20)/'Price Data'!D19 -> 0 | E20: =('Price Data'!E20*(1+'Stock Dividend'!E20+'Right Share Ratio'!E20)*Split!E20-'Price Data'!E19-'Right Share Ratio'!E20*'Right Share Offer Price'!E20*Split!E20)/'Price Data'!E19 -> 0 | F20: =('Price Data'!F20*(1+'Stock Dividend'!F20+'Right Share Ratio'!F20)*Split!F20-'Price Data'!F19-'Right Share Ratio'!F20*'Right Share Offer Price'!F20*Split!F20)/'Price Data'!F19 -> 0 | G20: =('Price Data'!G20*(1+'Stock Dividend'!G20+'Right Share Ratio'!G20)*Split!G20-'Price Data'!G19-'Right Share Ratio'!G20*'Right Share Offer Price'!G20*Split!G20)/'Price Data'!G19 -> -0.02247191 | H20: =('Price Data'!H20*(1+'Stock Dividend'!H20+'Right Share Ratio'!H20)*Split!H20-'Price Data'!H19-'Right Share Ratio'!H20*'Right Share Offer Price'!H20*Split!H20)/'Price Data'!H19 -> 0.15144231 | I20: =('Price Data'!I20*(1+'Stock Dividend'!I20+'Right Share Ratio'!I20)*Split!I20-'Price Data'!I19-'Right Share Ratio'!I20*'Right Share Offer Price'!I20*Split!I20)/'Price Data'!I19 -> 0 | J20: =('Price Data'!J20*(1+'Stock Dividend'!J20+'Right Share Ratio'!J20)*Split!J20-'Price Data'!J19-'Right Share Ratio'!J20*'Right Share Offer Price'!J20*Split!J20)/'Price Data'!J19 -> -0.033500838 | ... V20: =('Price Data'!V20*(1+'Stock Dividend'!V20+'Right Share Ratio'!V20)*Split!V20-'Price Data'!V19-'Right Share Ratio'!V20*'Right Share Offer Price'!V20*Split!V20)/'Price Data'!V19 -> 0.016138673
B21: February | C21: =('Price Data'!C21*(1+'Stock Dividend'!C21+'Right Share Ratio'!C21)*Split!C21-'Price Data'!C20-'Right Share Ratio'!C21*'Right Share Offer Price'!C21*Split!C21)/'Price Data'!C20 -> 0 | D21: =('Price Data'!D21*(1+'Stock Dividend'!D21+'Right Share Ratio'!D21)*Split!D21-'Price Data'!D20-'Right Share Ratio'!D21*'Right Share Offer Price'!D21*Split!D21)/'Price Data'!D20 -> 0 | E21: =('Price Data'!E21*(1+'Stock Dividend'!E21+'Right Share Ratio'!E21)*Split!E21-'Price Data'!E20-'Right Share Ratio'!E21*'Right Share Offer Price'!E21*Split!E21)/'Price Data'!E20 -> 0 | F21: =('Price Data'!F21*(1+'Stock Dividend'!F21+'Right Share Ratio'!F21)*Split!F21-'Price Data'!F20-'Right Share Ratio'!F21*'Right Share Offer Price'!F21*Split!F21)/'Price Data'!F20 -> 0 | G21: =('Price Data'!G21*(1+'Stock Dividend'!G21+'Right Share Ratio'!G21)*Split!G21-'Price Data'!G20-'Right Share Ratio'!G21*'Right Share Offer Price'!G21*Split!G21)/'Price Data'!G20 -> -0.11724138 | H21: =('Price Data'!H21*(1+'Stock Dividend'!H21+'Right Share Ratio'!H21)*Split!H21-'Price Data'!H20-'Right Share Ratio'!H21*'Right Share Offer Price'!H21*Split!H21)/'Price Data'!H20 -> -0.083507307 | I21: =('Price Data'!I21*(1+'Stock Dividend'!I21+'Right Share Ratio'!I21)*Split!I21-'Price Data'!I20-'Right Share Ratio'!I21*'Right Share Offer Price'!I21*Split!I21)/'Price Data'!I20 -> 0 | J21: =('Price Data'!J21*(1+'Stock Dividend'!J21+'Right Share Ratio'!J21)*Split!J21-'Price Data'!J20-'Right Share Ratio'!J21*'Right Share Offer Price'!J21*Split!J21)/'Price Data'!J20 -> 0.065857886 | ... V21: =('Price Data'!V21*(1+'Stock Dividend'!V21+'Right Share Ratio'!V21)*Split!V21-'Price Data'!V20-'Right Share Ratio'!V21*'Right Share Offer Price'!V21*Split!V21)/'Price Data'!V20 -> 0
B22: March | C22: =('Price Data'!C22*(1+'Stock Dividend'!C22+'Right Share Ratio'!C22)*Split!C22-'Price Data'!C21-'Right Share Ratio'!C22*'Right Share Offer Price'!C22*Split!C22)/'Price Data'!C21 -> 0 | D22: =('Price Data'!D22*(1+'Stock Dividend'!D22+'Right Share Ratio'!D22)*Split!D22-'Price Data'!D21-'Right Share Ratio'!D22*'Right Share Offer Price'!D22*Split!D22)/'Price Data'!D21 -> 0 | E22: =('Price Data'!E22*(1+'Stock Dividend'!E22+'Right Share Ratio'!E22)*Split!E22-'Price Data'!E21-'Right Share Ratio'!E22*'Right Share Offer Price'!E22*Split!E22)/'Price Data'!E21 -> 0 | F22: =('Price Data'!F22*(1+'Stock Dividend'!F22+'Right Share Ratio'!F22)*Split!F22-'Price Data'!F21-'Right Share Ratio'!F22*'Right Share Offer Price'!F22*Split!F22)/'Price Data'!F21 -> 0 | G22: =('Price Data'!G22*(1+'Stock Dividend'!G22+'Right Share Ratio'!G22)*Split!G22-'Price Data'!G21-'Right Share Ratio'!G22*'Right Share Offer Price'!G22*Split!G22)/'Price Data'!G21 -> 0 | H22: =('Price Data'!H22*(1+'Stock Dividend'!H22+'Right Share Ratio'!H22)*Split!H22-'Price Data'!H21-'Right Share Ratio'!H22*'Right Share Offer Price'!H22*Split!H22)/'Price Data'!H21 -> -0.006833713 | I22: =('Price Data'!I22*(1+'Stock Dividend'!I22+'Right Share Ratio'!I22)*Split!I22-'Price Data'!I21-'Right Share Ratio'!I22*'Right Share Offer Price'!I22*Split!I22)/'Price Data'!I21 -> 0 | J22: =('Price Data'!J22*(1+'Stock Dividend'!J22+'Right Share Ratio'!J22)*Split!J22-'Price Data'!J21-'Right Share Ratio'!J22*'Right Share Offer Price'!J22*Split!J22)/'Price Data'!J21 -> 0.17398374 | ... V22: =('Price Data'!V22*(1+'Stock Dividend'!V22+'Right Share Ratio'!V22)*Split!V22-'Price Data'!V21-'Right Share Ratio'!V22*'Right Share Offer Price'!V22*Split!V22)/'Price Data'!V21 -> 0.05
B23: April | C23: =('Price Data'!C23*(1+'Stock Dividend'!C23+'Right Share Ratio'!C23)*Split!C23-'Price Data'!C22-'Right Share Ratio'!C23*'Right Share Offer Price'!C23*Split!C23)/'Price Data'!C22 -> 0 | D23: =('Price Data'!D23*(1+'Stock Dividend'!D23+'Right Share Ratio'!D23)*Split!D23-'Price Data'!D22-'Right Share Ratio'!D23*'Right Share Offer Price'!D23*Split!D23)/'Price Data'!D22 -> 0 | E23: =('Price Data'!E23*(1+'Stock Dividend'!E23+'Right Share Ratio'!E23)*Split!E23-'Price Data'!E22-'Right Share Ratio'!E23*'Right Share Offer Price'!E23*Split!E23)/'Price Data'!E22 -> 0 | F23: =('Price Data'!F23*(1+'Stock Dividend'!F23+'Right Share Ratio'!F23)*Split!F23-'Price Data'!F22-'Right Share Ratio'!F23*'Right Share Offer Price'!F23*Split!F23)/'Price Data'!F22 -> 0.00058823529 | G23: =('Price Data'!G23*(1+'Stock Dividend'!G23+'Right Share Ratio'!G23)*Split!G23-'Price Data'!G22-'Right Share Ratio'!G23*'Right Share Offer Price'!G23*Split!G23)/'Price Data'!G22 -> 0 | H23: =('Price Data'!H23*(1+'Stock Dividend'!H23+'Right Share Ratio'!H23)*Split!H23-'Price Data'!H22-'Right Share Ratio'!H23*'Right Share Offer Price'!H23*Split!H23)/'Price Data'!H22 -> 0.027522936 | I23: =('Price Data'!I23*(1+'Stock Dividend'!I23+'Right Share Ratio'!I23)*Split!I23-'Price Data'!I22-'Right Share Ratio'!I23*'Right Share Offer Price'!I23*Split!I23)/'Price Data'!I22 -> 0 | J23: =('Price Data'!J23*(1+'Stock Dividend'!J23+'Right Share Ratio'!J23)*Split!J23-'Price Data'!J22-'Right Share Ratio'!J23*'Right Share Offer Price'!J23*Split!J23)/'Price Data'!J22 -> -0.011080332 | ... V23: =('Price Data'!V23*(1+'Stock Dividend'!V23+'Right Share Ratio'!V23)*Split!V23-'Price Data'!V22-'Right Share Ratio'!V23*'Right Share Offer Price'!V23*Split!V23)/'Price Data'!V22 -> 0.02464986
B24: May | C24: =('Price Data'!C24*(1+'Stock Dividend'!C24+'Right Share Ratio'!C24)*Split!C24-'Price Data'!C23-'Right Share Ratio'!C24*'Right Share Offer Price'!C24*Split!C24)/'Price Data'!C23 -> -0.00011090573 | D24: =('Price Data'!D24*(1+'Stock Dividend'!D24+'Right Share Ratio'!D24)*Split!D24-'Price Data'!D23-'Right Share Ratio'!D24*'Right Share Offer Price'!D24*Split!D24)/'Price Data'!D23 -> 0 | E24: =('Price Data'!E24*(1+'Stock Dividend'!E24+'Right Share Ratio'!E24)*Split!E24-'Price Data'!E23-'Right Share Ratio'!E24*'Right Share Offer Price'!E24*Split!E24)/'Price Data'!E23 -> 0 | F24: =('Price Data'!F24*(1+'Stock Dividend'!F24+'Right Share Ratio'!F24)*Split!F24-'Price Data'!F23-'Right Share Ratio'!F24*'Right Share Offer Price'!F24*Split!F24)/'Price Data'!F23 -> 0 | G24: =('Price Data'!G24*(1+'Stock Dividend'!G24+'Right Share Ratio'!G24)*Split!G24-'Price Data'!G23-'Right Share Ratio'!G24*'Right Share Offer Price'!G24*Split!G24)/'Price Data'!G23 -> 0.5078125 | H24: =('Price Data'!H24*(1+'Stock Dividend'!H24+'Right Share Ratio'!H24)*Split!H24-'Price Data'!H23-'Right Share Ratio'!H24*'Right Share Offer Price'!H24*Split!H24)/'Price Data'!H23 -> 0.22544643 | I24: =('Price Data'!I24*(1+'Stock Dividend'!I24+'Right Share Ratio'!I24)*Split!I24-'Price Data'!I23-'Right Share Ratio'!I24*'Right Share Offer Price'!I24*Split!I24)/'Price Data'!I23 -> 0 | J24: =('Price Data'!J24*(1+'Stock Dividend'!J24+'Right Share Ratio'!J24)*Split!J24-'Price Data'!J23-'Right Share Ratio'!J24*'Right Share Offer Price'!J24*Split!J24)/'Price Data'!J23 -> 0.29971989 | ... V24: =('Price Data'!V24*(1+'Stock Dividend'!V24+'Right Share Ratio'!V24)*Split!V24-'Price Data'!V23-'Right Share Ratio'!V24*'Right Share Offer Price'!V24*Split!V24)/'Price Data'!V23 -> -0.010934937
B25: June | C25: =('Price Data'!C25*(1+'Stock Dividend'!C25+'Right Share Ratio'!C25)*Split!C25-'Price Data'!C24-'Right Share Ratio'!C25*'Right Share Offer Price'!C25*Split!C25)/'Price Data'!C24 -> 0 | D25: =('Price Data'!D25*(1+'Stock Dividend'!D25+'Right Share Ratio'!D25)*Split!D25-'Price Data'!D24-'Right Share Ratio'!D25*'Right Share Offer Price'!D25*Split!D25)/'Price Data'!D24 -> -0.0032608696 | E25: =('Price Data'!E25*(1+'Stock Dividend'!E25+'Right Share Ratio'!E25)*Split!E25-'Price Data'!E24-'Right Share Ratio'!E25*'Right Share Offer Price'!E25*Split!E25)/'Price Data'!E24 -> 0 | F25: =('Price Data'!F25*(1+'Stock Dividend'!F25+'Right Share Ratio'!F25)*Split!F25-'Price Data'!F24-'Right Share Ratio'!F25*'Right Share Offer Price'!F25*Split!F25)/'Price Data'!F24 -> 0 | G25: =('Price Data'!G25*(1+'Stock Dividend'!G25+'Right Share Ratio'!G25)*Split!G25-'Price Data'!G24-'Right Share Ratio'!G25*'Right Share Offer Price'!G25*Split!G25)/'Price Data'!G24 -> -0.16580311 | H25: =('Price Data'!H25*(1+'Stock Dividend'!H25+'Right Share Ratio'!H25)*Split!H25-'Price Data'!H24-'Right Share Ratio'!H25*'Right Share Offer Price'!H25*Split!H25)/'Price Data'!H24 -> -0.11111111 | I25: =('Price Data'!I25*(1+'Stock Dividend'!I25+'Right Share Ratio'!I25)*Split!I25-'Price Data'!I24-'Right Share Ratio'!I25*'Right Share Offer Price'!I25*Split!I25)/'Price Data'!I24 -> 0 | J25: =('Price Data'!J25*(1+'Stock Dividend'!J25+'Right Share Ratio'!J25)*Split!J25-'Price Data'!J24-'Right Share Ratio'!J25*'Right Share Offer Price'!J25*Split!J25)/'Price Data'!J24 -> 0.26831897 | ... V25: =('Price Data'!V25*(1+'Stock Dividend'!V25+'Right Share Ratio'!V25)*Split!V25-'Price Data'!V24-'Right Share Ratio'!V25*'Right Share Offer Price'!V25*Split!V25)/'Price Data'!V24 -> -0.005527916
B26: July | C26: =('Price Data'!C26*(1+'Stock Dividend'!C26+'Right Share Ratio'!C26)*Split!C26-'Price Data'!C25-'Right Share Ratio'!C26*'Right Share Offer Price'!C26*Split!C26)/'Price Data'!C25 -> 0 | D26: =('Price Data'!D26*(1+'Stock Dividend'!D26+'Right Share Ratio'!D26)*Split!D26-'Price Data'!D25-'Right Share Ratio'!D26*'Right Share Offer Price'!D26*Split!D26)/'Price Data'!D25 -> 0 | E26: =('Price Data'!E26*(1+'Stock Dividend'!E26+'Right Share Ratio'!E26)*Split!E26-'Price Data'!E25-'Right Share Ratio'!E26*'Right Share Offer Price'!E26*Split!E26)/'Price Data'!E25 -> 0 | F26: =('Price Data'!F26*(1+'Stock Dividend'!F26+'Right Share Ratio'!F26)*Split!F26-'Price Data'!F25-'Right Share Ratio'!F26*'Right Share Offer Price'!F26*Split!F26)/'Price Data'!F25 -> 0 | G26: =('Price Data'!G26*(1+'Stock Dividend'!G26+'Right Share Ratio'!G26)*Split!G26-'Price Data'!G25-'Right Share Ratio'!G26*'Right Share Offer Price'!G26*Split!G26)/'Price Data'!G25 -> -0.082815735 | H26: =('Price Data'!H26*(1+'Stock Dividend'!H26+'Right Share Ratio'!H26)*Split!H26-'Price Data'!H25-'Right Share Ratio'!H26*'Right Share Offer Price'!H26*Split!H26)/'Price Data'!H25 -> 0.26844262 | I26: =('Price Data'!I26*(1+'Stock Dividend'!I26+'Right Share Ratio'!I26)*Split!I26-'Price Data'!I25-'Right Share Ratio'!I26*'Right Share Offer Price'!I26*Split!I26)/'Price Data'!I25 -> 0 | J26: =('Price Data'!J26*(1+'Stock Dividend'!J26+'Right Share Ratio'!J26)*Split!J26-'Price Data'!J25-'Right Share Ratio'!J26*'Right Share Offer Price'!J26*Split!J26)/'Price Data'!J25 -> 0.050127443 | ... V26: =('Price Data'!V26*(1+'Stock Dividend'!V26+'Right Share Ratio'!V26)*Split!V26-'Price Data'!V25-'Right Share Ratio'!V26*'Right Share Offer Price'!V26*Split!V26)/'Price Data'!V25 -> -0.013340745
B27: August | C27: =('Price Data'!C27*(1+'Stock Dividend'!C27+'Right Share Ratio'!C27)*Split!C27-'Price Data'!C26-'Right Share Ratio'!C27*'Right Share Offer Price'!C27*Split!C27)/'Price Data'!C26 -> 0 | D27: =('Price Data'!D27*(1+'Stock Dividend'!D27+'Right Share Ratio'!D27)*Split!D27-'Price Data'!D26-'Right Share Ratio'!D27*'Right Share Offer Price'!D27*Split!D27)/'Price Data'!D26 -> 0 | E27: =('Price Data'!E27*(1+'Stock Dividend'!E27+'Right Share Ratio'!E27)*Split!E27-'Price Data'!E26-'Right Share Ratio'!E27*'Right Share Offer Price'!E27*Split!E27)/'Price Data'!E26 -> 0 | F27: =('Price Data'!F27*(1+'Stock Dividend'!F27+'Right Share Ratio'!F27)*Split!F27-'Price Data'!F26-'Right Share Ratio'!F27*'Right Share Offer Price'!F27*Split!F27)/'Price Data'!F26 -> 0 | G27: =('Price Data'!G27*(1+'Stock Dividend'!G27+'Right Share Ratio'!G27)*Split!G27-'Price Data'!G26-'Right Share Ratio'!G27*'Right Share Offer Price'!G27*Split!G27)/'Price Data'!G26 -> -0.060948081 | H27: =('Price Data'!H27*(1+'Stock Dividend'!H27+'Right Share Ratio'!H27)*Split!H27-'Price Data'!H26-'Right Share Ratio'!H27*'Right Share Offer Price'!H27*Split!H27)/'Price Data'!H26 -> -0.082390953 | I27: =('Price Data'!I27*(1+'Stock Dividend'!I27+'Right Share Ratio'!I27)*Split!I27-'Price Data'!I26-'Right Share Ratio'!I27*'Right Share Offer Price'!I27*Split!I27)/'Price Data'!I26 -> 0 | J27: =('Price Data'!J27*(1+'Stock Dividend'!J27+'Right Share Ratio'!J27)*Split!J27-'Price Data'!J26-'Right Share Ratio'!J27*'Right Share Offer Price'!J27*Split!J27)/'Price Data'!J26 -> -0.0056634304 | ... V27: =('Price Data'!V27*(1+'Stock Dividend'!V27+'Right Share Ratio'!V27)*Split!V27-'Price Data'!V26-'Right Share Ratio'!V27*'Right Share Offer Price'!V27*Split!V27)/'Price Data'!V26 -> -0.0056338028
B28: September | C28: =('Price Data'!C28*(1+'Stock Dividend'!C28+'Right Share Ratio'!C28)*Split!C28-'Price Data'!C27-'Right Share Ratio'!C28*'Right Share Offer Price'!C28*Split!C28)/'Price Data'!C27 -> 0 | D28: =('Price Data'!D28*(1+'Stock Dividend'!D28+'Right Share Ratio'!D28)*Split!D28-'Price Data'!D27-'Right Share Ratio'!D28*'Right Share Offer Price'!D28*Split!D28)/'Price Data'!D27 -> 0 | E28: =('Price Data'!E28*(1+'Stock Dividend'!E28+'Right Share Ratio'!E28)*Split!E28-'Price Data'!E27-'Right Share Ratio'!E28*'Right Share Offer Price'!E28*Split!E28)/'Price Data'!E27 -> 0 | F28: =('Price Data'!F28*(1+'Stock Dividend'!F28+'Right Share Ratio'!F28)*Split!F28-'Price Data'!F27-'Right Share Ratio'!F28*'Right Share Offer Price'!F28*Split!F28)/'Price Data'!F27 -> 0 | G28: =('Price Data'!G28*(1+'Stock Dividend'!G28+'Right Share Ratio'!G28)*Split!G28-'Price Data'!G27-'Right Share Ratio'!G28*'Right Share Offer Price'!G28*Split!G28)/'Price Data'!G27 -> 0.70913462 | H28: =('Price Data'!H28*(1+'Stock Dividend'!H28+'Right Share Ratio'!H28)*Split!H28-'Price Data'!H27-'Right Share Ratio'!H28*'Right Share Offer Price'!H28*Split!H28)/'Price Data'!H27 -> 0.080985915 | I28: =('Price Data'!I28*(1+'Stock Dividend'!I28+'Right Share Ratio'!I28)*Split!I28-'Price Data'!I27-'Right Share Ratio'!I28*'Right Share Offer Price'!I28*Split!I28)/'Price Data'!I27 -> 0 | J28: =('Price Data'!J28*(1+'Stock Dividend'!J28+'Right Share Ratio'!J28)*Split!J28-'Price Data'!J27-'Right Share Ratio'!J28*'Right Share Offer Price'!J28*Split!J28)/'Price Data'!J27 -> -0.039869813 | ... V28: =('Price Data'!V28*(1+'Stock Dividend'!V28+'Right Share Ratio'!V28)*Split!V28-'Price Data'!V27-'Right Share Ratio'!V28*'Right Share Offer Price'!V28*Split!V28)/'Price Data'!V27 -> 0.0033994334
B29: October | C29: =('Price Data'!C29*(1+'Stock Dividend'!C29+'Right Share Ratio'!C29)*Split!C29-'Price Data'!C28-'Right Share Ratio'!C29*'Right Share Offer Price'!C29*Split!C29)/'Price Data'!C28 -> 0 | D29: =('Price Data'!D29*(1+'Stock Dividend'!D29+'Right Share Ratio'!D29)*Split!D29-'Price Data'!D28-'Right Share Ratio'!D29*'Right Share Offer Price'!D29*Split!D29)/'Price Data'!D28 -> 0 | E29: =('Price Data'!E29*(1+'Stock Dividend'!E29+'Right Share Ratio'!E29)*Split!E29-'Price Data'!E28-'Right Share Ratio'!E29*'Right Share Offer Price'!E29*Split!E29)/'Price Data'!E28 -> 0 | F29: =('Price Data'!F29*(1+'Stock Dividend'!F29+'Right Share Ratio'!F29)*Split!F29-'Price Data'!F28-'Right Share Ratio'!F29*'Right Share Offer Price'!F29*Split!F29)/'Price Data'!F28 -> 0 | G29: =('Price Data'!G29*(1+'Stock Dividend'!G29+'Right Share Ratio'!G29)*Split!G29-'Price Data'!G28-'Right Share Ratio'!G29*'Right Share Offer Price'!G29*Split!G29)/'Price Data'!G28 -> -0.17580872 | H29: =('Price Data'!H29*(1+'Stock Dividend'!H29+'Right Share Ratio'!H29)*Split!H29-'Price Data'!H28-'Right Share Ratio'!H29*'Right Share Offer Price'!H29*Split!H29)/'Price Data'!H28 -> -0.13680782 | I29: =('Price Data'!I29*(1+'Stock Dividend'!I29+'Right Share Ratio'!I29)*Split!I29-'Price Data'!I28-'Right Share Ratio'!I29*'Right Share Offer Price'!I29*Split!I29)/'Price Data'!I28 -> 0 | J29: =('Price Data'!J29*(1+'Stock Dividend'!J29+'Right Share Ratio'!J29)*Split!J29-'Price Data'!J28-'Right Share Ratio'!J29*'Right Share Offer Price'!J29*Split!J29)/'Price Data'!J28 -> 0.077118644 | ... V29: =('Price Data'!V29*(1+'Stock Dividend'!V29+'Right Share Ratio'!V29)*Split!V29-'Price Data'!V28-'Right Share Ratio'!V29*'Right Share Offer Price'!V29*Split!V29)/'Price Data'!V28 -> 0.0033879164
B30: November | C30: =('Price Data'!C30*(1+'Stock Dividend'!C30+'Right Share Ratio'!C30)*Split!C30-'Price Data'!C29-'Right Share Ratio'!C30*'Right Share Offer Price'!C30*Split!C30)/'Price Data'!C29 -> 0 | D30: =('Price Data'!D30*(1+'Stock Dividend'!D30+'Right Share Ratio'!D30)*Split!D30-'Price Data'!D29-'Right Share Ratio'!D30*'Right Share Offer Price'!D30*Split!D30)/'Price Data'!D29 -> 0 | E30: =('Price Data'!E30*(1+'Stock Dividend'!E30+'Right Share Ratio'!E30)*Split!E30-'Price Data'!E29-'Right Share Ratio'!E30*'Right Share Offer Price'!E30*Split!E30)/'Price Data'!E29 -> 0 | F30: =('Price Data'!F30*(1+'Stock Dividend'!F30+'Right Share Ratio'!F30)*Split!F30-'Price Data'!F29-'Right Share Ratio'!F30*'Right Share Offer Price'!F30*Split!F30)/'Price Data'!F29 -> 0 | G30: =('Price Data'!G30*(1+'Stock Dividend'!G30+'Right Share Ratio'!G30)*Split!G30-'Price Data'!G29-'Right Share Ratio'!G30*'Right Share Offer Price'!G30*Split!G30)/'Price Data'!G29 -> -0.087030717 | H30: =('Price Data'!H30*(1+'Stock Dividend'!H30+'Right Share Ratio'!H30)*Split!H30-'Price Data'!H29-'Right Share Ratio'!H30*'Right Share Offer Price'!H30*Split!H30)/'Price Data'!H29 -> -0.043396226 | I30: =('Price Data'!I30*(1+'Stock Dividend'!I30+'Right Share Ratio'!I30)*Split!I30-'Price Data'!I29-'Right Share Ratio'!I30*'Right Share Offer Price'!I30*Split!I30)/'Price Data'!I29 -> 0 | J30: =('Price Data'!J30*(1+'Stock Dividend'!J30+'Right Share Ratio'!J30)*Split!J30-'Price Data'!J29-'Right Share Ratio'!J30*'Right Share Offer Price'!J30*Split!J30)/'Price Data'!J29 -> -0.033831629 | ... V30: =('Price Data'!V30*(1+'Stock Dividend'!V30+'Right Share Ratio'!V30)*Split!V30-'Price Data'!V29-'Right Share Ratio'!V30*'Right Share Offer Price'!V30*Split!V30)/'Price Data'!V29 -> 0.0005627462
B31: December | C31: =('Price Data'!C31*(1+'Stock Dividend'!C31+'Right Share Ratio'!C31)*Split!C31-'Price Data'!C30-'Right Share Ratio'!C31*'Right Share Offer Price'!C31*Split!C31)/'Price Data'!C30 -> 0 | D31: =('Price Data'!D31*(1+'Stock Dividend'!D31+'Right Share Ratio'!D31)*Split!D31-'Price Data'!D30-'Right Share Ratio'!D31*'Right Share Offer Price'!D31*Split!D31)/'Price Data'!D30 -> 0 | E31: =('Price Data'!E31*(1+'Stock Dividend'!E31+'Right Share Ratio'!E31)*Split!E31-'Price Data'!E30-'Right Share Ratio'!E31*'Right Share Offer Price'!E31*Split!E31)/'Price Data'!E30 -> 0 | F31: =('Price Data'!F31*(1+'Stock Dividend'!F31+'Right Share Ratio'!F31)*Split!F31-'Price Data'!F30-'Right Share Ratio'!F31*'Right Share Offer Price'!F31*Split!F31)/'Price Data'!F30 -> 0 | G31: =('Price Data'!G31*(1+'Stock Dividend'!G31+'Right Share Ratio'!G31)*Split!G31-'Price Data'!G30-'Right Share Ratio'!G31*'Right Share Offer Price'!G31*Split!G31)/'Price Data'!G30 -> 0.061682243 | H31: =('Price Data'!H31*(1+'Stock Dividend'!H31+'Right Share Ratio'!H31)*Split!H31-'Price Data'!H30-'Right Share Ratio'!H31*'Right Share Offer Price'!H31*Split!H31)/'Price Data'!H30 -> -0.01183432 | I31: =('Price Data'!I31*(1+'Stock Dividend'!I31+'Right Share Ratio'!I31)*Split!I31-'Price Data'!I30-'Right Share Ratio'!I31*'Right Share Offer Price'!I31*Split!I31)/'Price Data'!I30 -> 0 | J31: =('Price Data'!J31*(1+'Stock Dividend'!J31+'Right Share Ratio'!J31)*Split!J31-'Price Data'!J30-'Right Share Ratio'!J31*'Right Share Offer Price'!J31*Split!J31)/'Price Data'!J30 -> 0.090390879 | ... V31: =('Price Data'!V31*(1+'Stock Dividend'!V31+'Right Share Ratio'!V31)*Split!V31-'Price Data'!V30-'Right Share Ratio'!V31*'Right Share Offer Price'!V31*Split!V31)/'Price Data'!V30 -> -0.052305962
A32: 2024 | B32: January | C32: =('Price Data'!C32*(1+'Stock Dividend'!C32+'Right Share Ratio'!C32)*Split!C32-'Price Data'!C31-'Right Share Ratio'!C32*'Right Share Offer Price'!C32*Split!C32)/'Price Data'!C31 -> 0.052861685 | D32: =('Price Data'!D32*(1+'Stock Dividend'!D32+'Right Share Ratio'!D32)*Split!D32-'Price Data'!D31-'Right Share Ratio'!D32*'Right Share Offer Price'!D32*Split!D32)/'Price Data'!D31 -> -0.10687023 | E32: =('Price Data'!E32*(1+'Stock Dividend'!E32+'Right Share Ratio'!E32)*Split!E32-'Price Data'!E31-'Right Share Ratio'!E32*'Right Share Offer Price'!E32*Split!E32)/'Price Data'!E31 -> -0.4549763 | F32: =('Price Data'!F32*(1+'Stock Dividend'!F32+'Right Share Ratio'!F32)*Split!F32-'Price Data'!F31-'Right Share Ratio'!F32*'Right Share Offer Price'!F32*Split!F32)/'Price Data'!F31 -> -0.1340388 | G32: =('Price Data'!G32*(1+'Stock Dividend'!G32+'Right Share Ratio'!G32)*Split!G32-'Price Data'!G31-'Right Share Ratio'!G32*'Right Share Offer Price'!G32*Split!G32)/'Price Data'!G31 -> 0.029929577 | H32: =('Price Data'!H32*(1+'Stock Dividend'!H32+'Right Share Ratio'!H32)*Split!H32-'Price Data'!H31-'Right Share Ratio'!H32*'Right Share Offer Price'!H32*Split!H32)/'Price Data'!H31 -> 0.01996008 | I32: =('Price Data'!I32*(1+'Stock Dividend'!I32+'Right Share Ratio'!I32)*Split!I32-'Price Data'!I31-'Right Share Ratio'!I32*'Right Share Offer Price'!I32*Split!I32)/'Price Data'!I31 -> -0.13701016 | J32: =('Price Data'!J32*(1+'Stock Dividend'!J32+'Right Share Ratio'!J32)*Split!J32-'Price Data'!J31-'Right Share Ratio'!J32*'Right Share Offer Price'!J32*Split!J32)/'Price Data'!J31 -> -0.0059746079 | ... V32: =('Price Data'!V32*(1+'Stock Dividend'!V32+'Right Share Ratio'!V32)*Split!V32-'Price Data'!V31-'Right Share Ratio'!V32*'Right Share Offer Price'!V32*Split!V32)/'Price Data'!V31 -> 0.0083086053
B33: February | C33: =('Price Data'!C33*(1+'Stock Dividend'!C33+'Right Share Ratio'!C33)*Split!C33-'Price Data'!C32-'Right Share Ratio'!C33*'Right Share Offer Price'!C33*Split!C33)/'Price Data'!C32 -> 0.13250283 | D33: =('Price Data'!D33*(1+'Stock Dividend'!D33+'Right Share Ratio'!D33)*Split!D33-'Price Data'!D32-'Right Share Ratio'!D33*'Right Share Offer Price'!D33*Split!D33)/'Price Data'!D32 -> 0.017094017 | E33: =('Price Data'!E33*(1+'Stock Dividend'!E33+'Right Share Ratio'!E33)*Split!E33-'Price Data'!E32-'Right Share Ratio'!E33*'Right Share Offer Price'!E33*Split!E33)/'Price Data'!E32 -> 0.025752508 | F33: =('Price Data'!F33*(1+'Stock Dividend'!F33+'Right Share Ratio'!F33)*Split!F33-'Price Data'!F32-'Right Share Ratio'!F33*'Right Share Offer Price'!F33*Split!F33)/'Price Data'!F32 -> -0.042769857 | G33: =('Price Data'!G33*(1+'Stock Dividend'!G33+'Right Share Ratio'!G33)*Split!G33-'Price Data'!G32-'Right Share Ratio'!G33*'Right Share Offer Price'!G33*Split!G33)/'Price Data'!G32 -> -0.066666667 | H33: =('Price Data'!H33*(1+'Stock Dividend'!H33+'Right Share Ratio'!H33)*Split!H33-'Price Data'!H32-'Right Share Ratio'!H33*'Right Share Offer Price'!H33*Split!H33)/'Price Data'!H32 -> -0.019569472 | I33: =('Price Data'!I33*(1+'Stock Dividend'!I33+'Right Share Ratio'!I33)*Split!I33-'Price Data'!I32-'Right Share Ratio'!I33*'Right Share Offer Price'!I33*Split!I33)/'Price Data'!I32 -> 0.46787756 | J33: =('Price Data'!J33*(1+'Stock Dividend'!J33+'Right Share Ratio'!J33)*Split!J33-'Price Data'!J32-'Right Share Ratio'!J33*'Right Share Offer Price'!J33*Split!J33)/'Price Data'!J32 -> 0.19534185 | ... V33: =('Price Data'!V33*(1+'Stock Dividend'!V33+'Right Share Ratio'!V33)*Split!V33-'Price Data'!V32-'Right Share Ratio'!V33*'Right Share Offer Price'!V33*Split!V33)/'Price Data'!V32 -> 0.02707475
B34: March | C34: =('Price Data'!C34*(1+'Stock Dividend'!C34+'Right Share Ratio'!C34)*Split!C34-'Price Data'!C33-'Right Share Ratio'!C34*'Right Share Offer Price'!C34*Split!C34)/'Price Data'!C33 -> -0.058333333 | D34: =('Price Data'!D34*(1+'Stock Dividend'!D34+'Right Share Ratio'!D34)*Split!D34-'Price Data'!D33-'Right Share Ratio'!D34*'Right Share Offer Price'!D34*Split!D34)/'Price Data'!D33 -> 0 | E34: =('Price Data'!E34*(1+'Stock Dividend'!E34+'Right Share Ratio'!E34)*Split!E34-'Price Data'!E33-'Right Share Ratio'!E34*'Right Share Offer Price'!E34*Split!E34)/'Price Data'!E33 -> -0.15226606 | F34: =('Price Data'!F34*(1+'Stock Dividend'!F34+'Right Share Ratio'!F34)*Split!F34-'Price Data'!F33-'Right Share Ratio'!F34*'Right Share Offer Price'!F34*Split!F34)/'Price Data'!F33 -> -0.13191489 | G34: =('Price Data'!G34*(1+'Stock Dividend'!G34+'Right Share Ratio'!G34)*Split!G34-'Price Data'!G33-'Right Share Ratio'!G34*'Right Share Offer Price'!G34*Split!G34)/'Price Data'!G33 -> 0 | H34: =('Price Data'!H34*(1+'Stock Dividend'!H34+'Right Share Ratio'!H34)*Split!H34-'Price Data'!H33-'Right Share Ratio'!H34*'Right Share Offer Price'!H34*Split!H34)/'Price Data'!H33 -> -0.099800399 | I34: =('Price Data'!I34*(1+'Stock Dividend'!I34+'Right Share Ratio'!I34)*Split!I34-'Price Data'!I33-'Right Share Ratio'!I34*'Right Share Offer Price'!I34*Split!I34)/'Price Data'!I33 -> 0.13748854 | J34: =('Price Data'!J34*(1+'Stock Dividend'!J34+'Right Share Ratio'!J34)*Split!J34-'Price Data'!J33-'Right Share Ratio'!J34*'Right Share Offer Price'!J34*Split!J34)/'Price Data'!J33 -> 0.11879321 | ... V34: =('Price Data'!V34*(1+'Stock Dividend'!V34+'Right Share Ratio'!V34)*Split!V34-'Price Data'!V33-'Right Share Ratio'!V34*'Right Share Offer Price'!V34*Split!V34)/'Price Data'!V33 -> -0.0068767908
B35: April | C35: =('Price Data'!C35*(1+'Stock Dividend'!C35+'Right Share Ratio'!C35)*Split!C35-'Price Data'!C34-'Right Share Ratio'!C35*'Right Share Offer Price'!C35*Split!C35)/'Price Data'!C34 -> -0.037522124 | D35: =('Price Data'!D35*(1+'Stock Dividend'!D35+'Right Share Ratio'!D35)*Split!D35-'Price Data'!D34-'Right Share Ratio'!D35*'Right Share Offer Price'!D35*Split!D35)/'Price Data'!D34 -> 0 | E35: =('Price Data'!E35*(1+'Stock Dividend'!E35+'Right Share Ratio'!E35)*Split!E35-'Price Data'!E34-'Right Share Ratio'!E35*'Right Share Offer Price'!E35*Split!E35)/'Price Data'!E34 -> -0.16161538 | F35: =('Price Data'!F35*(1+'Stock Dividend'!F35+'Right Share Ratio'!F35)*Split!F35-'Price Data'!F34-'Right Share Ratio'!F35*'Right Share Offer Price'!F35*Split!F35)/'Price Data'!F34 -> -0.090686275 | G35: =('Price Data'!G35*(1+'Stock Dividend'!G35+'Right Share Ratio'!G35)*Split!G35-'Price Data'!G34-'Right Share Ratio'!G35*'Right Share Offer Price'!G35*Split!G35)/'Price Data'!G34 -> 0.064102564 | H35: =('Price Data'!H35*(1+'Stock Dividend'!H35+'Right Share Ratio'!H35)*Split!H35-'Price Data'!H34-'Right Share Ratio'!H35*'Right Share Offer Price'!H35*Split!H35)/'Price Data'!H34 -> -0.042128603 | I35: =('Price Data'!I35*(1+'Stock Dividend'!I35+'Right Share Ratio'!I35)*Split!I35-'Price Data'!I34-'Right Share Ratio'!I35*'Right Share Offer Price'!I35*Split!I35)/'Price Data'!I34 -> 0.45950846 | J35: =('Price Data'!J35*(1+'Stock Dividend'!J35+'Right Share Ratio'!J35)*Split!J35-'Price Data'!J34-'Right Share Ratio'!J35*'Right Share Offer Price'!J35*Split!J35)/'Price Data'!J34 -> -0.0011235955 | ... V35: =('Price Data'!V35*(1+'Stock Dividend'!V35+'Right Share Ratio'!V35)*Split!V35-'Price Data'!V34-'Right Share Ratio'!V35*'Right Share Offer Price'!V35*Split!V35)/'Price Data'!V34 -> 0.0069244085
B36: May | C36: =('Price Data'!C36*(1+'Stock Dividend'!C36+'Right Share Ratio'!C36)*Split!C36-'Price Data'!C35-'Right Share Ratio'!C36*'Right Share Offer Price'!C36*Split!C36)/'Price Data'!C35 -> 0.053880103 | D36: =('Price Data'!D36*(1+'Stock Dividend'!D36+'Right Share Ratio'!D36)*Split!D36-'Price Data'!D35-'Right Share Ratio'!D36*'Right Share Offer Price'!D36*Split!D36)/'Price Data'!D35 -> 0.033613445 | E36: =('Price Data'!E36*(1+'Stock Dividend'!E36+'Right Share Ratio'!E36)*Split!E36-'Price Data'!E35-'Right Share Ratio'!E36*'Right Share Offer Price'!E36*Split!E36)/'Price Data'!E35 -> -0.096339114 | F36: =('Price Data'!F36*(1+'Stock Dividend'!F36+'Right Share Ratio'!F36)*Split!F36-'Price Data'!F35-'Right Share Ratio'!F36*'Right Share Offer Price'!F36*Split!F36)/'Price Data'!F35 -> -0.1212938 | G36: =('Price Data'!G36*(1+'Stock Dividend'!G36+'Right Share Ratio'!G36)*Split!G36-'Price Data'!G35-'Right Share Ratio'!G36*'Right Share Offer Price'!G36*Split!G36)/'Price Data'!G35 -> -0.060240964 | H36: =('Price Data'!H36*(1+'Stock Dividend'!H36+'Right Share Ratio'!H36)*Split!H36-'Price Data'!H35-'Right Share Ratio'!H36*'Right Share Offer Price'!H36*Split!H36)/'Price Data'!H35 -> -0.090277778 | I36: =('Price Data'!I36*(1+'Stock Dividend'!I36+'Right Share Ratio'!I36)*Split!I36-'Price Data'!I35-'Right Share Ratio'!I36*'Right Share Offer Price'!I36*Split!I36)/'Price Data'!I35 -> 0.090407177 | J36: =('Price Data'!J36*(1+'Stock Dividend'!J36+'Right Share Ratio'!J36)*Split!J36-'Price Data'!J35-'Right Share Ratio'!J36*'Right Share Offer Price'!J36*Split!J36)/'Price Data'!J35 -> -0.067491564 | ... V36: =('Price Data'!V36*(1+'Stock Dividend'!V36+'Right Share Ratio'!V36)*Split!V36-'Price Data'!V35-'Right Share Ratio'!V36*'Right Share Offer Price'!V36*Split!V36)/'Price Data'!V35 -> -0.0252149
B37: June | C37: =('Price Data'!C37*(1+'Stock Dividend'!C37+'Right Share Ratio'!C37)*Split!C37-'Price Data'!C36-'Right Share Ratio'!C37*'Right Share Offer Price'!C37*Split!C37)/'Price Data'!C36 -> 0.017658349 | D37: =('Price Data'!D37*(1+'Stock Dividend'!D37+'Right Share Ratio'!D37)*Split!D37-'Price Data'!D36-'Right Share Ratio'!D37*'Right Share Offer Price'!D37*Split!D37)/'Price Data'!D36 -> -0.20325203 | E37: =('Price Data'!E37*(1+'Stock Dividend'!E37+'Right Share Ratio'!E37)*Split!E37-'Price Data'!E36-'Right Share Ratio'!E37*'Right Share Offer Price'!E37*Split!E37)/'Price Data'!E36 -> -0.055970149 | F37: =('Price Data'!F37*(1+'Stock Dividend'!F37+'Right Share Ratio'!F37)*Split!F37-'Price Data'!F36-'Right Share Ratio'!F37*'Right Share Offer Price'!F37*Split!F37)/'Price Data'!F36 -> -0.027607362 | G37: =('Price Data'!G37*(1+'Stock Dividend'!G37+'Right Share Ratio'!G37)*Split!G37-'Price Data'!G36-'Right Share Ratio'!G37*'Right Share Offer Price'!G37*Split!G37)/'Price Data'!G36 -> -0.023809524 | H37: =('Price Data'!H37*(1+'Stock Dividend'!H37+'Right Share Ratio'!H37)*Split!H37-'Price Data'!H36-'Right Share Ratio'!H37*'Right Share Offer Price'!H37*Split!H37)/'Price Data'!H36 -> 0.015267176 | I37: =('Price Data'!I37*(1+'Stock Dividend'!I37+'Right Share Ratio'!I37)*Split!I37-'Price Data'!I36-'Right Share Ratio'!I37*'Right Share Offer Price'!I37*Split!I37)/'Price Data'!I36 -> -0.0034177215 | J37: =('Price Data'!J37*(1+'Stock Dividend'!J37+'Right Share Ratio'!J37)*Split!J37-'Price Data'!J36-'Right Share Ratio'!J37*'Right Share Offer Price'!J37*Split!J37)/'Price Data'!J36 -> -0.0042219542 | ... V37: =('Price Data'!V37*(1+'Stock Dividend'!V37+'Right Share Ratio'!V37)*Split!V37-'Price Data'!V36-'Right Share Ratio'!V37*'Right Share Offer Price'!V37*Split!V37)/'Price Data'!V36 -> 0.026455026
B38: July | C38: =('Price Data'!C38*(1+'Stock Dividend'!C38+'Right Share Ratio'!C38)*Split!C38-'Price Data'!C37-'Right Share Ratio'!C38*'Right Share Offer Price'!C38*Split!C38)/'Price Data'!C37 -> 0.081855903 | D38: =('Price Data'!D38*(1+'Stock Dividend'!D38+'Right Share Ratio'!D38)*Split!D38-'Price Data'!D37-'Right Share Ratio'!D38*'Right Share Offer Price'!D38*Split!D38)/'Price Data'!D37 -> 0.06122449 | E38: =('Price Data'!E38*(1+'Stock Dividend'!E38+'Right Share Ratio'!E38)*Split!E38-'Price Data'!E37-'Right Share Ratio'!E38*'Right Share Offer Price'!E38*Split!E38)/'Price Data'!E37 -> 0.075663467 | F38: =('Price Data'!F38*(1+'Stock Dividend'!F38+'Right Share Ratio'!F38)*Split!F38-'Price Data'!F37-'Right Share Ratio'!F38*'Right Share Offer Price'!F38*Split!F38)/'Price Data'!F37 -> 0 | G38: =('Price Data'!G38*(1+'Stock Dividend'!G38+'Right Share Ratio'!G38)*Split!G38-'Price Data'!G37-'Right Share Ratio'!G38*'Right Share Offer Price'!G38*Split!G38)/'Price Data'!G37 -> 0.054409006 | H38: =('Price Data'!H38*(1+'Stock Dividend'!H38+'Right Share Ratio'!H38)*Split!H38-'Price Data'!H37-'Right Share Ratio'!H38*'Right Share Offer Price'!H38*Split!H38)/'Price Data'!H37 -> -0.037593985 | I38: =('Price Data'!I38*(1+'Stock Dividend'!I38+'Right Share Ratio'!I38)*Split!I38-'Price Data'!I37-'Right Share Ratio'!I38*'Right Share Offer Price'!I38*Split!I38)/'Price Data'!I37 -> 0.081925568 | J38: =('Price Data'!J38*(1+'Stock Dividend'!J38+'Right Share Ratio'!J38)*Split!J38-'Price Data'!J37-'Right Share Ratio'!J38*'Right Share Offer Price'!J38*Split!J38)/'Price Data'!J37 -> -0.012719564 | ... V38: =('Price Data'!V38*(1+'Stock Dividend'!V38+'Right Share Ratio'!V38)*Split!V38-'Price Data'!V37-'Right Share Ratio'!V38*'Right Share Offer Price'!V38*Split!V38)/'Price Data'!V37 -> 0.02233677
B39: August | C39: =('Price Data'!C39*(1+'Stock Dividend'!C39+'Right Share Ratio'!C39)*Split!C39-'Price Data'!C38-'Right Share Ratio'!C39*'Right Share Offer Price'!C39*Split!C39)/'Price Data'!C38 -> 0.44456067 | D39: =('Price Data'!D39*(1+'Stock Dividend'!D39+'Right Share Ratio'!D39)*Split!D39-'Price Data'!D38-'Right Share Ratio'!D39*'Right Share Offer Price'!D39*Split!D39)/'Price Data'!D38 -> 0.19230769 | E39: =('Price Data'!E39*(1+'Stock Dividend'!E39+'Right Share Ratio'!E39)*Split!E39-'Price Data'!E38-'Right Share Ratio'!E39*'Right Share Offer Price'!E39*Split!E39)/'Price Data'!E38 -> 0.23989501 | F39: =('Price Data'!F39*(1+'Stock Dividend'!F39+'Right Share Ratio'!F39)*Split!F39-'Price Data'!F38-'Right Share Ratio'!F39*'Right Share Offer Price'!F39*Split!F39)/'Price Data'!F38 -> 0.3659306 | G39: =('Price Data'!G39*(1+'Stock Dividend'!G39+'Right Share Ratio'!G39)*Split!G39-'Price Data'!G38-'Right Share Ratio'!G39*'Right Share Offer Price'!G39*Split!G39)/'Price Data'!G38 -> -0.1405694 | H39: =('Price Data'!H39*(1+'Stock Dividend'!H39+'Right Share Ratio'!H39)*Split!H39-'Price Data'!H38-'Right Share Ratio'!H39*'Right Share Offer Price'!H39*Split!H39)/'Price Data'!H38 -> 0.015625 | I39: =('Price Data'!I39*(1+'Stock Dividend'!I39+'Right Share Ratio'!I39)*Split!I39-'Price Data'!I38-'Right Share Ratio'!I39*'Right Share Offer Price'!I39*Split!I39)/'Price Data'!I38 -> -0.18138061 | J39: =('Price Data'!J39*(1+'Stock Dividend'!J39+'Right Share Ratio'!J39)*Split!J39-'Price Data'!J38-'Right Share Ratio'!J39*'Right Share Offer Price'!J39*Split!J39)/'Price Data'!J38 -> -0.015337423 | ... V39: =('Price Data'!V39*(1+'Stock Dividend'!V39+'Right Share Ratio'!V39)*Split!V39-'Price Data'!V38-'Right Share Ratio'!V39*'Right Share Offer Price'!V39*Split!V39)/'Price Data'!V38 -> 0.088515406
B40: September | C40: =('Price Data'!C40*(1+'Stock Dividend'!C40+'Right Share Ratio'!C40)*Split!C40-'Price Data'!C39-'Right Share Ratio'!C40*'Right Share Offer Price'!C40*Split!C40)/'Price Data'!C39 -> 0.011103065 | D40: =('Price Data'!D40*(1+'Stock Dividend'!D40+'Right Share Ratio'!D40)*Split!D40-'Price Data'!D39-'Right Share Ratio'!D40*'Right Share Offer Price'!D40*Split!D40)/'Price Data'!D39 -> -0.12903226 | E40: =('Price Data'!E40*(1+'Stock Dividend'!E40+'Right Share Ratio'!E40)*Split!E40-'Price Data'!E39-'Right Share Ratio'!E40*'Right Share Offer Price'!E40*Split!E40)/'Price Data'!E39 -> -0.14902625 | F40: =('Price Data'!F40*(1+'Stock Dividend'!F40+'Right Share Ratio'!F40)*Split!F40-'Price Data'!F39-'Right Share Ratio'!F40*'Right Share Offer Price'!F40*Split!F40)/'Price Data'!F39 -> -0.1108545 | G40: =('Price Data'!G40*(1+'Stock Dividend'!G40+'Right Share Ratio'!G40)*Split!G40-'Price Data'!G39-'Right Share Ratio'!G40*'Right Share Offer Price'!G40*Split!G40)/'Price Data'!G39 -> -0.20289855 | H40: =('Price Data'!H40*(1+'Stock Dividend'!H40+'Right Share Ratio'!H40)*Split!H40-'Price Data'!H39-'Right Share Ratio'!H40*'Right Share Offer Price'!H40*Split!H40)/'Price Data'!H39 -> -0.069230769 | I40: =('Price Data'!I40*(1+'Stock Dividend'!I40+'Right Share Ratio'!I40)*Split!I40-'Price Data'!I39-'Right Share Ratio'!I40*'Right Share Offer Price'!I40*Split!I40)/'Price Data'!I39 -> 0.13165065 | J40: =('Price Data'!J40*(1+'Stock Dividend'!J40+'Right Share Ratio'!J40)*Split!J40-'Price Data'!J39-'Right Share Ratio'!J40*'Right Share Offer Price'!J40*Split!J40)/'Price Data'!J39 -> 0.021806854 | ... V40: =('Price Data'!V40*(1+'Stock Dividend'!V40+'Right Share Ratio'!V40)*Split!V40-'Price Data'!V39-'Right Share Ratio'!V40*'Right Share Offer Price'!V40*Split!V40)/'Price Data'!V39 -> -0.079258878
B41: October | C41: =('Price Data'!C41*(1+'Stock Dividend'!C41+'Right Share Ratio'!C41)*Split!C41-'Price Data'!C40-'Right Share Ratio'!C41*'Right Share Offer Price'!C41*Split!C41)/'Price Data'!C40 -> -0.047982812 | D41: =('Price Data'!D41*(1+'Stock Dividend'!D41+'Right Share Ratio'!D41)*Split!D41-'Price Data'!D40-'Right Share Ratio'!D41*'Right Share Offer Price'!D41*Split!D41)/'Price Data'!D40 -> 0.10185185 | E41: =('Price Data'!E41*(1+'Stock Dividend'!E41+'Right Share Ratio'!E41)*Split!E41-'Price Data'!E40-'Right Share Ratio'!E41*'Right Share Offer Price'!E41*Split!E41)/'Price Data'!E40 -> -0.05721393 | F41: =('Price Data'!F41*(1+'Stock Dividend'!F41+'Right Share Ratio'!F41)*Split!F41-'Price Data'!F40-'Right Share Ratio'!F41*'Right Share Offer Price'!F41*Split!F41)/'Price Data'!F40 -> 0.031168831 | G41: =('Price Data'!G41*(1+'Stock Dividend'!G41+'Right Share Ratio'!G41)*Split!G41-'Price Data'!G40-'Right Share Ratio'!G41*'Right Share Offer Price'!G41*Split!G41)/'Price Data'!G40 -> -0.015584416 | H41: =('Price Data'!H41*(1+'Stock Dividend'!H41+'Right Share Ratio'!H41)*Split!H41-'Price Data'!H40-'Right Share Ratio'!H41*'Right Share Offer Price'!H41*Split!H41)/'Price Data'!H40 -> -0.12947658 | I41: =('Price Data'!I41*(1+'Stock Dividend'!I41+'Right Share Ratio'!I41)*Split!I41-'Price Data'!I40-'Right Share Ratio'!I41*'Right Share Offer Price'!I41*Split!I41)/'Price Data'!I40 -> 0.02420479 | J41: =('Price Data'!J41*(1+'Stock Dividend'!J41+'Right Share Ratio'!J41)*Split!J41-'Price Data'!J40-'Right Share Ratio'!J41*'Right Share Offer Price'!J41*Split!J41)/'Price Data'!J40 -> -0.039634146 | ... V41: =('Price Data'!V41*(1+'Stock Dividend'!V41+'Right Share Ratio'!V41)*Split!V41-'Price Data'!V40-'Right Share Ratio'!V41*'Right Share Offer Price'!V41*Split!V41)/'Price Data'!V40 -> -0.015651202
B42: November | C42: =('Price Data'!C42*(1+'Stock Dividend'!C42+'Right Share Ratio'!C42)*Split!C42-'Price Data'!C41-'Right Share Ratio'!C42*'Right Share Offer Price'!C42*Split!C42)/'Price Data'!C41 -> -0.063941825 | D42: =('Price Data'!D42*(1+'Stock Dividend'!D42+'Right Share Ratio'!D42)*Split!D42-'Price Data'!D41-'Right Share Ratio'!D42*'Right Share Offer Price'!D42*Split!D42)/'Price Data'!D41 -> -0.075630252 | E42: =('Price Data'!E42*(1+'Stock Dividend'!E42+'Right Share Ratio'!E42)*Split!E42-'Price Data'!E41-'Right Share Ratio'!E42*'Right Share Offer Price'!E42*Split!E42)/'Price Data'!E41 -> -0.0047493404 | F42: =('Price Data'!F42*(1+'Stock Dividend'!F42+'Right Share Ratio'!F42)*Split!F42-'Price Data'!F41-'Right Share Ratio'!F42*'Right Share Offer Price'!F42*Split!F42)/'Price Data'!F41 -> 0.032745592 | G42: =('Price Data'!G42*(1+'Stock Dividend'!G42+'Right Share Ratio'!G42)*Split!G42-'Price Data'!G41-'Right Share Ratio'!G42*'Right Share Offer Price'!G42*Split!G42)/'Price Data'!G41 -> 0.13456464 | H42: =('Price Data'!H42*(1+'Stock Dividend'!H42+'Right Share Ratio'!H42)*Split!H42-'Price Data'!H41-'Right Share Ratio'!H42*'Right Share Offer Price'!H42*Split!H42)/'Price Data'!H41 -> 0.088607595 | I42: =('Price Data'!I42*(1+'Stock Dividend'!I42+'Right Share Ratio'!I42)*Split!I42-'Price Data'!I41-'Right Share Ratio'!I42*'Right Share Offer Price'!I42*Split!I42)/'Price Data'!I41 -> 0.21269488 | J42: =('Price Data'!J42*(1+'Stock Dividend'!J42+'Right Share Ratio'!J42)*Split!J42-'Price Data'!J41-'Right Share Ratio'!J42*'Right Share Offer Price'!J42*Split!J42)/'Price Data'!J41 -> 0.35873016 | ... V42: =('Price Data'!V42*(1+'Stock Dividend'!V42+'Right Share Ratio'!V42)*Split!V42-'Price Data'!V41-'Right Share Ratio'!V42*'Right Share Offer Price'!V42*Split!V42)/'Price Data'!V41 -> 0.085178876
B43: December | C43: =('Price Data'!C43*(1+'Stock Dividend'!C43+'Right Share Ratio'!C43)*Split!C43-'Price Data'!C42-'Right Share Ratio'!C43*'Right Share Offer Price'!C43*Split!C43)/'Price Data'!C42 -> 0.014465577 | D43: =('Price Data'!D43*(1+'Stock Dividend'!D43+'Right Share Ratio'!D43)*Split!D43-'Price Data'!D42-'Right Share Ratio'!D43*'Right Share Offer Price'!D43*Split!D43)/'Price Data'!D42 -> -0.018181818 | E43: =('Price Data'!E43*(1+'Stock Dividend'!E43+'Right Share Ratio'!E43)*Split!E43-'Price Data'!E42-'Right Share Ratio'!E43*'Right Share Offer Price'!E43*Split!E43)/'Price Data'!E42 -> -0.075821845 | F43: =('Price Data'!F43*(1+'Stock Dividend'!F43+'Right Share Ratio'!F43)*Split!F43-'Price Data'!F42-'Right Share Ratio'!F43*'Right Share Offer Price'!F43*Split!F43)/'Price Data'!F42 -> -0.051219512 | G43: =('Price Data'!G43*(1+'Stock Dividend'!G43+'Right Share Ratio'!G43)*Split!G43-'Price Data'!G42-'Right Share Ratio'!G43*'Right Share Offer Price'!G43*Split!G43)/'Price Data'!G42 -> -0.041860465 | H43: =('Price Data'!H43*(1+'Stock Dividend'!H43+'Right Share Ratio'!H43)*Split!H43-'Price Data'!H42-'Right Share Ratio'!H43*'Right Share Offer Price'!H43*Split!H43)/'Price Data'!H42 -> -0.069767442 | I43: =('Price Data'!I43*(1+'Stock Dividend'!I43+'Right Share Ratio'!I43)*Split!I43-'Price Data'!I42-'Right Share Ratio'!I43*'Right Share Offer Price'!I43*Split!I43)/'Price Data'!I42 -> -0.028058361 | J43: =('Price Data'!J43*(1+'Stock Dividend'!J43+'Right Share Ratio'!J43)*Split!J43-'Price Data'!J42-'Right Share Ratio'!J43*'Right Share Offer Price'!J43*Split!J43)/'Price Data'!J42 -> 0.052803738 | ... V43: =('Price Data'!V43*(1+'Stock Dividend'!V43+'Right Share Ratio'!V43)*Split!V43-'Price Data'!V42-'Right Share Ratio'!V43*'Right Share Offer Price'!V43*Split!V43)/'Price Data'!V42 -> -0.10308739
A44: 2025 | B44: January | C44: =('Price Data'!C44*(1+'Stock Dividend'!C44+'Right Share Ratio'!C44)*Split!C44-'Price Data'!C43-'Right Share Ratio'!C44*'Right Share Offer Price'!C44*Split!C44)/'Price Data'!C43 -> 0.057301294 | D44: =('Price Data'!D44*(1+'Stock Dividend'!D44+'Right Share Ratio'!D44)*Split!D44-'Price Data'!D43-'Right Share Ratio'!D44*'Right Share Offer Price'!D44*Split!D44)/'Price Data'!D43 -> -0.046296296 | E44: =('Price Data'!E44*(1+'Stock Dividend'!E44+'Right Share Ratio'!E44)*Split!E44-'Price Data'!E43-'Right Share Ratio'!E44*'Right Share Offer Price'!E44*Split!E44)/'Price Data'!E43 -> -0.065404475 | F44: =('Price Data'!F44*(1+'Stock Dividend'!F44+'Right Share Ratio'!F44)*Split!F44-'Price Data'!F43-'Right Share Ratio'!F44*'Right Share Offer Price'!F44*Split!F44)/'Price Data'!F43 -> -0.092544987 | G44: =('Price Data'!G44*(1+'Stock Dividend'!G44+'Right Share Ratio'!G44)*Split!G44-'Price Data'!G43-'Right Share Ratio'!G44*'Right Share Offer Price'!G44*Split!G44)/'Price Data'!G43 -> -0.053398058 | H44: =('Price Data'!H44*(1+'Stock Dividend'!H44+'Right Share Ratio'!H44)*Split!H44-'Price Data'!H43-'Right Share Ratio'!H44*'Right Share Offer Price'!H44*Split!H44)/'Price Data'!H43 -> 0 | I44: =('Price Data'!I44*(1+'Stock Dividend'!I44+'Right Share Ratio'!I44)*Split!I44-'Price Data'!I43-'Right Share Ratio'!I44*'Right Share Offer Price'!I44*Split!I44)/'Price Data'!I43 -> -0.024249423 | J44: =('Price Data'!J44*(1+'Stock Dividend'!J44+'Right Share Ratio'!J44)*Split!J44-'Price Data'!J43-'Right Share Ratio'!J44*'Right Share Offer Price'!J44*Split!J44)/'Price Data'!J43 -> -0.14824678 | ... V44: =('Price Data'!V44*(1+'Stock Dividend'!V44+'Right Share Ratio'!V44)*Split!V44-'Price Data'!V43-'Right Share Ratio'!V44*'Right Share Offer Price'!V44*Split!V44)/'Price Data'!V43 -> 0.018669778
B45: February | C45: =('Price Data'!C45*(1+'Stock Dividend'!C45+'Right Share Ratio'!C45)*Split!C45-'Price Data'!C44-'Right Share Ratio'!C45*'Right Share Offer Price'!C45*Split!C45)/'Price Data'!C44 -> 0.0097402597 | D45: =('Price Data'!D45*(1+'Stock Dividend'!D45+'Right Share Ratio'!D45)*Split!D45-'Price Data'!D44-'Right Share Ratio'!D45*'Right Share Offer Price'!D45*Split!D45)/'Price Data'!D44 -> 0 | E45: =('Price Data'!E45*(1+'Stock Dividend'!E45+'Right Share Ratio'!E45)*Split!E45-'Price Data'!E44-'Right Share Ratio'!E45*'Right Share Offer Price'!E45*Split!E45)/'Price Data'!E44 -> 0.058317986 | F45: =('Price Data'!F45*(1+'Stock Dividend'!F45+'Right Share Ratio'!F45)*Split!F45-'Price Data'!F44-'Right Share Ratio'!F45*'Right Share Offer Price'!F45*Split!F45)/'Price Data'!F44 -> 0.050991501 | G45: =('Price Data'!G45*(1+'Stock Dividend'!G45+'Right Share Ratio'!G45)*Split!G45-'Price Data'!G44-'Right Share Ratio'!G45*'Right Share Offer Price'!G45*Split!G45)/'Price Data'!G44 -> -0.035897436 | H45: =('Price Data'!H45*(1+'Stock Dividend'!H45+'Right Share Ratio'!H45)*Split!H45-'Price Data'!H44-'Right Share Ratio'!H45*'Right Share Offer Price'!H45*Split!H45)/'Price Data'!H44 -> -0.040625 | I45: =('Price Data'!I45*(1+'Stock Dividend'!I45+'Right Share Ratio'!I45)*Split!I45-'Price Data'!I44-'Right Share Ratio'!I45*'Right Share Offer Price'!I45*Split!I45)/'Price Data'!I44 -> -0.001183432 | J45: =('Price Data'!J45*(1+'Stock Dividend'!J45+'Right Share Ratio'!J45)*Split!J45-'Price Data'!J44-'Right Share Ratio'!J45*'Right Share Offer Price'!J45*Split!J45)/'Price Data'!J44 -> 0.0046899427 | ... V45: =('Price Data'!V45*(1+'Stock Dividend'!V45+'Right Share Ratio'!V45)*Split!V45-'Price Data'!V44-'Right Share Ratio'!V45*'Right Share Offer Price'!V45*Split!V45)/'Price Data'!V44 -> 0.0040091638
B46: March | C46: =('Price Data'!C46*(1+'Stock Dividend'!C46+'Right Share Ratio'!C46)*Split!C46-'Price Data'!C45-'Right Share Ratio'!C46*'Right Share Offer Price'!C46*Split!C46)/'Price Data'!C45 -> -0.026960178 | D46: =('Price Data'!D46*(1+'Stock Dividend'!D46+'Right Share Ratio'!D46)*Split!D46-'Price Data'!D45-'Right Share Ratio'!D46*'Right Share Offer Price'!D46*Split!D46)/'Price Data'!D45 -> 0.058252427 | E46: =('Price Data'!E46*(1+'Stock Dividend'!E46+'Right Share Ratio'!E46)*Split!E46-'Price Data'!E45-'Right Share Ratio'!E46*'Right Share Offer Price'!E46*Split!E46)/'Price Data'!E45 -> -0.060904872 | F46: =('Price Data'!F46*(1+'Stock Dividend'!F46+'Right Share Ratio'!F46)*Split!F46-'Price Data'!F45-'Right Share Ratio'!F46*'Right Share Offer Price'!F46*Split!F46)/'Price Data'!F45 -> -0.026954178 | G46: =('Price Data'!G46*(1+'Stock Dividend'!G46+'Right Share Ratio'!G46)*Split!G46-'Price Data'!G45-'Right Share Ratio'!G46*'Right Share Offer Price'!G46*Split!G46)/'Price Data'!G45 -> 0.02393617 | H46: =('Price Data'!H46*(1+'Stock Dividend'!H46+'Right Share Ratio'!H46)*Split!H46-'Price Data'!H45-'Right Share Ratio'!H46*'Right Share Offer Price'!H46*Split!H46)/'Price Data'!H45 -> -0.022801303 | I46: =('Price Data'!I46*(1+'Stock Dividend'!I46+'Right Share Ratio'!I46)*Split!I46-'Price Data'!I45-'Right Share Ratio'!I46*'Right Share Offer Price'!I46*Split!I46)/'Price Data'!I45 -> -0.0071090047 | J46: =('Price Data'!J46*(1+'Stock Dividend'!J46+'Right Share Ratio'!J46)*Split!J46-'Price Data'!J45-'Right Share Ratio'!J46*'Right Share Offer Price'!J46*Split!J46)/'Price Data'!J45 -> 0.010373444 | ... V46: =('Price Data'!V46*(1+'Stock Dividend'!V46+'Right Share Ratio'!V46)*Split!V46-'Price Data'!V45-'Right Share Ratio'!V46*'Right Share Offer Price'!V46*Split!V46)/'Price Data'!V45 -> 0.0011409013
B47: April | C47: =('Price Data'!C47*(1+'Stock Dividend'!C47+'Right Share Ratio'!C47)*Split!C47-'Price Data'!C46-'Right Share Ratio'!C47*'Right Share Offer Price'!C47*Split!C47)/'Price Data'!C46 -> -0.02541942 | D47: =('Price Data'!D47*(1+'Stock Dividend'!D47+'Right Share Ratio'!D47)*Split!D47-'Price Data'!D46-'Right Share Ratio'!D47*'Right Share Offer Price'!D47*Split!D47)/'Price Data'!D46 -> -0.018348624 | E47: =('Price Data'!E47*(1+'Stock Dividend'!E47+'Right Share Ratio'!E47)*Split!E47-'Price Data'!E46-'Right Share Ratio'!E47*'Right Share Offer Price'!E47*Split!E47)/'Price Data'!E46 -> -0.046942557 | F47: =('Price Data'!F47*(1+'Stock Dividend'!F47+'Right Share Ratio'!F47)*Split!F47-'Price Data'!F46-'Right Share Ratio'!F47*'Right Share Offer Price'!F47*Split!F47)/'Price Data'!F46 -> -0.060941828 | G47: =('Price Data'!G47*(1+'Stock Dividend'!G47+'Right Share Ratio'!G47)*Split!G47-'Price Data'!G46-'Right Share Ratio'!G47*'Right Share Offer Price'!G47*Split!G47)/'Price Data'!G46 -> -0.096103896 | H47: =('Price Data'!H47*(1+'Stock Dividend'!H47+'Right Share Ratio'!H47)*Split!H47-'Price Data'!H46-'Right Share Ratio'!H47*'Right Share Offer Price'!H47*Split!H47)/'Price Data'!H46 -> 0.04 | I47: =('Price Data'!I47*(1+'Stock Dividend'!I47+'Right Share Ratio'!I47)*Split!I47-'Price Data'!I46-'Right Share Ratio'!I47*'Right Share Offer Price'!I47*Split!I47)/'Price Data'!I46 -> -0.0047732697 | J47: =('Price Data'!J47*(1+'Stock Dividend'!J47+'Right Share Ratio'!J47)*Split!J47-'Price Data'!J46-'Right Share Ratio'!J47*'Right Share Offer Price'!J47*Split!J47)/'Price Data'!J46 -> 0.036447639 | ... V47: =('Price Data'!V47*(1+'Stock Dividend'!V47+'Right Share Ratio'!V47)*Split!V47-'Price Data'!V46-'Right Share Ratio'!V47*'Right Share Offer Price'!V47*Split!V47)/'Price Data'!V46 -> -0.018803419
B48: May | C48: =('Price Data'!C48*(1+'Stock Dividend'!C48+'Right Share Ratio'!C48)*Split!C48-'Price Data'!C47-'Right Share Ratio'!C48*'Right Share Offer Price'!C48*Split!C48)/'Price Data'!C47 -> 0.17370892 | D48: =('Price Data'!D48*(1+'Stock Dividend'!D48+'Right Share Ratio'!D48)*Split!D48-'Price Data'!D47-'Right Share Ratio'!D48*'Right Share Offer Price'!D48*Split!D48)/'Price Data'!D47 -> -0.08411215 | E48: =('Price Data'!E48*(1+'Stock Dividend'!E48+'Right Share Ratio'!E48)*Split!E48-'Price Data'!E47-'Right Share Ratio'!E48*'Right Share Offer Price'!E48*Split!E48)/'Price Data'!E47 -> -0.060920285 | F48: =('Price Data'!F48*(1+'Stock Dividend'!F48+'Right Share Ratio'!F48)*Split!F48-'Price Data'!F47-'Right Share Ratio'!F48*'Right Share Offer Price'!F48*Split!F48)/'Price Data'!F47 -> -0.056047198 | G48: =('Price Data'!G48*(1+'Stock Dividend'!G48+'Right Share Ratio'!G48)*Split!G48-'Price Data'!G47-'Right Share Ratio'!G48*'Right Share Offer Price'!G48*Split!G48)/'Price Data'!G47 -> -0.020114943 | H48: =('Price Data'!H48*(1+'Stock Dividend'!H48+'Right Share Ratio'!H48)*Split!H48-'Price Data'!H47-'Right Share Ratio'!H48*'Right Share Offer Price'!H48*Split!H48)/'Price Data'!H47 -> -0.10897436 | I48: =('Price Data'!I48*(1+'Stock Dividend'!I48+'Right Share Ratio'!I48)*Split!I48-'Price Data'!I47-'Right Share Ratio'!I48*'Right Share Offer Price'!I48*Split!I48)/'Price Data'!I47 -> -0.037170264 | J48: =('Price Data'!J48*(1+'Stock Dividend'!J48+'Right Share Ratio'!J48)*Split!J48-'Price Data'!J47-'Right Share Ratio'!J48*'Right Share Offer Price'!J48*Split!J48)/'Price Data'!J47 -> 0.075284794 | ... V48: =('Price Data'!V48*(1+'Stock Dividend'!V48+'Right Share Ratio'!V48)*Split!V48-'Price Data'!V47-'Right Share Ratio'!V48*'Right Share Offer Price'!V48*Split!V48)/'Price Data'!V47 -> -0.0023228804
B49: June | C49: =('Price Data'!C49*(1+'Stock Dividend'!C49+'Right Share Ratio'!C49)*Split!C49-'Price Data'!C48-'Right Share Ratio'!C49*'Right Share Offer Price'!C49*Split!C49)/'Price Data'!C48 -> 0.10225 | D49: =('Price Data'!D49*(1+'Stock Dividend'!D49+'Right Share Ratio'!D49)*Split!D49-'Price Data'!D48-'Right Share Ratio'!D49*'Right Share Offer Price'!D49*Split!D49)/'Price Data'!D48 -> 0.010204082 | E49: =('Price Data'!E49*(1+'Stock Dividend'!E49+'Right Share Ratio'!E49)*Split!E49-'Price Data'!E48-'Right Share Ratio'!E49*'Right Share Offer Price'!E49*Split!E49)/'Price Data'!E48 -> 0.028985507 | F49: =('Price Data'!F49*(1+'Stock Dividend'!F49+'Right Share Ratio'!F49)*Split!F49-'Price Data'!F48-'Right Share Ratio'!F49*'Right Share Offer Price'!F49*Split!F49)/'Price Data'!F48 -> 0.071 | G49: =('Price Data'!G49*(1+'Stock Dividend'!G49+'Right Share Ratio'!G49)*Split!G49-'Price Data'!G48-'Right Share Ratio'!G49*'Right Share Offer Price'!G49*Split!G49)/'Price Data'!G48 -> 0.15249267 | H49: =('Price Data'!H49*(1+'Stock Dividend'!H49+'Right Share Ratio'!H49)*Split!H49-'Price Data'!H48-'Right Share Ratio'!H49*'Right Share Offer Price'!H49*Split!H49)/'Price Data'!H48 -> 0.039568345 | I49: =('Price Data'!I49*(1+'Stock Dividend'!I49+'Right Share Ratio'!I49)*Split!I49-'Price Data'!I48-'Right Share Ratio'!I49*'Right Share Offer Price'!I49*Split!I49)/'Price Data'!I48 -> 0.22789539 | J49: =('Price Data'!J49*(1+'Stock Dividend'!J49+'Right Share Ratio'!J49)*Split!J49-'Price Data'!J48-'Right Share Ratio'!J49*'Right Share Offer Price'!J49*Split!J49)/'Price Data'!J48 -> 0.090741594 | ... V49: =('Price Data'!V49*(1+'Stock Dividend'!V49+'Right Share Ratio'!V49)*Split!V49-'Price Data'!V48-'Right Share Ratio'!V49*'Right Share Offer Price'!V49*Split!V49)/'Price Data'!V48 -> 0.061699651
B50: July | C50: =('Price Data'!C50*(1+'Stock Dividend'!C50+'Right Share Ratio'!C50)*Split!C50-'Price Data'!C49-'Right Share Ratio'!C50*'Right Share Offer Price'!C50*Split!C50)/'Price Data'!C49 -> 0.3944205 | D50: =('Price Data'!D50*(1+'Stock Dividend'!D50+'Right Share Ratio'!D50)*Split!D50-'Price Data'!D49-'Right Share Ratio'!D50*'Right Share Offer Price'!D50*Split!D50)/'Price Data'!D49 -> 0.31313131 | E50: =('Price Data'!E50*(1+'Stock Dividend'!E50+'Right Share Ratio'!E50)*Split!E50-'Price Data'!E49-'Right Share Ratio'!E50*'Right Share Offer Price'!E50*Split!E50)/'Price Data'!E49 -> 0.33098592 | F50: =('Price Data'!F50*(1+'Stock Dividend'!F50+'Right Share Ratio'!F50)*Split!F50-'Price Data'!F49-'Right Share Ratio'!F50*'Right Share Offer Price'!F50*Split!F50)/'Price Data'!F49 -> 0.21428571 | G50: =('Price Data'!G50*(1+'Stock Dividend'!G50+'Right Share Ratio'!G50)*Split!G50-'Price Data'!G49-'Right Share Ratio'!G50*'Right Share Offer Price'!G50*Split!G50)/'Price Data'!G49 -> 0.043256997 | H50: =('Price Data'!H50*(1+'Stock Dividend'!H50+'Right Share Ratio'!H50)*Split!H50-'Price Data'!H49-'Right Share Ratio'!H50*'Right Share Offer Price'!H50*Split!H50)/'Price Data'!H49 -> 0.19377163 | I50: =('Price Data'!I50*(1+'Stock Dividend'!I50+'Right Share Ratio'!I50)*Split!I50-'Price Data'!I49-'Right Share Ratio'!I50*'Right Share Offer Price'!I50*Split!I50)/'Price Data'!I49 -> -0.062880325 | J50: =('Price Data'!J50*(1+'Stock Dividend'!J50+'Right Share Ratio'!J50)*Split!J50-'Price Data'!J49-'Right Share Ratio'!J50*'Right Share Offer Price'!J50*Split!J50)/'Price Data'!J49 -> 0.095016892 | ... V50: =('Price Data'!V50*(1+'Stock Dividend'!V50+'Right Share Ratio'!V50)*Split!V50-'Price Data'!V49-'Right Share Ratio'!V50*'Right Share Offer Price'!V50*Split!V50)/'Price Data'!V49 -> 0.043859649
B51: August | C51: =('Price Data'!C51*(1+'Stock Dividend'!C51+'Right Share Ratio'!C51)*Split!C51-'Price Data'!C50-'Right Share Ratio'!C51*'Right Share Offer Price'!C51*Split!C51)/'Price Data'!C50 -> 0.081977879 | D51: =('Price Data'!D51*(1+'Stock Dividend'!D51+'Right Share Ratio'!D51)*Split!D51-'Price Data'!D50-'Right Share Ratio'!D51*'Right Share Offer Price'!D51*Split!D51)/'Price Data'!D50 -> -0.069230769 | E51: =('Price Data'!E51*(1+'Stock Dividend'!E51+'Right Share Ratio'!E51)*Split!E51-'Price Data'!E50-'Right Share Ratio'!E51*'Right Share Offer Price'!E51*Split!E51)/'Price Data'!E50 -> 0.010582011 | F51: =('Price Data'!F51*(1+'Stock Dividend'!F51+'Right Share Ratio'!F51)*Split!F51-'Price Data'!F50-'Right Share Ratio'!F51*'Right Share Offer Price'!F51*Split!F51)/'Price Data'!F50 -> -0.053921569 | G51: =('Price Data'!G51*(1+'Stock Dividend'!G51+'Right Share Ratio'!G51)*Split!G51-'Price Data'!G50-'Right Share Ratio'!G51*'Right Share Offer Price'!G51*Split!G51)/'Price Data'!G50 -> 0.14146341 | H51: =('Price Data'!H51*(1+'Stock Dividend'!H51+'Right Share Ratio'!H51)*Split!H51-'Price Data'!H50-'Right Share Ratio'!H51*'Right Share Offer Price'!H51*Split!H51)/'Price Data'!H50 -> 0.031884058 | I51: =('Price Data'!I51*(1+'Stock Dividend'!I51+'Right Share Ratio'!I51)*Split!I51-'Price Data'!I50-'Right Share Ratio'!I51*'Right Share Offer Price'!I51*Split!I51)/'Price Data'!I50 -> 0.11796537 | J51: =('Price Data'!J51*(1+'Stock Dividend'!J51+'Right Share Ratio'!J51)*Split!J51-'Price Data'!J50-'Right Share Ratio'!J51*'Right Share Offer Price'!J51*Split!J51)/'Price Data'!J50 -> 0.10952565 | ... V51: =('Price Data'!V51*(1+'Stock Dividend'!V51+'Right Share Ratio'!V51)*Split!V51-'Price Data'!V50-'Right Share Ratio'!V51*'Right Share Offer Price'!V51*Split!V51)/'Price Data'!V50 -> 0.0036764706
B52: September | C52: =('Price Data'!C52*(1+'Stock Dividend'!C52+'Right Share Ratio'!C52)*Split!C52-'Price Data'!C51-'Right Share Ratio'!C52*'Right Share Offer Price'!C52*Split!C52)/'Price Data'!C51 -> -0.091551413 | D52: =('Price Data'!D52*(1+'Stock Dividend'!D52+'Right Share Ratio'!D52)*Split!D52-'Price Data'!D51-'Right Share Ratio'!D52*'Right Share Offer Price'!D52*Split!D52)/'Price Data'!D51 -> 0.0082644628 | E52: =('Price Data'!E52*(1+'Stock Dividend'!E52+'Right Share Ratio'!E52)*Split!E52-'Price Data'!E51-'Right Share Ratio'!E52*'Right Share Offer Price'!E52*Split!E52)/'Price Data'!E51 -> 0.15706806 | F52: =('Price Data'!F52*(1+'Stock Dividend'!F52+'Right Share Ratio'!F52)*Split!F52-'Price Data'!F51-'Right Share Ratio'!F52*'Right Share Offer Price'!F52*Split!F52)/'Price Data'!F51 -> -0.012953368 | G52: =('Price Data'!G52*(1+'Stock Dividend'!G52+'Right Share Ratio'!G52)*Split!G52-'Price Data'!G51-'Right Share Ratio'!G52*'Right Share Offer Price'!G52*Split!G52)/'Price Data'!G51 -> -0.051282051 | H52: =('Price Data'!H52*(1+'Stock Dividend'!H52+'Right Share Ratio'!H52)*Split!H52-'Price Data'!H51-'Right Share Ratio'!H52*'Right Share Offer Price'!H52*Split!H52)/'Price Data'!H51 -> -0.033707865 | I52: =('Price Data'!I52*(1+'Stock Dividend'!I52+'Right Share Ratio'!I52)*Split!I52-'Price Data'!I51-'Right Share Ratio'!I52*'Right Share Offer Price'!I52*Split!I52)/'Price Data'!I51 -> -0.063891578 | J52: =('Price Data'!J52*(1+'Stock Dividend'!J52+'Right Share Ratio'!J52)*Split!J52-'Price Data'!J51-'Right Share Ratio'!J52*'Right Share Offer Price'!J52*Split!J52)/'Price Data'!J51 -> 0.10079944 | ... V52: =('Price Data'!V52*(1+'Stock Dividend'!V52+'Right Share Ratio'!V52)*Split!V52-'Price Data'!V51-'Right Share Ratio'!V52*'Right Share Offer Price'!V52*Split!V52)/'Price Data'!V51 -> -0.019884877
B53: October | C53: =('Price Data'!C53*(1+'Stock Dividend'!C53+'Right Share Ratio'!C53)*Split!C53-'Price Data'!C52-'Right Share Ratio'!C53*'Right Share Offer Price'!C53*Split!C53)/'Price Data'!C52 -> -0.020023167 | D53: =('Price Data'!D53*(1+'Stock Dividend'!D53+'Right Share Ratio'!D53)*Split!D53-'Price Data'!D52-'Right Share Ratio'!D53*'Right Share Offer Price'!D53*Split!D53)/'Price Data'!D52 -> -0.090163934 | E53: =('Price Data'!E53*(1+'Stock Dividend'!E53+'Right Share Ratio'!E53)*Split!E53-'Price Data'!E52-'Right Share Ratio'!E53*'Right Share Offer Price'!E53*Split!E53)/'Price Data'!E52 -> -0.027149321 | F53: =('Price Data'!F53*(1+'Stock Dividend'!F53+'Right Share Ratio'!F53)*Split!F53-'Price Data'!F52-'Right Share Ratio'!F53*'Right Share Offer Price'!F53*Split!F53)/'Price Data'!F52 -> -0.039370079 | G53: =('Price Data'!G53*(1+'Stock Dividend'!G53+'Right Share Ratio'!G53)*Split!G53-'Price Data'!G52-'Right Share Ratio'!G53*'Right Share Offer Price'!G53*Split!G53)/'Price Data'!G52 -> -0.024774775 | H53: =('Price Data'!H53*(1+'Stock Dividend'!H53+'Right Share Ratio'!H53)*Split!H53-'Price Data'!H52-'Right Share Ratio'!H53*'Right Share Offer Price'!H53*Split!H53)/'Price Data'!H52 -> -0.075581395 | I53: =('Price Data'!I53*(1+'Stock Dividend'!I53+'Right Share Ratio'!I53)*Split!I53-'Price Data'!I52-'Right Share Ratio'!I53*'Right Share Offer Price'!I53*Split!I53)/'Price Data'!I52 -> -0.01344364 | J53: =('Price Data'!J53*(1+'Stock Dividend'!J53+'Right Share Ratio'!J53)*Split!J53-'Price Data'!J52-'Right Share Ratio'!J53*'Right Share Offer Price'!J53*Split!J53)/'Price Data'!J52 -> -0.026523524 | ... V53: =('Price Data'!V53*(1+'Stock Dividend'!V53+'Right Share Ratio'!V53)*Split!V53-'Price Data'!V52-'Right Share Ratio'!V53*'Right Share Offer Price'!V53*Split!V53)/'Price Data'!V52 -> 0.0026695141
B54: November | C54: =('Price Data'!C54*(1+'Stock Dividend'!C54+'Right Share Ratio'!C54)*Split!C54-'Price Data'!C53-'Right Share Ratio'!C54*'Right Share Offer Price'!C54*Split!C54)/'Price Data'!C53 -> -0.033772374 | D54: =('Price Data'!D54*(1+'Stock Dividend'!D54+'Right Share Ratio'!D54)*Split!D54-'Price Data'!D53-'Right Share Ratio'!D54*'Right Share Offer Price'!D54*Split!D54)/'Price Data'!D53 -> 0.045045045 | E54: =('Price Data'!E54*(1+'Stock Dividend'!E54+'Right Share Ratio'!E54)*Split!E54-'Price Data'!E53-'Right Share Ratio'!E54*'Right Share Offer Price'!E54*Split!E54)/'Price Data'!E53 -> -0.08372093 | F54: =('Price Data'!F54*(1+'Stock Dividend'!F54+'Right Share Ratio'!F54)*Split!F54-'Price Data'!F53-'Right Share Ratio'!F54*'Right Share Offer Price'!F54*Split!F54)/'Price Data'!F53 -> -0.024590164 | G54: =('Price Data'!G54*(1+'Stock Dividend'!G54+'Right Share Ratio'!G54)*Split!G54-'Price Data'!G53-'Right Share Ratio'!G54*'Right Share Offer Price'!G54*Split!G54)/'Price Data'!G53 -> -0.064665127 | H54: =('Price Data'!H54*(1+'Stock Dividend'!H54+'Right Share Ratio'!H54)*Split!H54-'Price Data'!H53-'Right Share Ratio'!H54*'Right Share Offer Price'!H54*Split!H54)/'Price Data'!H53 -> -0.044025157 | I54: =('Price Data'!I54*(1+'Stock Dividend'!I54+'Right Share Ratio'!I54)*Split!I54-'Price Data'!I53-'Right Share Ratio'!I54*'Right Share Offer Price'!I54*Split!I54)/'Price Data'!I53 -> -0.21745283 | J54: =('Price Data'!J54*(1+'Stock Dividend'!J54+'Right Share Ratio'!J54)*Split!J54-'Price Data'!J53-'Right Share Ratio'!J54*'Right Share Offer Price'!J54*Split!J54)/'Price Data'!J53 -> 0.023029517 | ... V54: =('Price Data'!V54*(1+'Stock Dividend'!V54+'Right Share Ratio'!V54)*Split!V54-'Price Data'!V53-'Right Share Ratio'!V54*'Right Share Offer Price'!V54*Split!V54)/'Price Data'!V53 -> 0.01970181
B55: December | C55: =('Price Data'!C55*(1+'Stock Dividend'!C55+'Right Share Ratio'!C55)*Split!C55-'Price Data'!C54-'Right Share Ratio'!C55*'Right Share Offer Price'!C55*Split!C55)/'Price Data'!C54 -> -0.041069556 | D55: =('Price Data'!D55*(1+'Stock Dividend'!D55+'Right Share Ratio'!D55)*Split!D55-'Price Data'!D54-'Right Share Ratio'!D55*'Right Share Offer Price'!D55*Split!D55)/'Price Data'!D54 -> 0.051724138 | E55: =('Price Data'!E55*(1+'Stock Dividend'!E55+'Right Share Ratio'!E55)*Split!E55-'Price Data'!E54-'Right Share Ratio'!E55*'Right Share Offer Price'!E55*Split!E55)/'Price Data'!E54 -> -0.040609137 | F55: =('Price Data'!F55*(1+'Stock Dividend'!F55+'Right Share Ratio'!F55)*Split!F55-'Price Data'!F54-'Right Share Ratio'!F55*'Right Share Offer Price'!F55*Split!F55)/'Price Data'!F54 -> -0.030812325 | G55: =('Price Data'!G55*(1+'Stock Dividend'!G55+'Right Share Ratio'!G55)*Split!G55-'Price Data'!G54-'Right Share Ratio'!G55*'Right Share Offer Price'!G55*Split!G55)/'Price Data'!G54 -> 0.064197531 | H55: =('Price Data'!H55*(1+'Stock Dividend'!H55+'Right Share Ratio'!H55)*Split!H55-'Price Data'!H54-'Right Share Ratio'!H55*'Right Share Offer Price'!H55*Split!H55)/'Price Data'!H54 -> 0.0032894737 | I55: =('Price Data'!I55*(1+'Stock Dividend'!I55+'Right Share Ratio'!I55)*Split!I55-'Price Data'!I54-'Right Share Ratio'!I55*'Right Share Offer Price'!I55*Split!I55)/'Price Data'!I54 -> -0.049226442 | J55: =('Price Data'!J55*(1+'Stock Dividend'!J55+'Right Share Ratio'!J55)*Split!J55-'Price Data'!J54-'Right Share Ratio'!J55*'Right Share Offer Price'!J55*Split!J55)/'Price Data'!J54 -> 0.20577045 | ... V55: =('Price Data'!V55*(1+'Stock Dividend'!V55+'Right Share Ratio'!V55)*Split!V55-'Price Data'!V54-'Right Share Ratio'!V55*'Right Share Offer Price'!V55*Split!V55)/'Price Data'!V54 -> -0.1232376
A56: 2026 | B56: January | C56: =('Price Data'!C56*(1+'Stock Dividend'!C56+'Right Share Ratio'!C56)*Split!C56-'Price Data'!C55-'Right Share Ratio'!C56*'Right Share Offer Price'!C56*Split!C56)/'Price Data'!C55 -> 0.17277201 | D56: =('Price Data'!D56*(1+'Stock Dividend'!D56+'Right Share Ratio'!D56)*Split!D56-'Price Data'!D55-'Right Share Ratio'!D56*'Right Share Offer Price'!D56*Split!D56)/'Price Data'!D55 -> 0.049180328 | E56: =('Price Data'!E56*(1+'Stock Dividend'!E56+'Right Share Ratio'!E56)*Split!E56-'Price Data'!E55-'Right Share Ratio'!E56*'Right Share Offer Price'!E56*Split!E56)/'Price Data'!E55 -> 0.042328042 | F56: =('Price Data'!F56*(1+'Stock Dividend'!F56+'Right Share Ratio'!F56)*Split!F56-'Price Data'!F55-'Right Share Ratio'!F56*'Right Share Offer Price'!F56*Split!F56)/'Price Data'!F55 -> 0.083815029 | G56: =('Price Data'!G56*(1+'Stock Dividend'!G56+'Right Share Ratio'!G56)*Split!G56-'Price Data'!G55-'Right Share Ratio'!G56*'Right Share Offer Price'!G56*Split!G56)/'Price Data'!G55 -> 0.27610209 | H56: =('Price Data'!H56*(1+'Stock Dividend'!H56+'Right Share Ratio'!H56)*Split!H56-'Price Data'!H55-'Right Share Ratio'!H56*'Right Share Offer Price'!H56*Split!H56)/'Price Data'!H55 -> 0.33770492 | I56: =('Price Data'!I56*(1+'Stock Dividend'!I56+'Right Share Ratio'!I56)*Split!I56-'Price Data'!I55-'Right Share Ratio'!I56*'Right Share Offer Price'!I56*Split!I56)/'Price Data'!I55 -> 0.025147929 | J56: =('Price Data'!J56*(1+'Stock Dividend'!J56+'Right Share Ratio'!J56)*Split!J56-'Price Data'!J55-'Right Share Ratio'!J56*'Right Share Offer Price'!J56*Split!J56)/'Price Data'!J55 -> 0.15435183 | ... V56: =('Price Data'!V56*(1+'Stock Dividend'!V56+'Right Share Ratio'!V56)*Split!V56-'Price Data'!V55-'Right Share Ratio'!V56*'Right Share Offer Price'!V56*Split!V56)/'Price Data'!V55 -> 0.0095294818
B57: February | C57: =('Price Data'!C57*(1+'Stock Dividend'!C57+'Right Share Ratio'!C57)*Split!C57-'Price Data'!C56-'Right Share Ratio'!C57*'Right Share Offer Price'!C57*Split!C57)/'Price Data'!C56 -> 0.18243978 | D57: =('Price Data'!D57*(1+'Stock Dividend'!D57+'Right Share Ratio'!D57)*Split!D57-'Price Data'!D56-'Right Share Ratio'!D57*'Right Share Offer Price'!D57*Split!D57)/'Price Data'!D56 -> 0.0390625 | E57: =('Price Data'!E57*(1+'Stock Dividend'!E57+'Right Share Ratio'!E57)*Split!E57-'Price Data'!E56-'Right Share Ratio'!E57*'Right Share Offer Price'!E57*Split!E57)/'Price Data'!E56 -> 0.040609137 | F57: =('Price Data'!F57*(1+'Stock Dividend'!F57+'Right Share Ratio'!F57)*Split!F57-'Price Data'!F56-'Right Share Ratio'!F57*'Right Share Offer Price'!F57*Split!F57)/'Price Data'!F56 -> 0.037333333 | G57: =('Price Data'!G57*(1+'Stock Dividend'!G57+'Right Share Ratio'!G57)*Split!G57-'Price Data'!G56-'Right Share Ratio'!G57*'Right Share Offer Price'!G57*Split!G57)/'Price Data'!G56 -> -0.030909091 | H57: =('Price Data'!H57*(1+'Stock Dividend'!H57+'Right Share Ratio'!H57)*Split!H57-'Price Data'!H56-'Right Share Ratio'!H57*'Right Share Offer Price'!H57*Split!H57)/'Price Data'!H56 -> -0.056372549 | I57: =('Price Data'!I57*(1+'Stock Dividend'!I57+'Right Share Ratio'!I57)*Split!I57-'Price Data'!I56-'Right Share Ratio'!I57*'Right Share Offer Price'!I57*Split!I57)/'Price Data'!I56 -> 0.01010101 | J57: =('Price Data'!J57*(1+'Stock Dividend'!J57+'Right Share Ratio'!J57)*Split!J57-'Price Data'!J56-'Right Share Ratio'!J57*'Right Share Offer Price'!J57*Split!J57)/'Price Data'!J56 -> 0.072665148 | ... V57: =('Price Data'!V57*(1+'Stock Dividend'!V57+'Right Share Ratio'!V57)*Split!V57-'Price Data'!V56-'Right Share Ratio'!V57*'Right Share Offer Price'!V57*Split!V57)/'Price Data'!V56 -> 0.044247788
B58: March | C58: =('Price Data'!C58*(1+'Stock Dividend'!C58+'Right Share Ratio'!C58)*Split!C58-'Price Data'!C57-'Right Share Ratio'!C58*'Right Share Offer Price'!C58*Split!C58)/'Price Data'!C57 -> -0.23432777 | D58: =('Price Data'!D58*(1+'Stock Dividend'!D58+'Right Share Ratio'!D58)*Split!D58-'Price Data'!D57-'Right Share Ratio'!D58*'Right Share Offer Price'!D58*Split!D58)/'Price Data'!D57 -> -0.037593985 | E58: =('Price Data'!E58*(1+'Stock Dividend'!E58+'Right Share Ratio'!E58)*Split!E58-'Price Data'!E57-'Right Share Ratio'!E58*'Right Share Offer Price'!E58*Split!E58)/'Price Data'!E57 -> -0.087804878 | F58: =('Price Data'!F58*(1+'Stock Dividend'!F58+'Right Share Ratio'!F58)*Split!F58-'Price Data'!F57-'Right Share Ratio'!F58*'Right Share Offer Price'!F58*Split!F58)/'Price Data'!F57 -> -0.064267352 | G58: =('Price Data'!G58*(1+'Stock Dividend'!G58+'Right Share Ratio'!G58)*Split!G58-'Price Data'!G57-'Right Share Ratio'!G58*'Right Share Offer Price'!G58*Split!G58)/'Price Data'!G57 -> -0.018761726 | H58: =('Price Data'!H58*(1+'Stock Dividend'!H58+'Right Share Ratio'!H58)*Split!H58-'Price Data'!H57-'Right Share Ratio'!H58*'Right Share Offer Price'!H58*Split!H58)/'Price Data'!H57 -> -0.036363636 | I58: =('Price Data'!I58*(1+'Stock Dividend'!I58+'Right Share Ratio'!I58)*Split!I58-'Price Data'!I57-'Right Share Ratio'!I58*'Right Share Offer Price'!I58*Split!I58)/'Price Data'!I57 -> -0.018571429 | J58: =('Price Data'!J58*(1+'Stock Dividend'!J58+'Right Share Ratio'!J58)*Split!J58-'Price Data'!J57-'Right Share Ratio'!J58*'Right Share Offer Price'!J58*Split!J58)/'Price Data'!J57 -> 0.029093226 | ... V58: =('Price Data'!V58*(1+'Stock Dividend'!V58+'Right Share Ratio'!V58)*Split!V58-'Price Data'!V57-'Right Share Ratio'!V58*'Right Share Offer Price'!V58*Split!V58)/'Price Data'!V57 -> -0.033333333
B59: April | C59: =('Price Data'!C59*(1+'Stock Dividend'!C59+'Right Share Ratio'!C59)*Split!C59-'Price Data'!C58-'Right Share Ratio'!C59*'Right Share Offer Price'!C59*Split!C59)/'Price Data'!C58 -> 0.092516306 | D59: =('Price Data'!D59*(1+'Stock Dividend'!D59+'Right Share Ratio'!D59)*Split!D59-'Price Data'!D58-'Right Share Ratio'!D59*'Right Share Offer Price'!D59*Split!D59)/'Price Data'!D58 -> 0.3203125 | E59: =('Price Data'!E59*(1+'Stock Dividend'!E59+'Right Share Ratio'!E59)*Split!E59-'Price Data'!E58-'Right Share Ratio'!E59*'Right Share Offer Price'!E59*Split!E59)/'Price Data'!E58 -> 0.0053475936 | F59: =('Price Data'!F59*(1+'Stock Dividend'!F59+'Right Share Ratio'!F59)*Split!F59-'Price Data'!F58-'Right Share Ratio'!F59*'Right Share Offer Price'!F59*Split!F59)/'Price Data'!F58 -> 0.046703297 | G59: =('Price Data'!G59*(1+'Stock Dividend'!G59+'Right Share Ratio'!G59)*Split!G59-'Price Data'!G58-'Right Share Ratio'!G59*'Right Share Offer Price'!G59*Split!G59)/'Price Data'!G58 -> 0.015296367 | H59: =('Price Data'!H59*(1+'Stock Dividend'!H59+'Right Share Ratio'!H59)*Split!H59-'Price Data'!H58-'Right Share Ratio'!H59*'Right Share Offer Price'!H59*Split!H59)/'Price Data'!H58 -> 0.018867925 | I59: =('Price Data'!I59*(1+'Stock Dividend'!I59+'Right Share Ratio'!I59)*Split!I59-'Price Data'!I58-'Right Share Ratio'!I59*'Right Share Offer Price'!I59*Split!I59)/'Price Data'!I58 -> 0.23289665 | J59: =('Price Data'!J59*(1+'Stock Dividend'!J59+'Right Share Ratio'!J59)*Split!J59-'Price Data'!J58-'Right Share Ratio'!J59*'Right Share Offer Price'!J59*Split!J59)/'Price Data'!J58 -> 0.095542716 | ... V59: =('Price Data'!V59*(1+'Stock Dividend'!V59+'Right Share Ratio'!V59)*Split!V59-'Price Data'!V58-'Right Share Ratio'!V59*'Right Share Offer Price'!V59*Split!V59)/'Price Data'!V58 -> -0.0093512566
B60: May | C60: =('Price Data'!C60*(1+'Stock Dividend'!C60+'Right Share Ratio'!C60)*Split!C60-'Price Data'!C59-'Right Share Ratio'!C60*'Right Share Offer Price'!C60*Split!C60)/'Price Data'!C59 -> 0.21594658 | D60: =('Price Data'!D60*(1+'Stock Dividend'!D60+'Right Share Ratio'!D60)*Split!D60-'Price Data'!D59-'Right Share Ratio'!D60*'Right Share Offer Price'!D60*Split!D60)/'Price Data'!D59 -> -0.10153846 | E60: =('Price Data'!E60*(1+'Stock Dividend'!E60+'Right Share Ratio'!E60)*Split!E60-'Price Data'!E59-'Right Share Ratio'!E60*'Right Share Offer Price'!E60*Split!E60)/'Price Data'!E59 -> 0.0053191489 | F60: =('Price Data'!F60*(1+'Stock Dividend'!F60+'Right Share Ratio'!F60)*Split!F60-'Price Data'!F59-'Right Share Ratio'!F60*'Right Share Offer Price'!F60*Split!F60)/'Price Data'!F59 -> -0.020997375 | G60: =('Price Data'!G60*(1+'Stock Dividend'!G60+'Right Share Ratio'!G60)*Split!G60-'Price Data'!G59-'Right Share Ratio'!G60*'Right Share Offer Price'!G60*Split!G60)/'Price Data'!G59 -> -0.041431262 | H60: =('Price Data'!H60*(1+'Stock Dividend'!H60+'Right Share Ratio'!H60)*Split!H60-'Price Data'!H59-'Right Share Ratio'!H60*'Right Share Offer Price'!H60*Split!H60)/'Price Data'!H59 -> 0.11111111 | I60: =('Price Data'!I60*(1+'Stock Dividend'!I60+'Right Share Ratio'!I60)*Split!I60-'Price Data'!I59-'Right Share Ratio'!I60*'Right Share Offer Price'!I60*Split!I60)/'Price Data'!I59 -> -0.10743802 | J60: =('Price Data'!J60*(1+'Stock Dividend'!J60+'Right Share Ratio'!J60)*Split!J60-'Price Data'!J59-'Right Share Ratio'!J60*'Right Share Offer Price'!J60*Split!J60)/'Price Data'!J59 -> 0.086833679 | ... V60: =('Price Data'!V60*(1+'Stock Dividend'!V60+'Right Share Ratio'!V60)*Split!V60-'Price Data'!V59-'Right Share Ratio'!V60*'Right Share Offer Price'!V60*Split!V60)/'Price Data'!V59 -> -0.005899705
B61: June | C61: =('Price Data'!C61*(1+'Stock Dividend'!C61+'Right Share Ratio'!C61)*Split!C61-'Price Data'!C60-'Right Share Ratio'!C61*'Right Share Offer Price'!C61*Split!C61)/'Price Data'!C60 -> -0.026745914 | D61: =('Price Data'!D61*(1+'Stock Dividend'!D61+'Right Share Ratio'!D61)*Split!D61-'Price Data'!D60-'Right Share Ratio'!D61*'Right Share Offer Price'!D61*Split!D61)/'Price Data'!D60 -> 0.095890411 | E61: =('Price Data'!E61*(1+'Stock Dividend'!E61+'Right Share Ratio'!E61)*Split!E61-'Price Data'!E60-'Right Share Ratio'!E61*'Right Share Offer Price'!E61*Split!E61)/'Price Data'!E60 -> 0.82777778 | F61: =('Price Data'!F61*(1+'Stock Dividend'!F61+'Right Share Ratio'!F61)*Split!F61-'Price Data'!F60-'Right Share Ratio'!F61*'Right Share Offer Price'!F61*Split!F61)/'Price Data'!F60 -> 0.09919571 | G61: =('Price Data'!G61*(1+'Stock Dividend'!G61+'Right Share Ratio'!G61)*Split!G61-'Price Data'!G60-'Right Share Ratio'!G61*'Right Share Offer Price'!G61*Split!G61)/'Price Data'!G60 -> 0.2632613 | H61: =('Price Data'!H61*(1+'Stock Dividend'!H61+'Right Share Ratio'!H61)*Split!H61-'Price Data'!H60-'Right Share Ratio'!H61*'Right Share Offer Price'!H61*Split!H61)/'Price Data'!H60 -> 0.080952381 | I61: =('Price Data'!I61*(1+'Stock Dividend'!I61+'Right Share Ratio'!I61)*Split!I61-'Price Data'!I60-'Right Share Ratio'!I61*'Right Share Offer Price'!I61*Split!I61)/'Price Data'!I60 -> -0.062169312 | J61: =('Price Data'!J61*(1+'Stock Dividend'!J61+'Right Share Ratio'!J61)*Split!J61-'Price Data'!J60-'Right Share Ratio'!J61*'Right Share Offer Price'!J61*Split!J61)/'Price Data'!J60 -> -0.10935875 | ... V61: =('Price Data'!V61*(1+'Stock Dividend'!V61+'Right Share Ratio'!V61)*Split!V61-'Price Data'!V60-'Right Share Ratio'!V61*'Right Share Offer Price'!V61*Split!V61)/'Price Data'!V60 -> 0.10682493
B62: July | C62: =('Price Data'!C62*(1+'Stock Dividend'!C62+'Right Share Ratio'!C62)*Split!C62-'Price Data'!C61-'Right Share Ratio'!C62*'Right Share Offer Price'!C62*Split!C62)/'Price Data'!C61 -> -0.033587786 | D62: =('Price Data'!D62*(1+'Stock Dividend'!D62+'Right Share Ratio'!D62)*Split!D62-'Price Data'!D61-'Right Share Ratio'!D62*'Right Share Offer Price'!D62*Split!D62)/'Price Data'!D61 -> -0.0375 | E62: =('Price Data'!E62*(1+'Stock Dividend'!E62+'Right Share Ratio'!E62)*Split!E62-'Price Data'!E61-'Right Share Ratio'!E62*'Right Share Offer Price'!E62*Split!E62)/'Price Data'!E61 -> -0.021276596 | F62: =('Price Data'!F62*(1+'Stock Dividend'!F62+'Right Share Ratio'!F62)*Split!F62-'Price Data'!F61-'Right Share Ratio'!F62*'Right Share Offer Price'!F62*Split!F62)/'Price Data'!F61 -> 0.073170732 | G62: =('Price Data'!G62*(1+'Stock Dividend'!G62+'Right Share Ratio'!G62)*Split!G62-'Price Data'!G61-'Right Share Ratio'!G62*'Right Share Offer Price'!G62*Split!G62)/'Price Data'!G61 -> -0.020217729 | H62: =('Price Data'!H62*(1+'Stock Dividend'!H62+'Right Share Ratio'!H62)*Split!H62-'Price Data'!H61-'Right Share Ratio'!H62*'Right Share Offer Price'!H62*Split!H62)/'Price Data'!H61 -> 0.061674009 | I62: =('Price Data'!I62*(1+'Stock Dividend'!I62+'Right Share Ratio'!I62)*Split!I62-'Price Data'!I61-'Right Share Ratio'!I62*'Right Share Offer Price'!I62*Split!I62)/'Price Data'!I61 -> -0.019746121 | J62: =('Price Data'!J62*(1+'Stock Dividend'!J62+'Right Share Ratio'!J62)*Split!J62-'Price Data'!J61-'Right Share Ratio'!J62*'Right Share Offer Price'!J62*Split!J62)/'Price Data'!J61 -> -0.061685153 | ... V62: =('Price Data'!V62*(1+'Stock Dividend'!V62+'Right Share Ratio'!V62)*Split!V62-'Price Data'!V61-'Right Share Ratio'!V62*'Right Share Offer Price'!V62*Split!V62)/'Price Data'!V61 -> -0.021983914
B63: August | C63: =('Price Data'!C63*(1+'Stock Dividend'!C63+'Right Share Ratio'!C63)*Split!C63-'Price Data'!C62-'Right Share Ratio'!C63*'Right Share Offer Price'!C63*Split!C63)/'Price Data'!C62 -> -0.017377567 | D63: =('Price Data'!D63*(1+'Stock Dividend'!D63+'Right Share Ratio'!D63)*Split!D63-'Price Data'!D62-'Right Share Ratio'!D63*'Right Share Offer Price'!D63*Split!D63)/'Price Data'!D62 -> -0.025974026 | E63: =('Price Data'!E63*(1+'Stock Dividend'!E63+'Right Share Ratio'!E63)*Split!E63-'Price Data'!E62-'Right Share Ratio'!E63*'Right Share Offer Price'!E63*Split!E63)/'Price Data'!E62 -> -0.037267081 | F63: =('Price Data'!F63*(1+'Stock Dividend'!F63+'Right Share Ratio'!F63)*Split!F63-'Price Data'!F62-'Right Share Ratio'!F63*'Right Share Offer Price'!F63*Split!F63)/'Price Data'!F62 -> -0.072727273 | G63: =('Price Data'!G63*(1+'Stock Dividend'!G63+'Right Share Ratio'!G63)*Split!G63-'Price Data'!G62-'Right Share Ratio'!G63*'Right Share Offer Price'!G63*Split!G63)/'Price Data'!G62 -> -0.06984127 | H63: =('Price Data'!H63*(1+'Stock Dividend'!H63+'Right Share Ratio'!H63)*Split!H63-'Price Data'!H62-'Right Share Ratio'!H63*'Right Share Offer Price'!H63*Split!H63)/'Price Data'!H62 -> -0.020746888 | I63: =('Price Data'!I63*(1+'Stock Dividend'!I63+'Right Share Ratio'!I63)*Split!I63-'Price Data'!I62-'Right Share Ratio'!I63*'Right Share Offer Price'!I63*Split!I63)/'Price Data'!I62 -> -0.24460432 | J63: =('Price Data'!J63*(1+'Stock Dividend'!J63+'Right Share Ratio'!J63)*Split!J63-'Price Data'!J62-'Right Share Ratio'!J63*'Right Share Offer Price'!J63*Split!J63)/'Price Data'!J62 -> -0.020738283 | ... V63: =('Price Data'!V63*(1+'Stock Dividend'!V63+'Right Share Ratio'!V63)*Split!V63-'Price Data'!V62-'Right Share Ratio'!V63*'Right Share Offer Price'!V63*Split!V63)/'Price Data'!V62 -> -0.035087719

Sheet Total Return
C1: Bank | E1: Financial Institutions | G1: Insurance | I1: Food & Allied | L1: Miscellaneous | M1: Tannery | N1: Cement | O1: Telecommunication | P1: Pharmacuticals & Chemicals | T1: Engineering | U1: IT Sector | V1: Fuel & Power
A2: Years | B2: Months | C2: BRACBANK | D2: NCC | E2: IPDC | F2: DBH | G2: PARAMOUNT | H2: ASIAPACINS | I2: LOVELLO | J2: FINEFOODS | K2: OLYMPIC | L2: INDEXAGRO | M2: APEXFOOT | N2: CONFIDCEM | O2: GP | P2: IBNSINA | Q2: RENATA | R2: MARICO | S2: RECKITTBEN | T2: KDSALTD | U2: ADNTEL | V2: JAMUNAOIL
A3: 2021 | B3: August
B4: September | C4: ='Dividend Yield'!C4+'Capital Gain'!C4 -> 0.010392985 | D4: ='Dividend Yield'!D4+'Capital Gain'!D4 -> 0.0064102564 | E4: ='Dividend Yield'!E4+'Capital Gain'!E4 -> 0.25583288 | F4: ='Dividend Yield'!F4+'Capital Gain'!F4 -> 0.049779205 | G4: ='Dividend Yield'!G4+'Capital Gain'!G4 -> -0.063901345 | H4: ='Dividend Yield'!H4+'Capital Gain'!H4 -> -0.032394366 | I4: ='Dividend Yield'!I4+'Capital Gain'!I4 -> 0.05820275 | J4: ='Dividend Yield'!J4+'Capital Gain'!J4 -> -0.049557522 | ... V4: ='Dividend Yield'!V4+'Capital Gain'!V4 -> 0.0054674686
B5: October | C5: ='Dividend Yield'!C5+'Capital Gain'!C5 -> -0.037608486 | D5: ='Dividend Yield'!D5+'Capital Gain'!D5 -> -0.012738854 | E5: ='Dividend Yield'!E5+'Capital Gain'!E5 -> -0.14625189 | F5: ='Dividend Yield'!F5+'Capital Gain'!F5 -> -0.070618228 | G5: ='Dividend Yield'!G5+'Capital Gain'!G5 -> -0.05988024 | H5: ='Dividend Yield'!H5+'Capital Gain'!H5 -> -0.013100437 | I5: ='Dividend Yield'!I5+'Capital Gain'!I5 -> -0.022061046 | J5: ='Dividend Yield'!J5+'Capital Gain'!J5 -> -0.23091248 | ... V5: ='Dividend Yield'!V5+'Capital Gain'!V5 -> -0.057096248
B6: November | C6: ='Dividend Yield'!C6+'Capital Gain'!C6 -> 0.18336673 | D6: ='Dividend Yield'!D6+'Capital Gain'!D6 -> -0.0064516129 | E6: ='Dividend Yield'!E6+'Capital Gain'!E6 -> -0.057692308 | F6: ='Dividend Yield'!F6+'Capital Gain'!F6 -> -0.037443423 | G6: ='Dividend Yield'!G6+'Capital Gain'!G6 -> -0.095541401 | H6: ='Dividend Yield'!H6+'Capital Gain'!H6 -> -0.095870206 | I6: ='Dividend Yield'!I6+'Capital Gain'!I6 -> 0.066568463 | J6: ='Dividend Yield'!J6+'Capital Gain'!J6 -> -0.079903148 | ... V6: ='Dividend Yield'!V6+'Capital Gain'!V6 -> -0.01384083
B7: December | C7: ='Dividend Yield'!C7+'Capital Gain'!C7 -> 0.020321761 | D7: ='Dividend Yield'!D7+'Capital Gain'!D7 -> -0.0064935065 | E7: ='Dividend Yield'!E7+'Capital Gain'!E7 -> -0.012889366 | F7: ='Dividend Yield'!F7+'Capital Gain'!F7 -> -0.0012824166 | G7: ='Dividend Yield'!G7+'Capital Gain'!G7 -> 0.032394366 | H7: ='Dividend Yield'!H7+'Capital Gain'!H7 -> 0.11745514 | I7: ='Dividend Yield'!I7+'Capital Gain'!I7 -> -0.086696562 | J7: ='Dividend Yield'!J7+'Capital Gain'!J7 -> 0.32631579 | ... V7: ='Dividend Yield'!V7+'Capital Gain'!V7 -> 0.00058479532
A8: 2022 | B8: January | C8: ='Dividend Yield'!C8+'Capital Gain'!C8 -> -0.0019363762 | D8: ='Dividend Yield'!D8+'Capital Gain'!D8 -> -0.0065359477 | E8: ='Dividend Yield'!E8+'Capital Gain'!E8 -> 0.015505985 | F8: ='Dividend Yield'!F8+'Capital Gain'!F8 -> -0.00385219 | G8: ='Dividend Yield'!G8+'Capital Gain'!G8 -> -0.028649386 | H8: ='Dividend Yield'!H8+'Capital Gain'!H8 -> -0.054014599 | I8: ='Dividend Yield'!I8+'Capital Gain'!I8 -> 0.15155483 | J8: ='Dividend Yield'!J8+'Capital Gain'!J8 -> -0.071428571 | ... V8: ='Dividend Yield'!V8+'Capital Gain'!V8 -> 0.05222674
B9: February | C9: ='Dividend Yield'!C9+'Capital Gain'!C9 -> -0.021618625 | D9: ='Dividend Yield'!D9+'Capital Gain'!D9 -> -0.013157895 | E9: ='Dividend Yield'!E9+'Capital Gain'!E9 -> -0.071256362 | F9: ='Dividend Yield'!F9+'Capital Gain'!F9 -> -0.045545689 | G9: ='Dividend Yield'!G9+'Capital Gain'!G9 -> -0.058988764 | H9: ='Dividend Yield'!H9+'Capital Gain'!H9 -> -0.12191358 | I9: ='Dividend Yield'!I9+'Capital Gain'!I9 -> -0.054292211 | J9: ='Dividend Yield'!J9+'Capital Gain'!J9 -> 0.023504274 | ... V9: ='Dividend Yield'!V9+'Capital Gain'!V9 -> 0.0023837902
B10: March | C10: ='Dividend Yield'!C10+'Capital Gain'!C10 -> -0.079603399 | D10: ='Dividend Yield'!D10+'Capital Gain'!D10 -> 0.026666667 | E10: ='Dividend Yield'!E10+'Capital Gain'!E10 -> 0.16492121 | F10: ='Dividend Yield'!F10+'Capital Gain'!F10 -> 0.10569899 | G10: ='Dividend Yield'!G10+'Capital Gain'!G10 -> -0.08358209 | H10: ='Dividend Yield'!H10+'Capital Gain'!H10 -> -0.029876977 | I10: ='Dividend Yield'!I10+'Capital Gain'!I10 -> 0.13946498 | J10: ='Dividend Yield'!J10+'Capital Gain'!J10 -> -0.048016701 | ... V10: ='Dividend Yield'!V10+'Capital Gain'!V10 -> -0.029726516
B11: April | C11: ='Dividend Yield'!C11+'Capital Gain'!C11 -> 0.092580638 | D11: ='Dividend Yield'!D11+'Capital Gain'!D11 -> 0.012987013 | E11: ='Dividend Yield'!E11+'Capital Gain'!E11 -> 0.37782863 | F11: ='Dividend Yield'!F11+'Capital Gain'!F11 -> 0.012195122 | G11: ='Dividend Yield'!G11+'Capital Gain'!G11 -> -0.052519438 | H11: ='Dividend Yield'!H11+'Capital Gain'!H11 -> 0.041666667 | I11: ='Dividend Yield'!I11+'Capital Gain'!I11 -> 0.011870219 | J11: ='Dividend Yield'!J11+'Capital Gain'!J11 -> -0.083333333 | ... V11: ='Dividend Yield'!V11+'Capital Gain'!V11 -> 0.026960784
B12: May | C12: ='Dividend Yield'!C12+'Capital Gain'!C12 -> -0.10643564 | D12: ='Dividend Yield'!D12+'Capital Gain'!D12 -> 0 | E12: ='Dividend Yield'!E12+'Capital Gain'!E12 -> -0.07547518 | F12: ='Dividend Yield'!F12+'Capital Gain'!F12 -> -0.063253012 | G12: ='Dividend Yield'!G12+'Capital Gain'!G12 -> -0.15411559 | H12: ='Dividend Yield'!H12+'Capital Gain'!H12 -> -0.062709223 | I12: ='Dividend Yield'!I12+'Capital Gain'!I12 -> 0 | J12: ='Dividend Yield'!J12+'Capital Gain'!J12 -> 0.009569378 | ... V12: ='Dividend Yield'!V12+'Capital Gain'!V12 -> 0
B13: June | C13: ='Dividend Yield'!C13+'Capital Gain'!C13 -> 0.0096952909 | D13: ='Dividend Yield'!D13+'Capital Gain'!D13 -> 0.043333333 | E13: ='Dividend Yield'!E13+'Capital Gain'!E13 -> 0.0017964072 | F13: ='Dividend Yield'!F13+'Capital Gain'!F13 -> -0.001607717 | G13: ='Dividend Yield'!G13+'Capital Gain'!G13 -> 0.072463768 | H13: ='Dividend Yield'!H13+'Capital Gain'!H13 -> -0.011560694 | I13: ='Dividend Yield'!I13+'Capital Gain'!I13 -> -0.0070385819 | J13: ='Dividend Yield'!J13+'Capital Gain'!J13 -> 0.071090047 | ... V13: ='Dividend Yield'!V13+'Capital Gain'!V13 -> 0.057279236
B14: July | C14: ='Dividend Yield'!C14+'Capital Gain'!C14 -> -0.069958848 | D14: ='Dividend Yield'!D14+'Capital Gain'!D14 -> -0.041666667 | E14: ='Dividend Yield'!E14+'Capital Gain'!E14 -> 0.094839609 | F14: ='Dividend Yield'!F14+'Capital Gain'!F14 -> -0.049919485 | G14: ='Dividend Yield'!G14+'Capital Gain'!G14 -> -0.027027027 | H14: ='Dividend Yield'!H14+'Capital Gain'!H14 -> -0.068226121 | I14: ='Dividend Yield'!I14+'Capital Gain'!I14 -> -0.090574954 | J14: ='Dividend Yield'!J14+'Capital Gain'!J14 -> -0.019911504 | ... V14: ='Dividend Yield'!V14+'Capital Gain'!V14 -> -0.046839729
B15: August | C15: ='Dividend Yield'!C15+'Capital Gain'!C15 -> 0 | D15: ='Dividend Yield'!D15+'Capital Gain'!D15 -> 0.02173913 | E15: ='Dividend Yield'!E15+'Capital Gain'!E15 -> 0.18544131 | F15: ='Dividend Yield'!F15+'Capital Gain'!F15 -> 0.061016949 | G15: ='Dividend Yield'!G15+'Capital Gain'!G15 -> -0.035714286 | H15: ='Dividend Yield'!H15+'Capital Gain'!H15 -> 0.039748954 | I15: ='Dividend Yield'!I15+'Capital Gain'!I15 -> 0.091801386 | J15: ='Dividend Yield'!J15+'Capital Gain'!J15 -> 0.19187359 | ... V15: ='Dividend Yield'!V15+'Capital Gain'!V15 -> 0.007696862
B16: September | C16: ='Dividend Yield'!C16+'Capital Gain'!C16 -> -0.0025811209 | D16: ='Dividend Yield'!D16+'Capital Gain'!D16 -> -0.021276596 | E16: ='Dividend Yield'!E16+'Capital Gain'!E16 -> -0.027786306 | F16: ='Dividend Yield'!F16+'Capital Gain'!F16 -> -0.076677316 | G16: ='Dividend Yield'!G16+'Capital Gain'!G16 -> -0.043209877 | H16: ='Dividend Yield'!H16+'Capital Gain'!H16 -> -0.072434608 | I16: ='Dividend Yield'!I16+'Capital Gain'!I16 -> 0.019301957 | J16: ='Dividend Yield'!J16+'Capital Gain'!J16 -> 0.12878788 | ... V16: ='Dividend Yield'!V16+'Capital Gain'!V16 -> -0.016451234
B17: October | C17: ='Dividend Yield'!C17+'Capital Gain'!C17 -> 0 | D17: ='Dividend Yield'!D17+'Capital Gain'!D17 -> 0 | E17: ='Dividend Yield'!E17+'Capital Gain'!E17 -> -0.13374388 | F17: ='Dividend Yield'!F17+'Capital Gain'!F17 -> 0 | G17: ='Dividend Yield'!G17+'Capital Gain'!G17 -> 0 | H17: ='Dividend Yield'!H17+'Capital Gain'!H17 -> -0.036876356 | I17: ='Dividend Yield'!I17+'Capital Gain'!I17 -> -0.061478599 | J17: ='Dividend Yield'!J17+'Capital Gain'!J17 -> 0.048657718 | ... V17: ='Dividend Yield'!V17+'Capital Gain'!V17 -> 0.00059737157
B18: November | C18: ='Dividend Yield'!C18+'Capital Gain'!C18 -> 0 | D18: ='Dividend Yield'!D18+'Capital Gain'!D18 -> 0 | E18: ='Dividend Yield'!E18+'Capital Gain'!E18 -> 0 | F18: ='Dividend Yield'!F18+'Capital Gain'!F18 -> 0 | G18: ='Dividend Yield'!G18+'Capital Gain'!G18 -> 0 | H18: ='Dividend Yield'!H18+'Capital Gain'!H18 -> -0.018018018 | I18: ='Dividend Yield'!I18+'Capital Gain'!I18 -> -0.012983382 | J18: ='Dividend Yield'!J18+'Capital Gain'!J18 -> -0.06622268 | ... V18: ='Dividend Yield'!V18+'Capital Gain'!V18 -> 0.0089552239
B19: December | C19: ='Dividend Yield'!C19+'Capital Gain'!C19 -> 0 | D19: ='Dividend Yield'!D19+'Capital Gain'!D19 -> 0 | E19: ='Dividend Yield'!E19+'Capital Gain'!E19 -> 0 | F19: ='Dividend Yield'!F19+'Capital Gain'!F19 -> 0 | G19: ='Dividend Yield'!G19+'Capital Gain'!G19 -> -0.043010753 | H19: ='Dividend Yield'!H19+'Capital Gain'!H19 -> -0.04587156 | I19: ='Dividend Yield'!I19+'Capital Gain'!I19 -> 0 | J19: ='Dividend Yield'!J19+'Capital Gain'!J19 -> 0.025773196 | ... V19: ='Dividend Yield'!V19+'Capital Gain'!V19 -> 0.061668264
A20: 2023 | B20: January | C20: ='Dividend Yield'!C20+'Capital Gain'!C20 -> 0 | D20: ='Dividend Yield'!D20+'Capital Gain'!D20 -> 0 | E20: ='Dividend Yield'!E20+'Capital Gain'!E20 -> 0 | F20: ='Dividend Yield'!F20+'Capital Gain'!F20 -> 0 | G20: ='Dividend Yield'!G20+'Capital Gain'!G20 -> -0.02247191 | H20: ='Dividend Yield'!H20+'Capital Gain'!H20 -> 0.15144231 | I20: ='Dividend Yield'!I20+'Capital Gain'!I20 -> 0 | J20: ='Dividend Yield'!J20+'Capital Gain'!J20 -> -0.033500838 | ... V20: ='Dividend Yield'!V20+'Capital Gain'!V20 -> 0.016138673
B21: February | C21: ='Dividend Yield'!C21+'Capital Gain'!C21 -> 0 | D21: ='Dividend Yield'!D21+'Capital Gain'!D21 -> 0 | E21: ='Dividend Yield'!E21+'Capital Gain'!E21 -> 0 | F21: ='Dividend Yield'!F21+'Capital Gain'!F21 -> 0 | G21: ='Dividend Yield'!G21+'Capital Gain'!G21 -> -0.11724138 | H21: ='Dividend Yield'!H21+'Capital Gain'!H21 -> -0.083507307 | I21: ='Dividend Yield'!I21+'Capital Gain'!I21 -> 0 | J21: ='Dividend Yield'!J21+'Capital Gain'!J21 -> 0.065857886 | ... V21: ='Dividend Yield'!V21+'Capital Gain'!V21 -> 0
B22: March | C22: ='Dividend Yield'!C22+'Capital Gain'!C22 -> 0 | D22: ='Dividend Yield'!D22+'Capital Gain'!D22 -> 0 | E22: ='Dividend Yield'!E22+'Capital Gain'!E22 -> 0.018228217 | F22: ='Dividend Yield'!F22+'Capital Gain'!F22 -> 0 | G22: ='Dividend Yield'!G22+'Capital Gain'!G22 -> 0 | H22: ='Dividend Yield'!H22+'Capital Gain'!H22 -> -0.006833713 | I22: ='Dividend Yield'!I22+'Capital Gain'!I22 -> 0 | J22: ='Dividend Yield'!J22+'Capital Gain'!J22 -> 0.17398374 | ... V22: ='Dividend Yield'!V22+'Capital Gain'!V22 -> 0.05
B23: April | C23: ='Dividend Yield'!C23+'Capital Gain'!C23 -> 0 | D23: ='Dividend Yield'!D23+'Capital Gain'!D23 -> 0 | E23: ='Dividend Yield'!E23+'Capital Gain'!E23 -> 0 | F23: ='Dividend Yield'!F23+'Capital Gain'!F23 -> 0.027043262 | G23: ='Dividend Yield'!G23+'Capital Gain'!G23 -> 0 | H23: ='Dividend Yield'!H23+'Capital Gain'!H23 -> 0.027522936 | I23: ='Dividend Yield'!I23+'Capital Gain'!I23 -> 0 | J23: ='Dividend Yield'!J23+'Capital Gain'!J23 -> -0.011080332 | ... V23: ='Dividend Yield'!V23+'Capital Gain'!V23 -> 0.02464986
B24: May | C24: ='Dividend Yield'!C24+'Capital Gain'!C24 -> 0.029698315 | D24: ='Dividend Yield'!D24+'Capital Gain'!D24 -> 0 | E24: ='Dividend Yield'!E24+'Capital Gain'!E24 -> 0 | F24: ='Dividend Yield'!F24+'Capital Gain'!F24 -> 0 | G24: ='Dividend Yield'!G24+'Capital Gain'!G24 -> 0.52508366 | H24: ='Dividend Yield'!H24+'Capital Gain'!H24 -> 0.25276883 | I24: ='Dividend Yield'!I24+'Capital Gain'!I24 -> 0 | J24: ='Dividend Yield'!J24+'Capital Gain'!J24 -> 0.29971989 | ... V24: ='Dividend Yield'!V24+'Capital Gain'!V24 -> -0.010934937
B25: June | C25: ='Dividend Yield'!C25+'Capital Gain'!C25 -> 0 | D25: ='Dividend Yield'!D25+'Capital Gain'!D25 -> 0.034907069 | E25: ='Dividend Yield'!E25+'Capital Gain'!E25 -> 0 | F25: ='Dividend Yield'!F25+'Capital Gain'!F25 -> 0 | G25: ='Dividend Yield'!G25+'Capital Gain'!G25 -> -0.16580311 | H25: ='Dividend Yield'!H25+'Capital Gain'!H25 -> -0.11111111 | I25: ='Dividend Yield'!I25+'Capital Gain'!I25 -> 0 | J25: ='Dividend Yield'!J25+'Capital Gain'!J25 -> 0.26831897 | ... V25: ='Dividend Yield'!V25+'Capital Gain'!V25 -> -0.005527916
B26: July | C26: ='Dividend Yield'!C26+'Capital Gain'!C26 -> 0 | D26: ='Dividend Yield'!D26+'Capital Gain'!D26 -> 0 | E26: ='Dividend Yield'!E26+'Capital Gain'!E26 -> 0 | F26: ='Dividend Yield'!F26+'Capital Gain'!F26 -> 0 | G26: ='Dividend Yield'!G26+'Capital Gain'!G26 -> -0.082815735 | H26: ='Dividend Yield'!H26+'Capital Gain'!H26 -> 0.26844262 | I26: ='Dividend Yield'!I26+'Capital Gain'!I26 -> 0 | J26: ='Dividend Yield'!J26+'Capital Gain'!J26 -> 0.050127443 | ... V26: ='Dividend Yield'!V26+'Capital Gain'!V26 -> -0.013340745
B27: August | C27: ='Dividend Yield'!C27+'Capital Gain'!C27 -> 0 | D27: ='Dividend Yield'!D27+'Capital Gain'!D27 -> 0 | E27: ='Dividend Yield'!E27+'Capital Gain'!E27 -> 0 | F27: ='Dividend Yield'!F27+'Capital Gain'!F27 -> 0 | G27: ='Dividend Yield'!G27+'Capital Gain'!G27 -> -0.060948081 | H27: ='Dividend Yield'!H27+'Capital Gain'!H27 -> -0.082390953 | I27: ='Dividend Yield'!I27+'Capital Gain'!I27 -> 0 | J27: ='Dividend Yield'!J27+'Capital Gain'!J27 -> -0.0056634304 | ... V27: ='Dividend Yield'!V27+'Capital Gain'!V27 -> -0.0056338028
B28: September | C28: ='Dividend Yield'!C28+'Capital Gain'!C28 -> 0 | D28: ='Dividend Yield'!D28+'Capital Gain'!D28 -> 0 | E28: ='Dividend Yield'!E28+'Capital Gain'!E28 -> 0 | F28: ='Dividend Yield'!F28+'Capital Gain'!F28 -> 0 | G28: ='Dividend Yield'!G28+'Capital Gain'!G28 -> 0.70913462 | H28: ='Dividend Yield'!H28+'Capital Gain'!H28 -> 0.080985915 | I28: ='Dividend Yield'!I28+'Capital Gain'!I28 -> 0 | J28: ='Dividend Yield'!J28+'Capital Gain'!J28 -> -0.039869813 | ... V28: ='Dividend Yield'!V28+'Capital Gain'!V28 -> 0.0033994334
B29: October | C29: ='Dividend Yield'!C29+'Capital Gain'!C29 -> 0 | D29: ='Dividend Yield'!D29+'Capital Gain'!D29 -> 0 | E29: ='Dividend Yield'!E29+'Capital Gain'!E29 -> 0 | F29: ='Dividend Yield'!F29+'Capital Gain'!F29 -> 0 | G29: ='Dividend Yield'!G29+'Capital Gain'!G29 -> -0.17580872 | H29: ='Dividend Yield'!H29+'Capital Gain'!H29 -> -0.13680782 | I29: ='Dividend Yield'!I29+'Capital Gain'!I29 -> 0 | J29: ='Dividend Yield'!J29+'Capital Gain'!J29 -> 0.077118644 | ... V29: ='Dividend Yield'!V29+'Capital Gain'!V29 -> 0.0033879164
B30: November | C30: ='Dividend Yield'!C30+'Capital Gain'!C30 -> 0 | D30: ='Dividend Yield'!D30+'Capital Gain'!D30 -> 0 | E30: ='Dividend Yield'!E30+'Capital Gain'!E30 -> 0 | F30: ='Dividend Yield'!F30+'Capital Gain'!F30 -> 0 | G30: ='Dividend Yield'!G30+'Capital Gain'!G30 -> -0.087030717 | H30: ='Dividend Yield'!H30+'Capital Gain'!H30 -> -0.043396226 | I30: ='Dividend Yield'!I30+'Capital Gain'!I30 -> 0.029027576 | J30: ='Dividend Yield'!J30+'Capital Gain'!J30 -> -0.032813713 | ... V30: ='Dividend Yield'!V30+'Capital Gain'!V30 -> 0.0005627462
B31: December | C31: ='Dividend Yield'!C31+'Capital Gain'!C31 -> 0 | D31: ='Dividend Yield'!D31+'Capital Gain'!D31 -> 0 | E31: ='Dividend Yield'!E31+'Capital Gain'!E31 -> 0 | F31: ='Dividend Yield'!F31+'Capital Gain'!F31 -> 0 | G31: ='Dividend Yield'!G31+'Capital Gain'!G31 -> 0.061682243 | H31: ='Dividend Yield'!H31+'Capital Gain'!H31 -> -0.01183432 | I31: ='Dividend Yield'!I31+'Capital Gain'!I31 -> 0 | J31: ='Dividend Yield'!J31+'Capital Gain'!J31 -> 0.090390879 | ... V31: ='Dividend Yield'!V31+'Capital Gain'!V31 -> 0.024845374
A32: 2024 | B32: January | C32: ='Dividend Yield'!C32+'Capital Gain'!C32 -> 0.052861685 | D32: ='Dividend Yield'!D32+'Capital Gain'!D32 -> -0.10687023 | E32: ='Dividend Yield'!E32+'Capital Gain'!E32 -> -0.4549763 | F32: ='Dividend Yield'!F32+'Capital Gain'!F32 -> -0.1340388 | G32: ='Dividend Yield'!G32+'Capital Gain'!G32 -> 0.029929577 | H32: ='Dividend Yield'!H32+'Capital Gain'!H32 -> 0.01996008 | I32: ='Dividend Yield'!I32+'Capital Gain'!I32 -> -0.13701016 | J32: ='Dividend Yield'!J32+'Capital Gain'!J32 -> -0.0059746079 | ... V32: ='Dividend Yield'!V32+'Capital Gain'!V32 -> 0.0083086053
B33: February | C33: ='Dividend Yield'!C33+'Capital Gain'!C33 -> 0.13250283 | D33: ='Dividend Yield'!D33+'Capital Gain'!D33 -> 0.017094017 | E33: ='Dividend Yield'!E33+'Capital Gain'!E33 -> 0.025752508 | F33: ='Dividend Yield'!F33+'Capital Gain'!F33 -> -0.042769857 | G33: ='Dividend Yield'!G33+'Capital Gain'!G33 -> -0.066666667 | H33: ='Dividend Yield'!H33+'Capital Gain'!H33 -> -0.019569472 | I33: ='Dividend Yield'!I33+'Capital Gain'!I33 -> 0.46787756 | J33: ='Dividend Yield'!J33+'Capital Gain'!J33 -> 0.19534185 | ... V33: ='Dividend Yield'!V33+'Capital Gain'!V33 -> 0.02707475
B34: March | C34: ='Dividend Yield'!C34+'Capital Gain'!C34 -> -0.058333333 | D34: ='Dividend Yield'!D34+'Capital Gain'!D34 -> 0 | E34: ='Dividend Yield'!E34+'Capital Gain'!E34 -> -0.15226606 | F34: ='Dividend Yield'!F34+'Capital Gain'!F34 -> -0.13191489 | G34: ='Dividend Yield'!G34+'Capital Gain'!G34 -> 0 | H34: ='Dividend Yield'!H34+'Capital Gain'!H34 -> -0.099800399 | I34: ='Dividend Yield'!I34+'Capital Gain'!I34 -> 0.13748854 | J34: ='Dividend Yield'!J34+'Capital Gain'!J34 -> 0.11879321 | ... V34: ='Dividend Yield'!V34+'Capital Gain'!V34 -> -0.0068767908
B35: April | C35: ='Dividend Yield'!C35+'Capital Gain'!C35 -> -0.037522124 | D35: ='Dividend Yield'!D35+'Capital Gain'!D35 -> 0 | E35: ='Dividend Yield'!E35+'Capital Gain'!E35 -> -0.13753061 | F35: ='Dividend Yield'!F35+'Capital Gain'!F35 -> -0.050255008 | G35: ='Dividend Yield'!G35+'Capital Gain'!G35 -> 0.064102564 | H35: ='Dividend Yield'!H35+'Capital Gain'!H35 -> -0.042128603 | I35: ='Dividend Yield'!I35+'Capital Gain'!I35 -> 0.45950846 | J35: ='Dividend Yield'!J35+'Capital Gain'!J35 -> -0.0011235955 | ... V35: ='Dividend Yield'!V35+'Capital Gain'!V35 -> 0.0069244085
B36: May | C36: ='Dividend Yield'!C36+'Capital Gain'!C36 -> 0.092267819 | D36: ='Dividend Yield'!D36+'Capital Gain'!D36 -> 0.033613445 | E36: ='Dividend Yield'!E36+'Capital Gain'!E36 -> -0.096339114 | F36: ='Dividend Yield'!F36+'Capital Gain'!F36 -> -0.1212938 | G36: ='Dividend Yield'!G36+'Capital Gain'!G36 -> -0.041925946 | H36: ='Dividend Yield'!H36+'Capital Gain'!H36 -> -0.059743427 | I36: ='Dividend Yield'!I36+'Capital Gain'!I36 -> 0.090407177 | J36: ='Dividend Yield'!J36+'Capital Gain'!J36 -> -0.067491564 | ... V36: ='Dividend Yield'!V36+'Capital Gain'!V36 -> -0.0252149
B37: June | C37: ='Dividend Yield'!C37+'Capital Gain'!C37 -> 0.017658349 | D37: ='Dividend Yield'!D37+'Capital Gain'!D37 -> -0.080803053 | E37: ='Dividend Yield'!E37+'Capital Gain'!E37 -> -0.055970149 | F37: ='Dividend Yield'!F37+'Capital Gain'!F37 -> -0.027607362 | G37: ='Dividend Yield'!G37+'Capital Gain'!G37 -> -0.023809524 | H37: ='Dividend Yield'!H37+'Capital Gain'!H37 -> 0.015267176 | I37: ='Dividend Yield'!I37+'Capital Gain'!I37 -> -0.0034177215 | J37: ='Dividend Yield'!J37+'Capital Gain'!J37 -> -0.0042219542 | ... V37: ='Dividend Yield'!V37+'Capital Gain'!V37 -> 0.026455026
